Workbook

Sheet PnL_upd 28 июл
G1: Комментарии
B2: Период расчета в модели: год | C2: Вариант 1 | E2: Вариант 2.1 | G2: NEW. В модели учтено получение комиссии Т - только от первых оплат МПСтатс + сокращены расходы Т на маркетинг
C3: Биллинг Т | E3: Биллинг МПС (с рекуррентами и ковенантами)
A4: Доходы: Тарифы MPStats оплачены клиентами | B4: Клиентский доход (тарифы МПСтатс) - от всей базы селлеров (~12 мес) | C4: =Воронка!R44 -> 1.4127074e+08 | E4: =C4 -> 1.4127074e+08
B5: Клиентский доход (тарифы МПСтатс) - 6 мес (неактуально) | C5: ='период вознаграждения'!G6 -> 1.3907468e+08 | E5: =C5 -> 1.3907468e+08
B6: Клиентский доход (тарифы МПСтатс) - 3 мес (неактуально) | C6: ='период вознаграждения'!M6 -> 73059219 | E6: =C6 -> 73059219
B7: Клиентский доход (тарифы МПСтатс) - первая оплата (на разн. кол-во мес) | C7: ='период вознаграждения'!T6 -> 84930192 | E7: =C7 -> 84930192 | G7: NEW. Upd - 27 июля - прогноз первых оплат - по ср чеку первой оплаты от МПС после обнолвения тарифов (в начале июня) - 84 930 192 руб - применила этот вариант, более точно
B9: Расходы Т-Банк
B10: Договор 1 (лицензия + техподдержка ПО МПСтатс)
B11: услуги по договору | C11: лицензия + техподдержка | E11: лицензия + техподдержка
A12: Договор 1 (лицензия и тех поддержка со стороны МПСтатс) | B12: Лицензия на ПО MPStats (ежегодно) | C12: 396000 | E12: =C12 -> 396000 | G12: NEW - Стоимость от МПСтатс - 396 000 руб. Отправить расчет лицензии налоговикам - спарвочно, чтобы была инофрмация по запросу. Оплата ежегоднго. Провалидировать с налогами и юристами - ОК.
A13: Лицензия на ПО MPStats -- какая минимально возможная? (единоразово бессрочно) | B13: Тех. поддержка ПО MPStats (в год) | C13: ='доп расходы_свод'!C17 -> 360000 | E13: =C13 -> 360000 | G13: по расчету МПС
A14: Тех. поддержка интеграции в целом от MPStats (в год) | B14: ИТОГО по Договору 1 | C14: =C12+C13 -> 756000 | E14: =E12+E13 -> 756000 | G14: Доход для МПС, расход для Т
B15: доля от клиентского дохода MPStats | C15: =C14/C$4 -> 0.0053514265 | E15: =E14/E$4 -> 0.0053514265
B16: Договор 2 (биллинг + лидген)
B17: услуги по договору | C17: биллинг + техподдержка + лидогенерация Т | E17: лидогенерация + техподдержка Т
A18: Расходы на привлечение Т-Банк | B18: 1. Расходы на привлечение Т-Банк | C18: =SUM(C19:C21) -> 4046442.6 | E18: =SUM(E19:E21) -> 4046442.6
A19: Расходы на внутренний маркетинг (запуск 6 кампаний) | B19: Расходы на внутренний маркетинг | C19: ='расходы для PnL'!B3/6*2 -> 1500000 | E19: ='расходы для PnL'!C3/6*2 -> 1500000 | G19: скоратили косты на маркетинг - запуск 2 кампаний
A20: Расходы на внешний маркетинг (медиа, тг) | B20: Расходы на внешний маркетинг | C20: ='расходы для PnL'!B4 -> 1500000 | E20: ='расходы для PnL'!C4 -> 1500000 | G20: медиа, ТГ
A21: Расходы на API запросы к маркетплейсам на время триал (бесплатная версия полного продуката MPStats на 14 дней) | B21: Расходы на API запросы к маркетплейсам на время триал | C21: ='расходы для PnL'!B5 -> 1046442.6 | E21: ='расходы для PnL'!C5 -> 1046442.6 | G21: Т несет расходы в период пользования клиентами продуката MPStats - триал на 14 дней (возможно затраты будут меньше, если кол-во дней триала меньше)
A22: Расходы на биллинг Т-Банк | B22: 2. Расходы на биллинг Т-Банк | C22: =SUM(C23:C25) -> 3072857.1 | E22: =SUM(E23:E25) -> 500000
A23: Разработка Биллинга от Т-Банк | B23: Разработка Биллинга от Т-Банк | C23: ='расходы для PnL'!B7 -> 1800000 | E23: ='расходы для PnL'!C7 -> 500000
A24: Бухгалтерское сопровождение биллинга | B24: Бухгалтерское сопровождение биллинга | C24: ='расходы для PnL'!B8 -> 0 | E24: ='расходы для PnL'!C8 -> 0 | G24: нет данных для расчета
B25: Техподдержка биллинг | C25: ='расходы для PnL'!B9 -> 1272857.1
A26: Тех. поддержка интеграции в целом от Т-Банк | B26: 3. Техподдержка Т-банк интеграции | C26: ='расходы для PnL'!B10 -> 1272857.1 | E26: ='расходы для PnL'!C10 -> 1272857.1
A27: Расходы на запросы к API Т-Банк (необходимо для базовой работы сервиса) | B27: 4. Расходы на запросы к API Т-Банк | C27: ='расходы для PnL'!B11 -> 7956567.1 | E27: ='расходы для PnL'!C11 -> 7956567.1 | G27: необходимо для базовой работы сервиса
B28: ИТОГО расходы Т | C28: =SUM(C18,C22,C26,C27) -> 16348724 | E28: =SUM(E18,E22,E26,E27) -> 13775867
B29: маржа Т поверх расходов | C29: 0.15 | E29: 0.16 | G29: 10% - мин.требование налогов Т для рыночности сделки
B31: Стоимость для договора 2 (калькуляция от затрат + маржа)
B32: Биллинг | C32: =C22*(1+C$29) -> 3533785.7 | E32: 0 | G32: разработка+интеграция +маржа Т
B33: доля от клиентского дохода MPStats (бессрочно) | C33: =C32/C$4 -> 0.025014279 | E33: =E32/E$4 -> 0
B34: Лидогенерация Т (вкл расходы техподдержка Т + API) | C34: =(C18+C26+C27)*(1+C$29) -> 15267247 | E34: =(E18+E26+E27+E22)*(1+E$29) -> 15980006 | G34: внешний/внутренний маркетинг Т + расходы на API/техподдержку +маржа 10%
B35: % от клиентского дохода (12 мес) - неактуально | C35: =C$34/C4 -> 0.10807083 | E35: =E$34/E4 -> 0.11311617
B36: % от клиентского дохода (6 мес) - неактуально | C36: =C$34/C5 -> 0.10977733 | E36: =E$34/E5 -> 0.11490234
B37: % от клиентского дохода (3 мес) - неактуально | C37: =C$34/C6 -> 0.20897085 | E37: =E$34/E6 -> 0.21872675
B38: % от клиентского дохода (первая оплата) | C38: =C$34/C7 -> 0.1797623 | E38: =E$34/E7 -> 0.18815459
B39: ИТОГО по Договору 2 (расчет 1: расходы Т+ маржа) | C39: =C32+C34 -> 18801033 | E39: =E32+E34 -> 15980006 | G39: Доход для Т, расход для МПС
B40: % от клиентского дохода (12 мес) | C40: =C39/C4 -> 0.13308511 | E40: =E39/E4 -> 0.11311617
B42: Стоимость для договора 2 (калькуляция от клиентских доходов)
B43: Биллинг Т | C43: =C$4*C47 -> 3533785.7 | E43: =E$4*E47 -> 0
B44: Лидогенерация Т | C44: =C$4*C48 -> 15267247 | E44: =E$4*E48 -> 15980006
B45: ИТОГО по Договору 2 (расчет 2: флэт % от клиентского дохода) | C45: =C43+C44 -> 18801033 | E45: =E43+E44 -> 15980006 | G45: Доход для Т, расход для МПС
B46: Расчет от доли клиентского дохода MPStats | C46: =C45/C4 -> 0.13308511 | E46: =E47+E48 -> 0.11311617
B47: % биллинг | C47: =C33 -> 0.025014279 | E47: =E33 -> 0
B48: % лидген (вкл расходы: привлечение, техподдержка, запросы API) | C48: =C35 -> 0.10807083 | E48: =E35 -> 0.11311617
G49: похожий договор Мпстаст - Партнер (получает 15-30%) - но это не МПС, а Точка
B50: P&L для сторон | C50: Биллинг Т | E50: Биллинг МПС (с рекуррентами и ковенантами) | K50: 1 | L50: 1 - от расходов Т + маржа; 2 - от требуемой доходности Т
B51: МПСтатс
B52: Доходы | C52: =SUM(C53:C54) -> 1.4202674e+08 | E52: =SUM(E53:E54) -> 1.4202674e+08
B53: Доход с клиентов (тарифы МПСтатс) | C53: =C4 -> 1.4127074e+08 | E53: =E4 -> 1.4127074e+08 | G53: без НДС (льгота для ИТ компаний)
B54: Договор 1 (лицензия + тех поддержка МПСтатс) | C54: =C14 -> 756000 | E54: =E14 -> 756000 | G54: лицензция – без НДС (льгота для ИТ компаний); тех поддержка – с НДС.
B56: Расходы | C56: =SUM(C57:C61) -> 77938038 | E56: =SUM(E57:E61) -> 70941011
B57: Sales команда МПСтатс | C57: ='расходы для PnL'!B14 -> 50425005 | E57: ='расходы для PnL'!C14 -> 50425005
B58: Договор 2 (биллинг Т) | C58: =CHOOSE($K$50,C32,C43) -> 3533785.7 | E58: =CHOOSE($K$50,E32,E43) -> 0 | G58: НДС 22% к стоимости услуг по Дог.2. Т-Банк начисляет НДС, уплачивает его в бюджет. МПСтатс оплачивают счет от нас с учетом НДС и принимают к себе в зачет эту сумму
B59: Договор 2 (лидген Т) | C59: =CHOOSE($K$50,C34,C44) -> 15267247 | E59: =CHOOSE($K$50,E34,E44) -> 15980006
B60: Техподдержка интеграции МПСтатс | C60: ='расходы для PnL'!B15 -> 360000 | E60: ='расходы для PnL'!C15 -> 360000
B61: Техподдержка пользователей МПСтатс | C61: ='расходы для PnL'!B16 -> 8352000 | E61: ='расходы для PnL'!C16 -> 4176000
B63: Прибыль МПС от МПСтатс (за вычетом всех расходов) | C63: =C52-C56 -> 64088705 | E63: =E52-E56 -> 71085732
B64: маржинальность по проекту для МПС (прибыль/доходы) | C64: =C63/C52 -> 0.45124392 | E64: =E63/E52 -> 0.50050948
B65: Прибыль МПС от клиентского дохода МПСтатс (за вычетом лидгена Т) | C65: =C53-C59 -> 1.260035e+08 | E65: =E53-E59 -> 1.2529074e+08
B66: доля от клиентского дохода MPStats | C66: =C65/C4 -> 0.89192917 | E66: =E65/E4 -> 0.88688383 | G66: Вознаграждение МПСтатс за вычетом комиссии Т-Банк за лидген+ биллинг/ только лидген.
B68: Справочно: налоги МПС
B69: НДС 22% – тех поддержка по Договору 1 | C69: =C13*22% -> 79200 | E69: =E13*22% -> 79200
B70: Налог на прибыль 5% (льгота для ИТ компаний) | C70: =C63*5% -> 3204435.2 | E70: =E63*5% -> 3554286.6
B71: Разница налог на прибыль | C71: =C70-E70 -> -349851.35
B73: Т-Банк
B74: Доходы | C74: =SUM(C75:C77) -> 18801033 | E74: =SUM(E75:E77) -> 15980006
B75: Доход с клиентов (тарифы МПСтатс)
B76: Договор 2 (биллинг Т) | C76: =C58 -> 3533785.7 | E76: =E58 -> 0 | G76: НДС 22% к стоимости услуг по Дог.2. Т-Банк начисляет НДС, уплачивает его в бюджет. МПСтатс оплачивают счет от нас с учетом НДС и принимают к себе в зачет эту сумму
B77: Договор 2 (лидген Т) | C77: =C59 -> 15267247 | E77: =E59 -> 15980006
B79: Расходы | C79: =SUM(C80:C82) -> 17104724 | E79: =SUM(E80:E82) -> 14531867
B80: Договор 1 (лицензия + тех поддержка МПСтатс) | C80: =C54 -> 756000 | E80: =E54 -> 756000
B81: Договор 2 (биллинг Т) | C81: =C22 -> 3072857.1 | E81: 0
B82: Договор 2 (лидген Т + тех поддержка + API) | C82: =C18+C26+C27 -> 13275867 | E82: =E18+E26+E27+E22 -> 13775867
B84: Прибыль Т от МПСтатс | C84: =C74-C79 -> 1696308.6 | E84: =E74-E79 -> 1448138.7
B85: маржинальность по проекту для Т (прибыль/доходы) | C85: =C84/C74 -> 0.090224225 | E85: =E84/E74 -> 0.090621915
B86: доля от клиентского дохода MPStats | C86: =C84/C$4 -> 0.012007501 | E86: =E84/E$4 -> 0.010250804
B87: маржинальность как доля прибыли Т к расходам (от налоговиков) | C87: =C84/C79 -> 0.099171936 | E87: =E84/E79 -> 0.099652626 | G87: 10% - мин.требование налогов Т для рыночности сделки
B89: Потенциальная прибыль Т по другим продуктам | C89: =Воронка!R77 -> 1.1041509e+08 | E89: =C89 -> 1.1041509e+08
B90: Общая прибыль Т (MPStats + экосистемный эффект) | C90: =C84+C89 -> 1.121114e+08 | E90: =E84+E89 -> 1.1186323e+08
B92: Справочно: налоги Т-Банк
B93: НДС 22% (в доходах по Договору 2) | C93: =(C76+C77)*22% -> 4136227.2 | E93: =(E76+E77)*22% -> 3515601.2 | G93: НДС 22% к стоимости услуг по Дог.2. Т-Банк начисляет НДС, уплачивает его в бюджет. МПСтатс оплачивают счет от нас с учетом НДС и НЕ принимают к себе в зачет эту сумму (инфо от МПС что не смогут в зачет). ?? Уточнить с налогами последствия по НДС для МПС (большую часть выручки не облагают НДС => не смогут принять к вычету НДС по договору с Т?) --- - Будут платить НДС
B94: Налог на прибыль 25% | C94: =C84*25% -> 424077.15 | E94: =E84*25% -> 362034.68
B95: Разница налог на прибыль | C95: =C94-E94 -> 62042.476
B97: P&L Total | C97: Биллинг Т | E97: Биллинг МПС (с рекуррентами и ковенантами)
B98: ИТОГО: МПС + Т-Банк
B99: Доходы | C99: =C100+C103 -> 1.6082778e+08 | E99: =E100+E103 -> 1.5800675e+08
B100: МПС | C100: =SUM(C101:C102) -> 1.4202674e+08 | E100: =SUM(E101:E102) -> 1.4202674e+08
B101: Доход с клиентов (тарифы МПСтатс) | C101: =C53 -> 1.4127074e+08 | E101: =E53 -> 1.4127074e+08 | G101: доход МПС
B102: Договор 1 (лицензия + тех поддержка МПСтатс) | C102: =C54 -> 756000 | E102: =E54 -> 756000 | G102: доход МПС, расход Т
B103: Т-Банк | C103: =C104+C105 -> 18801033 | E103: =E104+E105 -> 15980006
B104: Договор 2 (биллинг Т) | C104: =C58 -> 3533785.7 | E104: =E58 -> 0 | G104: доход Т-Банк, расход МПС
B105: Договор 2 (лидген Т) | C105: =C59 -> 15267247 | E105: =E59 -> 15980006
B107: Расходы | C107: =C108+C114 -> 95042762 | E107: =E108+E114 -> 85472878
B108: МПС | C108: =SUM(C109:C113) -> 77938038 | E108: =SUM(E109:E113) -> 70941011
B109: =B57 -> Sales команда МПСтатс | C109: =C57 -> 50425005 | E109: =E57 -> 50425005
B110: Договор 2 (биллинг Т) | C110: =C58 -> 3533785.7 | E110: =E58 -> 0 | G110: оплата Т за биллинг
B111: Договор 2 (лидген Т) | C111: =C59 -> 15267247 | E111: =E59 -> 15980006 | G111: оплата Т за лидген
B112: Техподдержка интеграции МПСтатс | C112: =C60 -> 360000 | E112: =E60 -> 360000
B113: Техподдержка пользователей МПСтатс | C113: =C61 -> 8352000 | E113: =E61 -> 4176000
...

Sheet ИТОГ_new v4_первые оплаты
G1: Комментарии
B2: Период расчета в модели: год | C2: Вариант 1 | E2: Вариант 2.1 | G2: NEW. В модели учтено получение комиссии Т - от первых оплат МПСтатс
C3: Биллинг Т | E3: Биллинг МПС (с рекуррентами и ковенантами)
A4: Доходы: Тарифы MPStats оплачены клиентами | B4: Клиентский доход (тарифы МПСтатс) - от всей базы селлеров (~12 мес) | C4: =Воронка!#REF! -> #REF! | E4: =Воронка!#REF! -> #REF!
B5: Клиентский доход (тарифы МПСтатс) - 6 мес | C5: ='период вознаграждения'!G6 -> 1.3907468e+08 | E5: =C5 -> 1.3907468e+08
B6: Клиентский доход (тарифы МПСтатс) - 3 мес | C6: ='период вознаграждения'!M6 -> 73059219 | E6: =C6 -> 73059219
B7: Клиентский доход (тарифы МПСтатс) - первая оплата (на разн. кол-во мес) | C7: ='период вознаграждения'!T6 -> 84930192 | E7: =C7 -> 84930192 | G7: NEW. Прикинула 2 варианта 1) Инфо по кол-ву мес по первым оплатам по новым тарифам (с началак июня) - от МПС. Сумму первых оплат считала по LTV от МПС более ранним данным - 78 682 122 руб 2) Upd - 27 июля - по ср чеку первой оплаты от МПС после обнолвения тарифов (в начале июня) - 84 930 192 руб - применила этот вариант, более точно
B9: Расходы Т-Банк
B10: Договор 1 (лицензия + техподдержка ПО МПСтатс)
B11: услуги по договору | C11: лицензия + техподдержка | E11: лицензия + техподдержка
A12: Договор 1 (лицензия и тех поддержка со стороны МПСтатс) | B12: Лицензия на ПО MPStats (ежегодно) | C12: 396000 | E12: =C12 -> 396000 | G12: NEW - Стоимость от МПСтатс - 396 000 руб. Отправить расчет лицензии налоговикам - спарвочно, чтобы была инофрмация по запросу. Оплата ежегоднго. Провалидировать с налогами и юристами - ОК.
A13: Лицензия на ПО MPStats -- какая минимально возможная? (единоразово бессрочно) | B13: Тех. поддержка ПО MPStats (в год) | C13: ='доп расходы_свод'!C17 -> 360000 | E13: =C13 -> 360000 | G13: по расчету МПС
A14: Тех. поддержка интеграции в целом от MPStats (в год) | B14: ИТОГО по Договору 1 | C14: =C12+C13 -> 756000 | E14: =E12+E13 -> 756000 | G14: Доход для МПС, расход для Т
B15: доля от клиентского дохода MPStats | C15: =C14/C$4 -> #REF! | E15: =E14/E$4 -> #REF!
B16: Договор 2 (биллинг + лидген)
B17: услуги по договору | C17: биллинг + техподдержка + лидогенерация Т | E17: лидогенерация + техподдержка Т
A18: Расходы на привлечение Т-Банк | B18: 1. Расходы на привлечение Т-Банк | C18: =SUM(C19:C21) -> #REF! | E18: =SUM(E19:E21) -> #REF!
A19: Расходы на внутренний маркетинг (запуск 6 кампаний) | B19: Расходы на внутренний маркетинг | C19: =Воронка!#REF! -> #REF! | E19: =Воронка!#REF! -> #REF! | G19: запуск 6 кампаний (исх). можно сократить косты на маркетинг
A20: Расходы на внешний маркетинг (медиа, тг) | B20: Расходы на внешний маркетинг | C20: =Воронка!#REF! -> #REF! | E20: =Воронка!#REF! -> #REF! | G20: медиа, ТГ
A21: Расходы на API запросы к маркетплейсам на время триал (бесплатная версия полного продуката MPStats на 14 дней) | B21: Расходы на API запросы к маркетплейсам на время триал | C21: =Воронка!#REF! -> #REF! | E21: =Воронка!#REF! -> #REF! | G21: Т несет расходы в период пользования клиентами продуката MPStats - триал на 14 дней. Возможно затраты будут меньше, если кол-во дней триала меньше
A22: Расходы на биллинг Т-Банк | B22: 2. Расходы на биллинг Т-Банк | C22: =SUM(C23:C25) -> #REF! | E22: =SUM(E23:E25) -> #REF!
A23: Разработка Биллинга от Т-Банк | B23: Разработка Биллинга от Т-Банк | C23: =Воронка!#REF! -> #REF! | E23: =Воронка!#REF! -> #REF!
A24: Бухгалтерское сопровождение биллинга | B24: Бухгалтерское сопровождение биллинга | C24: =Воронка!#REF! -> #REF! | E24: =Воронка!#REF! -> #REF! | G24: нет данных для расчета
B25: Техподдержка биллинг | C25: =расходы_разработка!D50-расходы_разработка!E50 -> 1272857.1
A26: Тех. поддержка интеграции в целом от Т-Банк | B26: 3. Техподдержка Т-банк интеграции | C26: =расходы_разработка!D50-расходы_разработка!E50 -> 1272857.1 | E26: =расходы_разработка!E50 -> 1272857.1
A27: Расходы на запросы к API Т-Банк (необходимо для базовой работы сервиса) | B27: 4. Расходы на запросы к API Т-Банк | C27: =Воронка!#REF! -> #REF! | E27: =Воронка!#REF! -> #REF! | G27: необходимо для базовой работы сервиса
B28: ИТОГО расходы Т | C28: =SUM(C18,C22,C26,C27) -> #REF! | E28: =SUM(E18,E22,E26,E27) -> #REF!
B29: маржа поверх расходов | C29: 0.14 | E29: 0.15 | G29: 10% - мин.требование налогов Т для рыночности сделки
B31: Стоимость для договора 2 (калькуляция от затрат + маржа)
B32: Биллинг | C32: =C22*(1+C$29) -> #REF! | E32: 0 | G32: разработка+интеграция +маржа Т
B33: доля от клиентского дохода MPStats (бессрочно) | C33: =C32/C$4 -> #REF! | E33: =E32/E$4 -> #REF!
B34: Лидогенерация Т (вкл расходы техподдержка Т + API) | C34: =(C18+C26+C27)*(1+C$29) -> #REF! | E34: =(E18+E26+E27+E22)*(1+E$29) -> #REF! | G34: внешний/внутренний маркетинг Т + расходы на API/техподдержку +маржа 10%
B35: % от клиентского дохода (12 мес) | C35: =C$34/C4 -> #REF! | E35: =E$34/E4 -> #REF!
B36: % от клиентского дохода (6 мес) | C36: =C$34/C5 -> #REF! | E36: =E$34/E5 -> #REF!
B37: % от клиентского дохода (3 мес) | C37: =C$34/C6 -> #REF! | E37: =E$34/E6 -> #REF!
B38: % от клиентского дохода (первая оплата) | C38: =C$34/C7 -> #REF! | E38: =E$34/E7 -> #REF!
B39: ИТОГО по Договору 2 (расчет 1: расходы Т+ маржа) | C39: =C32+C34 -> #REF! | E39: =E32+E34 -> #REF! | G39: Доход для Т, расход для МПС
B40: % от клиентского дохода (12 мес) | C40: =C39/C4 -> #REF! | E40: =E39/E4 -> #REF!
B42: Стоимость для договора 2 (калькуляция от клиентских доходов)
B43: Биллинг Т | C43: =C$4*C47 -> #REF! | E43: =E$4*E47 -> #REF!
B44: Лидогенерация Т | C44: =C$4*C48 -> #REF! | E44: =E$4*E48 -> #REF!
B45: ИТОГО по Договору 2 (расчет 2: флэт % от клиентского дохода) | C45: =C43+C44 -> #REF! | E45: =E43+E44 -> #REF! | G45: Доход для Т, расход для МПС
B46: Расчет от доли клиентского дохода MPStats | C46: =C45/C4 -> #REF! | E46: =E47+E48 -> #REF!
B47: % биллинг | C47: =C33 -> #REF! | E47: =E33 -> #REF!
B48: % лидген (вкл расходы: привлечение, техподдержка, запросы API) | C48: =C35 -> #REF! | E48: =E35 -> #REF!
G49: похожий договор Мпстаст - Партнер (получает 15-30%) - но это не МПС, а Точка
B50: P&L для сторон | C50: Биллинг Т | E50: Биллинг МПС (с рекуррентами и ковенантами) | K50: 1 | L50: 1 - от расходов Т + маржа; 2 - от требуемой доходности Т
B51: МПСтатс
B52: Доходы | C52: =SUM(C53:C54) -> #REF! | E52: =SUM(E53:E54) -> #REF!
B53: Доход с клиентов (тарифы МПСтатс) | C53: =C4 -> #REF! | E53: =E4 -> #REF! | G53: без НДС (льгота для ИТ компаний)
B54: Договор 1 (лицензия + тех поддержка МПСтатс) | C54: =C14 -> 756000 | E54: =E14 -> 756000 | G54: лицензция – без НДС (льгота для ИТ компаний); тех поддержка – с НДС.
B56: Расходы | C56: =SUM(C57:C61) -> #REF! | E56: =SUM(E57:E61) -> #REF!
B57: Sales команда МПСтатс | C57: =Воронка!R52 -> 50425005 | E57: =Воронка!R52 -> 50425005
B58: Договор 2 (биллинг Т) | C58: =CHOOSE($K$50,C32,C43) -> #REF! | E58: =CHOOSE($K$50,E32,E43) -> 0 | G58: НДС 22% к стоимости услуг по Дог.2. Т-Банк начисляет НДС, уплачивает его в бюджет. МПСтатс оплачивают счет от нас с учетом НДС и принимают к себе в зачет эту сумму
B59: Договор 2 (лидген Т) | C59: =CHOOSE($K$50,C34,C44) -> #REF! | E59: =CHOOSE($K$50,E34,E44) -> #REF!
B60: Техподдержка интеграции МПСтатс | C60: =C13 -> 360000 | E60: =E13 -> 360000
B61: Техподдержка пользователей МПСтатс | C61: ='доп расходы_свод'!D17 -> 8352000 | E61: ='доп расходы_свод'!D18 -> 4176000
B63: Прибыль МПС от МПСтатс (за вычетом всех расходов) | C63: =C52-C56 -> #REF! | E63: =E52-E56 -> #REF!
B64: маржинальность по проекту для МПС (прибыль/доходы) | C64: =C63/C52 -> #REF! | E64: =E63/E52 -> #REF!
B65: Прибыль МПС от клиентского дохода МПСтатс (за вычетом лидгена Т) | C65: =C53-C59 -> #REF! | E65: =E53-E59 -> #REF!
B66: доля от клиентского дохода MPStats | C66: =C65/C4 -> #REF! | E66: =E65/E4 -> #REF! | G66: Вознаграждение МПСтатс за вычетом комиссии Т-Банк за лидген+ биллинг/ только лидген.
B68: Справочно: налоги МПС
B69: НДС 22% – тех поддержка по Договору 1 | C69: =C13*22% -> 79200 | E69: =E13*22% -> 79200
B70: Налог на прибыль 5% (льгота для ИТ компаний) | C70: =C63*5% -> #REF! | E70: =E63*5% -> #REF!
B71: Разница налог на прибыль | C71: =C70-E70 -> #REF!
B73: Т-Банк
B74: Доходы | C74: =SUM(C75:C77) -> #REF! | E74: =SUM(E75:E77) -> #REF!
B75: Доход с клиентов (тарифы МПСтатс)
B76: Договор 2 (биллинг Т) | C76: =C58 -> #REF! | E76: =E58 -> 0 | G76: НДС 22% к стоимости услуг по Дог.2. Т-Банк начисляет НДС, уплачивает его в бюджет. МПСтатс оплачивают счет от нас с учетом НДС и принимают к себе в зачет эту сумму
B77: Договор 2 (лидген Т) | C77: =C59 -> #REF! | E77: =E59 -> #REF!
B79: Расходы | C79: =SUM(C80:C82) -> #REF! | E79: =SUM(E80:E82) -> #REF!
B80: Договор 1 (лицензия + тех поддержка МПСтатс) | C80: =C54 -> 756000 | E80: =E54 -> 756000
B81: Договор 2 (биллинг Т) | C81: =C22 -> #REF! | E81: 0
B82: Договор 2 (лидген Т + тех поддержка + API) | C82: =C18+C26+C27 -> #REF! | E82: =E18+E26+E27+E22 -> #REF!
B84: Прибыль Т от МПСтатс | C84: =C74-C79 -> #REF! | E84: =E74-E79 -> #REF!
B85: маржинальность по проекту для Т (прибыль/доходы) | C85: =C84/C74 -> #REF! | E85: =E84/E74 -> #REF!
B86: доля от клиентского дохода MPStats | C86: =C84/C$4 -> #REF! | E86: =E84/E$4 -> #REF!
B87: маржинальность как доля прибыли Т к расходам (от налоговиков) | C87: =C84/C79 -> #REF! | E87: =E84/E79 -> #REF! | G87: 10% - мин.требование налогов Т для рыночности сделки
B89: Потенциальная прибыль Т по другим продуктам | C89: =Воронка!#REF! -> #REF! | E89: =Воронка!#REF! -> #REF!
B90: Общая прибыль Т (MPStats + экосистемный эффект) | C90: =C84+C89 -> #REF! | E90: =E84+E89 -> #REF!
B92: Справочно: налоги Т-Банк
B93: НДС 22% (в доходах по Договору 2) | C93: =(C76+C77)*22% -> #REF! | E93: =(E76+E77)*22% -> #REF! | G93: НДС 22% к стоимости услуг по Дог.2. Т-Банк начисляет НДС, уплачивает его в бюджет. МПСтатс оплачивают счет от нас с учетом НДС и НЕ принимают к себе в зачет эту сумму (инфо от МПС что не смогут в зачет). ?? Уточнить с налогами последствия по НДС для МПС (большую часть выручки не облагают НДС => не смогут принять к вычету НДС по договору с Т?) --- - Будут платить НДС
B94: Налог на прибыль 25% | C94: =C84*25% -> #REF! | E94: =E84*25% -> #REF!
B95: Разница налог на прибыль | C95: =C94-E94 -> #REF!
B97: P&L Total | C97: Биллинг Т | E97: Биллинг МПС (с рекуррентами и ковенантами)
B98: ИТОГО: МПС + Т-Банк
B99: Доходы | C99: =C100+C103 -> #REF! | E99: =E100+E103 -> #REF!
B100: МПС | C100: =SUM(C101:C102) -> #REF! | E100: =SUM(E101:E102) -> #REF!
B101: Доход с клиентов (тарифы МПСтатс) | C101: =C53 -> #REF! | E101: =E53 -> #REF! | G101: доход МПС
B102: Договор 1 (лицензия + тех поддержка МПСтатс) | C102: =C54 -> 756000 | E102: =E54 -> 756000 | G102: доход МПС, расход Т
B103: Т-Банк | C103: =C104+C105 -> #REF! | E103: =E104+E105 -> #REF!
B104: Договор 2 (биллинг Т) | C104: =C58 -> #REF! | E104: =E58 -> 0 | G104: доход Т-Банк, расход МПС
B105: Договор 2 (лидген Т) | C105: =C59 -> #REF! | E105: =E59 -> #REF!
B107: Расходы | C107: =C108+C114 -> #REF! | E107: =E108+E114 -> #REF!
B108: МПС | C108: =SUM(C109:C113) -> #REF! | E108: =SUM(E109:E113) -> #REF!
B109: =B57 -> Sales команда МПСтатс | C109: =C57 -> 50425005 | E109: =E57 -> 50425005
B110: Договор 2 (биллинг Т) | C110: =C58 -> #REF! | E110: =E58 -> 0 | G110: оплата Т за биллинг
B111: Договор 2 (лидген Т) | C111: =C59 -> #REF! | E111: =E59 -> #REF! | G111: оплата Т за лидген
B112: Техподдержка интеграции МПСтатс | C112: =C60 -> 360000 | E112: =E60 -> 360000
B113: Техподдержка пользователей МПСтатс | C113: =C61 -> 8352000 | E113: =E61 -> 4176000
...

Sheet первые оплаты
A1: Категория доходов | B1: Срок | C1: Кол-во пользователей | D1: Вклад | F1: Категория доходов | G1: Кол-во пользователей | H1: Вклад | I1: Средний срок (мес.)
A2: 1_неизвестно | B2: 0 | C2: 1 | D2: =B2*C2 -> 0 | F2: 1_неизвестно | G2: =SUM(C2:C7) -> 191 | H2: =SUM(D2:D7) -> 408 | I2: =H2/G2 -> 2.1361257
A3: 1_неизвестно | B3: 1 | C3: 140 | D3: =B3*C3 -> 140 | F3: 2_<1 млн | G3: =SUM(C8:C12) -> 161 | H3: =SUM(D8:D12) -> 507 | I3: =H3/G3 -> 3.1490683
A4: 1_неизвестно | B4: 2 | C4: 2 | D4: =B4*C4 -> 4 | F4: 3_1-10 млн | G4: =SUM(C13:C17) -> 102 | H4: =SUM(D13:D17) -> 374 | I4: =H4/G4 -> 3.6666667
A5: 1_неизвестно | B5: 3 | C5: 28 | D5: =B5*C5 -> 84 | F5: 4_10+млн | G5: =SUM(C18:C21) -> 37 | H5: =SUM(D18:D21) -> 166 | I5: =H5/G5 -> 4.4864865
A6: 1_неизвестно | B6: 6 | C6: 10 | D6: =B6*C6 -> 60
A7: 1_неизвестно | B7: 12 | C7: 10 | D7: =B7*C7 -> 120
A8: 2_<1 млн | B8: 1 | C8: 94 | D8: =B8*C8 -> 94
A9: 2_<1 млн | B9: 2 | C9: 1 | D9: =B9*C9 -> 2
A10: 2_<1 млн | B10: 3 | C10: 35 | D10: =B10*C10 -> 105
A11: 2_<1 млн | B11: 6 | C11: 11 | D11: =B11*C11 -> 66
A12: 2_<1 млн | B12: 12 | C12: 20 | D12: =B12*C12 -> 240
A13: 3_1-10 млн | B13: 0 | C13: 2 | D13: =B13*C13 -> 0
A14: 3_1-10 млн | B14: 1 | C14: 53 | D14: =B14*C14 -> 53
A15: 3_1-10 млн | B15: 3 | C15: 21 | D15: =B15*C15 -> 63
A16: 3_1-10 млн | B16: 6 | C16: 9 | D16: =B16*C16 -> 54
A17: 3_1-10 млн | B17: 12 | C17: 17 | D17: =B17*C17 -> 204
... A21: 4_10+млн | B21: 12 | C21: 9 | D21: =B21*C21 -> 108
B26: Кол-во пользователей | C26: Сумма оплаты
A27: 1_неизвестно | B27: 191 | C27: 3752242
A28: 0 | B28: 1 | C28: 666
A29: 1 | B29: 140 | C29: 1583647
A30: 2 | B30: 2 | C30: 10000
A31: 3 | B31: 28 | C31: 783108
A32: 6 | B32: 10 | C32: 594903
A33: 12 | B33: 10 | C33: 779918
A34: 2_<1 млн | B34: 161 | C34: 4477202
A35: 1 | B35: 94 | C35: 1024717
A36: 2 | B36: 1 | C36: 25980
A37: 3 | B37: 35 | C37: 874673
A38: 6 | B38: 11 | C38: 506114
A39: 12 | B39: 20 | C39: 2045718
A40: 3_1-10 млн | B40: 102 | C40: 3392809
A41: 0 | B41: 2 | C41: 5500
A42: 1 | B42: 53 | C42: 616841
A43: 3 | B43: 21 | C43: 721044
A44: 6 | B44: 9 | C44: 418312
A45: 12 | B45: 17 | C45: 1631112
A46: 4_10+млн | B46: 37 | C46: 2024535
A47: 1 | B47: 19 | C47: 383254
A48: 3 | B48: 5 | C48: 151115
A49: 6 | B49: 4 | C49: 460467
A50: 12 | B50: 9 | C50: 1029699
A51: (пусто)
A52: (пусто)
A53: Общий итог | B53: 491 | C53: 13646788

Sheet Воронка
F1: 1.1 Биллинг MPS as is (нет реккурентов и ковенант) | M1: 2. Биллинг Т-Банк | S1: Биллинг Т-Банк | AB1: Биллинг Т-Банк
F2: Гипотеза 1. Биллинг MPS + Sales (as is - без реккурентнтов и ковенант) | M2: Гипотеза 2.Биллинг Т / Биллинг MPS (с рекуррентами и ковенанатами)+ Sales Mpstast | S2: Гипотеза 3.Digital + Биллинг Т -- перепроверить формулы в этом варианте (вреотяно местами некорректные) | AB2: Гипотеза 4. Digital + Sales MPS (> 1млн) + Биллинг Т ---- перепроверить формулы в этом варианте (вреотяно местами некорректные)
AB3: Digital (до 1 млн оборот) | AH3: Sales (>1 млн оборот)
A4: Воронка | B4: Конверсии как дали MPStats | C4: Конверсии как дали MPStats | D4: От какого этапа | E4: От всех лидов | F4: Конверсии | G4: Сегмент 1. Активные клиенты в Т с выплатами от МП. 1 приоритет | H4: Сегмент 2. Активные клиенты в Т., но без выплат от МП на РКО. | I4: Сегмент 3. Спящие клиенты в Т (нет транзакций по РКО). Проснулись | J4: Сегмент 4. Клиенты без РКО в Т - Рынок. Открыли РКО | K4: ALL | L4: От всех лидов | M4: Конверсии | N4: Сегмент 1. Активные селлеры в Т с выплатами от МП. 1 приоритет | O4: Сегмент 2. Активные селлеры в Т., но без выплат от МП | P4: Сегмент 3. Спящие селлеры в Т (нет транзакций по РКО) | Q4: Сегмент 4. Селлеры без РКО в Т - Рынок | R4: ALL | S4: Конверсии | T4: Сегмент 1. Активные селлеры в Т с выплатами от МП. 1 приоритет | U4: Сегмент 2. Активные селлеры в Т., но без выплат от МП | V4: Сегмент 3. Спящие селлеры в Т (нет транзакций по РКО) | W4: Сегмент 4. Селлеры без РКО в Т - Рынок | X4: ALL | Y4: От все Лиды Digital | Z4: От все Лиды Sales | AA4: От все Лиды | AB4: Конверсии | AC4: Сегмент 1. Активные селлеры в Т с выплатами от МП. 1 приоритет | AD4: Сегмент 2. Активные селлеры в Т., но без выплат от МП | AE4: Сегмент 3. Спящие селлеры в Т (нет транзакций по РКО) | AF4: Сегмент 4. Селлеры без РКО в Т - Рынок | AG4: ALL Digital | AH4: Конверсии | AI4: Сегмент 1. Активные селлеры в Т с выплатами от МП. 1 приоритет | AJ4: Сегмент 2. Активные селлеры в Т., но без выплат от МП | AK4: Сегмент 3. Спящие селлеры в Т (нет транзакций по РКО) | AL4: Сегмент 4. Селлеры без РКО в Т - Рынок | AM4: ALL Sales | AN4: ALL
A5: База селлеров | F5: 1 | G5: ='База селлеров'!B63 -> 79000 | H5: ='База селлеров'!C63 -> 33000 | I5: ='База селлеров'!D67 -> 1820 | J5: ='База селлеров'!E67 -> 3705 | K5: =SUM(G5:J5) -> 117525 | M5: =F5 -> 1 | N5: =G5 -> 79000 | O5: =H5 -> 33000 | P5: =I5 -> 1820 | Q5: =J5 -> 3705 | R5: =SUM(N5:Q5) -> 117525 | S5: =M5 -> 1 | T5: =N5 -> 79000 | U5: =O5 -> 33000 | V5: =P5 -> 1820 | W5: =Q5 -> 3705 | X5: =SUM(T5:W5) -> 117525 | AC5: =T5*T91 -> 70079.175 | AD5: =U5*U91 -> 27249.295 | AE5: =V5*V91 -> 1564.9858 | AF5: =W5*W91 -> 3185.8639 | AG5: =SUM(AC5:AF5) -> 102079.32 | AI5: =T5-AC5 -> 8920.8253 | AJ5: =U5-AD5 -> 5750.7049 | AK5: =V5-AE5 -> 255.01424 | AL5: =W5-AF5 -> 519.13612 | AM5: =SUM(AI5:AL5) -> 15445.681 | AN5: =AG5+AM5 -> 117525
A6: Увеличение базы - влияние MPStast | I6: ='База селлеров'!D69 -> 130 | J6: ='База селлеров'!E69 -> 1233 | P6: =I6 -> 130 | Q6: =J6 -> 1233 | V6: =P6 -> 130 | W6: =Q6 -> 1233 | AE6: =V6*V91 -> 111.7847 | AF6: =W6*W91 -> 1060.2349 | AK6: =V6-AE6 -> 18.215303 | AL6: =W6-AF6 -> 172.76514
A7: Лиды (визиты Селлер) | C7: 1 | D7: от Базы | F7: 0.5 | G7: =G5*$F$7 -> 39500 | H7: =H5*$F$7 -> 16500 | I7: =I5*$F$7 -> 910 | J7: =J5*$F$7 -> 1852.5 | K7: =SUM(G7:J7) -> 58762.5 | M7: =F7 -> 0.5 | N7: =G7 -> 39500 | O7: =H7 -> 16500 | P7: =I7 -> 910 | Q7: =J7 -> 1852.5 | R7: =SUM(N7:Q7) -> 58762.5 | S7: =M7 -> 0.5 | T7: =N7 -> 39500 | U7: =O7 -> 16500 | V7: =P7 -> 910 | W7: =Q7 -> 1852.5 | X7: =SUM(T7:W7) -> 58762.5 | AB7: =S7 -> 0.5 | AC7: =$AB$7*AC5 -> 35039.587 | AD7: =$AB$7*AD5 -> 13624.648 | AE7: =$AB$7*AE5 -> 782.49288 | AF7: =$AB$7*AF5 -> 1592.9319 | AG7: =SUM(AC7:AF7) -> 51039.66 | AH7: =M7 -> 0.5 | AI7: =$AH$7*AI5 -> 4460.4126 | AJ7: =$AH$7*AJ5 -> 2875.3524 | AK7: =$AH$7*AK5 -> 127.50712 | AL7: =$AH$7*AL5 -> 259.56806 | AM7: =SUM(AI7:AL7) -> 7722.8403 | AN7: =AG7+AM7 -> 58762.5
A8: Оставление API ключа | F8: 0.35 | G8: =$F8*G7 -> 13825 | H8: =$F8*H7 -> 5775 | I8: =$F8*I7 -> 318.5 | J8: =$F8*J7 -> 648.375 | K8: =SUM(G8:J8) -> 20566.875 | M8: 0.35 | N8: =$F8*N7 -> 13825 | O8: =$F8*O7 -> 5775 | P8: =$F8*P7 -> 318.5 | Q8: =$F8*Q7 -> 648.375 | R8: =SUM(N8:Q8) -> 20566.875 | S8: 0.35 | T8: =$F8*T7 -> 13825 | U8: =$F8*U7 -> 5775 | V8: =$F8*V7 -> 318.5 | W8: =$F8*W7 -> 648.375 | X8: =SUM(T8:W8) -> 20566.875 | AB8: 0.35 | AC8: =$F8*AC7 -> 12263.856 | AD8: =$F8*AD7 -> 4768.6266 | AE8: =$F8*AE7 -> 273.87251 | AF8: =$F8*AF7 -> 557.52618 | AG8: =SUM(AC8:AF8) -> 17863.881 | AH8: 0.35 | AI8: =$F8*AI7 -> 1561.1444 | AJ8: =$F8*AJ7 -> 1006.3734 | AK8: =$F8*AK7 -> 44.627491 | AL8: =$F8*AL7 -> 90.848822 | AM8: =SUM(AI8:AL8) -> 2702.9941 | AN8: =AG8+AM8 -> 20566.875
A9: Оффер триала
A10: Триала выдан
A11: Активация триала | F11: 0.21 | G11: =$F11*G7 -> 8295 | H11: =$F11*H7 -> 3465 | I11: =$F11*I7 -> 191.1 | J11: =$F11*J7 -> 389.025 | K11: =SUM(G11:J11) -> 12340.125 | M11: 0.21 | N11: =$F11*N7 -> 8295 | O11: =$F11*O7 -> 3465 | P11: =$F11*P7 -> 191.1 | Q11: =$F11*Q7 -> 389.025 | R11: =SUM(N11:Q11) -> 12340.125 | S11: 0.21 | T11: =$F11*T7 -> 8295 | U11: =$F11*U7 -> 3465 | V11: =$F11*V7 -> 191.1 | W11: =$F11*W7 -> 389.025 | X11: =SUM(T11:W11) -> 12340.125 | AB11: 0.21 | AC11: =$F11*AC7 -> 7358.3133 | AD11: =$F11*AD7 -> 2861.176 | AE11: =$F11*AE7 -> 164.32351 | AF11: =$F11*AF7 -> 334.51571 | AG11: =SUM(AC11:AF11) -> 10718.329 | AH11: 0.21 | AI11: =$F11*AI7 -> 936.68665 | AJ11: =$F11*AJ7 -> 603.82401 | AK11: =$F11*AK7 -> 26.776495 | AL11: =$F11*AL7 -> 54.509293 | AM11: =SUM(AI11:AL11) -> 1621.7965 | AN11: =AG11+AM11 -> 12340.125
A12: Активация в Селлере
A13: Квалификацированные лиды ЦА (не дозвон КЦ) | D13: от Лиды | F13: =G13/G7 -> 0.25 | G13: =G7-G14 -> 9875 | H13: =H7-H14 -> 4125 | I13: =I7-I14 -> 227.5 | J13: =J7-J14 -> 463.125 | K13: =SUM(G13:J13) -> 14690.625 | M13: =N13/N7 -> 0.25 | N13: =N7-N14 -> 9875 | O13: =O7-O14 -> 4125 | P13: =P7-P14 -> 227.5 | Q13: =Q7-Q14 -> 463.125 | R13: =SUM(N13:Q13) -> 14690.625 | S13: - | T13: - | U13: - | V13: - | W13: - | X13: - | AH13: =M13 -> 0.25 | AI13: =AI7-AI14 -> 1115.1032 | AJ13: =AJ7-AJ14 -> 718.83811 | AK13: =AK7-AK14 -> 31.87678 | AL13: =AL7-AL14 -> 64.892016 | AM13: =SUM(AI13:AL13) -> 1930.7101 | AN13: =AG13+AM13 -> 1930.7101
A14: Квалификацированные лиды ЦА (дозвоны) | B14: от Лиды | C14: 0.13 | D14: от Лиды | F14: 0.75 | G14: =$G$7*F14 -> 29625 | H14: =$H$7*F14 -> 12375 | I14: =$I$7*F14 -> 682.5 | J14: =$J$7*F14 -> 1389.375 | K14: =SUM(G14:J14) -> 44071.875 | M14: =F14 -> 0.75 | N14: =$N$7*M14 -> 29625 | O14: =$O$7*M14 -> 12375 | P14: =$P$7*M14 -> 682.5 | Q14: =$Q$7*M14 -> 1389.375 | R14: =SUM(N14:Q14) -> 44071.875 | S14: - | T14: - | U14: - | V14: - | W14: - | X14: - | AH14: =M14 -> 0.75 | AI14: =$AI$7*AH14 -> 3345.3095 | AJ14: =$AJ$7*AH14 -> 2156.5143 | AK14: =$AK$7*AH14 -> 95.630339 | AL14: =$AL$7*AH14 -> 194.67605 | AM14: =SUM(AI14:AL14) -> 5792.1302 | AN14: =AG14+AM14 -> 5792.1302
A15: /Оффер демо встречи | B15: от Квалиф. Лиды | C15: 1 | D15: от Квал. Лиды | F15: 1 | G15: =$G$14*F15 -> 29625 | H15: =$H$14*F15 -> 12375 | I15: =$I$14*F15 -> 682.5 | J15: =$J$14*F15 -> 1389.375 | K15: =SUM(G15:J15) -> 44071.875 | M15: =F15 -> 1 | N15: =$N$7*M15 -> 39500 | O15: =$O$7*M15 -> 16500 | P15: =$P$7*M15 -> 910 | Q15: =$Q$7*M15 -> 1852.5 | R15: =SUM(N15:Q15) -> 58762.5 | S15: - | T15: - | U15: - | V15: - | W15: - | X15: - | AH15: =M15 -> 1 | AI15: =$AI$7*AH15 -> 4460.4126 | AJ15: =$AJ$7*AH15 -> 2875.3524 | AK15: =$AK$7*AH15 -> 127.50712 | AL15: =$AL$7*AH15 -> 259.56806 | AM15: =SUM(AI15:AL15) -> 7722.8403 | AN15: =AG15+AM15 -> 7722.8403
A16: //Согласились на демо встречу | B16: от Квалиф. Лиды | C16: 0.4 | D16: от Квал. Лиды | F16: ='Воронка MPS_обработано'!N10 -> 0.4 | G16: =$G$14*F16 -> 11850 | H16: =$H$14*F16 -> 4950 | I16: =$I$14*F16 -> 273 | J16: =$J$14*F16 -> 555.75 | K16: =SUM(G16:J16) -> 17628.75 | M16: =F16 -> 0.4 | N16: =$N$7*M16 -> 15800 | O16: =$O$7*M16 -> 6600 | P16: =$P$7*M16 -> 364 | Q16: =$Q$7*M16 -> 741 | R16: =SUM(N16:Q16) -> 23505 | S16: - | T16: - | U16: - | V16: - | W16: - | X16: - | AH16: =M16 -> 0.4 | AI16: =$AI$7*AH16 -> 1784.1651 | AJ16: =$AJ$7*AH16 -> 1150.141 | AK16: =$AK$7*AH16 -> 51.002847 | AL16: =$AL$7*AH16 -> 103.82722 | AM16: =SUM(AI16:AL16) -> 3089.1361 | AN16: =AG16+AM16 -> 3089.1361
A17: //Демо встреча состоялась | B17: от Квалиф. Лиды | C17: 0.298 | D17: от Квал. Лиды | F17: ='Воронка MPS_обработано'!N11 -> 0.298 | G17: =$G$14*F17 -> 8828.25 | H17: =$H$14*F17 -> 3687.75 | I17: =$I$14*F17 -> 203.385 | J17: =$J$14*F17 -> 414.03375 | K17: =SUM(G17:J17) -> 13133.419 | M17: =F17 -> 0.298 | N17: =$N$7*M17 -> 11771 | O17: =$O$7*M17 -> 4917 | P17: =$P$7*M17 -> 271.18 | Q17: =$Q$7*M17 -> 552.045 | R17: =SUM(N17:Q17) -> 17511.225 | S17: - | T17: - | U17: - | V17: - | W17: - | X17: - | AH17: =M17 -> 0.298 | AI17: =$AI$7*AH17 -> 1329.203 | AJ17: =$AJ$7*AH17 -> 856.85503 | AK17: =$AK$7*AH17 -> 37.997121 | AL17: =$AL$7*AH17 -> 77.351283 | AM17: =SUM(AI17:AL17) -> 2301.4064 | AN17: =AG17+AM17 -> 2301.4064
A18: /Дозвон sales (кто не согласился на демо) | B18: от Квалиф. Лиды | C18: 0.455 | D18: от Квал. Лиды | F18: ='Воронка MPS_обработано'!N12 -> 0.455 | G18: =$G$14*F18 -> 13479.375 | H18: =$H$14*F18 -> 5630.625 | I18: =$I$14*F18 -> 310.5375 | J18: =$J$14*F18 -> 632.16562 | K18: =SUM(G18:J18) -> 20052.703 | M18: =F18 -> 0.455 | N18: =$N$7*M18 -> 17972.5 | O18: =$O$7*M18 -> 7507.5 | P18: =$P$7*M18 -> 414.05 | Q18: =$Q$7*M18 -> 842.8875 | R18: =SUM(N18:Q18) -> 26736.938 | S18: - | T18: - | U18: - | V18: - | W18: - | X18: - | AH18: =M18 -> 0.455 | AI18: =$AI$7*AH18 -> 2029.4878 | AJ18: =$AJ$7*AH18 -> 1308.2854 | AK18: =$AK$7*AH18 -> 58.015739 | AL18: =$AL$7*AH18 -> 118.10347 | AM18: =SUM(AI18:AL18) -> 3513.8923 | AN18: =AG18+AM18 -> 3513.8923
A19: Покупка тарифа MPS (основной канал) | B19: от Лиды | C19: 0,7% / 0,41%/ 1,1% всего | D19: от Квал. Лиды | E19: =K19/K7 -> 0.064038462 | F19: ='Воронка MPS_обработано'!N14 -> 0.085384615 | G19: =$G$14*F19 -> 2529.5192 | H19: =$H$14*F19 -> 1056.6346 | I19: =$I$14*F19 -> 58.275 | J19: =$J$14*F19 -> 118.63125 | K19: =SUM(G19:J19) -> 3763.0601 | L19: =R19/R7 -> 0.096057692 | M19: =F19*1.5 -> 0.12807692 | N19: =N14*$M$19 -> 3794.2788 | O19: =O14*$M$19 -> 1584.9519 | P19: =P14*$M$19 -> 87.4125 | Q19: =Q14*$M$19 -> 177.94688 | R19: =SUM(N19:Q19) -> 5644.5901 | S19: ='Воронка Селлер as is'!F12 -> 0.017475399 | T19: =$S$19*T7 -> 690.27825 | U19: =$S$19*U7 -> 288.34408 | V19: =$S$19*V7 -> 15.902613 | W19: =$S$19*W7 -> 32.373176 | X19: =SUM(T19:W19) -> 1026.8981 | Y19: =AG19/$AG$7 -> 0.017475399 | Z19: =AM19/$AM$7 -> 0.096057692 | AA19: =AN19/AN7 -> 0.027803048 | AB19: =S19 -> 0.017475399 | AC19: =$S$19*AC7 -> 612.33076 | AD19: =$S$19*AD7 -> 238.09615 | AE19: =$S$19*AE7 -> 13.674375 | AF19: =$S$19*AF7 -> 27.837121 | AG19: =SUM(AC19:AF19) -> 891.9384 | AH19: =M19 -> 0.12807692 | AI19: =AI14*$AH$19 -> 428.45694 | AJ19: =AJ14*$AH$19 -> 276.19972 | AK19: =AK14*$AH$19 -> 12.24804 | AL19: =AL14*$AH$19 -> 24.933509 | AM19: =SUM(AI19:AL19) -> 741.83821 | AN19: =AG19+AM19 -> 1633.7766
A20: Покупка тарифа MPS (самоходы) | D20: от Лиды | E20: =K20/K7 -> 0.0043688497 | F20: =S19 -> 0.017475399 | G20: =G13*$F$20 -> 172.56956 | H20: =H13*$F$20 -> 72.08602 | I20: =I13*$F$20 -> 3.9756532 | J20: =J13*$F$20 -> 8.093294 | K20: =SUM(G20:J20) -> 256.72453 | L20: =R20/R7 -> 0.0043688497 | M20: =S19 -> 0.017475399 | N20: =N13*$M$20 -> 172.56956 | O20: =O13*$M$20 -> 72.08602 | P20: =P13*$M$20 -> 3.9756532 | Q20: =Q13*$M$20 -> 8.093294 | R20: =SUM(N20:Q20) -> 256.72453 | Y20: =AG20/$AG$7 -> 0 | Z20: =AM20/$AM$7 -> 0.0043688497 | AA20: =AN20/AN7 -> 0.00057417449 | AH20: =M20 -> 0.017475399 | AI20: =AI13*$AH$20 -> 19.486872 | AJ20: =AJ13*$AH$20 -> 12.561983 | AK20: =AK13*$AH$20 -> 0.55705943 | AL20: =AL13*$AH$20 -> 1.1340138 | AM20: =SUM(AI20:AL20) -> 33.739928 | AN20: =AG20+AM20 -> 33.739928
A21: Покупка тарифа MPS (всего) | E21: =K21/K7 -> 0.068407311 | G21: =SUM(G19:G20) -> 2702.0888 | H21: =SUM(H19:H20) -> 1128.7206 | I21: =SUM(I19:I20) -> 62.250653 | J21: =SUM(J19:J20) -> 126.72454 | K21: =SUM(G21:J21) -> 4019.7846 | L21: =R21/R7 -> 0.10042654 | N21: =SUM(N19:N20) -> 3966.8484 | O21: =SUM(O19:O20) -> 1657.0379 | P21: =SUM(P19:P20) -> 91.388153 | Q21: =SUM(Q19:Q20) -> 186.04017 | R21: =SUM(N21:Q21) -> 5901.3147 | T21: =T19 -> 690.27825 | U21: =U19 -> 288.34408 | V21: =V19 -> 15.902613 | W21: =W19 -> 32.373176 | X21: =SUM(T21:W21) -> 1026.8981 | Y21: =AG21/$AG$7 -> 0.017475399 | Z21: =AM21/$AM$7 -> 0.10042654 | AA21: =AN21/AN7 -> 0.028377223 | AC21: =AC19 -> 612.33076 | AD21: =AD19 -> 238.09615 | AE21: =AE19 -> 13.674375 | AF21: =AF19 -> 27.837121 | AG21: =SUM(AC21:AF21) -> 891.9384 | AI21: =SUM(AI19:AI20) -> 447.94382 | AJ21: =SUM(AJ19:AJ20) -> 288.7617 | AK21: =SUM(AK19:AK20) -> 12.805099 | AL21: =SUM(AL19:AL20) -> 26.067523 | AM21: =SUM(AI21:AL21) -> 775.57814 | AN21: =AG21+AM21 -> 1667.5165
A22: >100 млн | G22: =G$21*G88 -> 0.29496946 | H22: =H$21*H88 -> 1.9448507 | I22: =I$21*I88 -> 0.051336957 | J22: =J$21*J88 -> 0.10450738 | K22: =SUM(G22:J22) -> 2.3956645 | N22: =N$21*N88 -> 0.43303504 | O22: =O$21*O88 -> 2.8551719 | P22: =P$21*P88 -> 0.075366111 | Q22: =Q$21*Q88 -> 0.15342387 | R22: =SUM(N22:Q22) -> 3.5169969 | T22: =T$21*T88 -> 0.075353187 | U22: =U$21*U88 -> 0.49683347 | V22: =V$21*V88 -> 0.013114589 | W22: =W$21*W88 -> 0.026697557 | X22: =SUM(T22:W22) -> 0.6119988 | AC22: =AC$21*AC88 -> 0 | AD22: =AD$21*AD88 -> 0 | AE22: =AE$21*AE88 -> 0 | AF22: =AF$21*AF88 -> 0 | AG22: =SUM(AC22:AF22) -> 0 | AI22: =AI$21*AI88 -> 0.43303504 | AJ22: =AJ$21*AJ88 -> 2.8551719 | AK22: =AK$21*AK88 -> 0.075366111 | AL22: =AL$21*AL88 -> 0.15342387 | AM22: =SUM(AI22:AL22) -> 3.5169969 | AN22: =AG22+AM22 -> 3.5169969
A23: 10-100 млн | G23: =G$21*G89 -> 20.268616 | H23: =H$21*H89 -> 23.161404 | I23: =I$21*I89 -> 0.82625481 | J23: =J$21*J89 -> 1.6820187 | K23: =SUM(G23:J23) -> 45.938293 | N23: =N$21*N89 -> 29.755693 | O23: =O$21*O89 -> 34.002502 | P23: =P$21*P89 -> 1.2129977 | Q23: =Q$21*Q89 -> 2.4693168 | R23: =SUM(N23:Q23) -> 67.44051 | T23: =T$21*T89 -> 5.1778404 | U23: =U$21*U89 -> 5.9168349 | V23: =V$21*V89 -> 0.21107586 | W23: =W$21*W89 -> 0.42969015 | X23: =SUM(T23:W23) -> 11.735441 | AC23: =AC$21*AC89 -> 0 | AD23: =AD$21*AD89 -> 0 | AE23: =AE$21*AE89 -> 0 | AF23: =AF$21*AF89 -> 0 | AG23: =SUM(AC23:AF23) -> 0 | AI23: =AI$21*AI89 -> 29.755693 | AJ23: =AJ$21*AJ89 -> 34.002502 | AK23: =AK$21*AK89 -> 1.2129977 | AL23: =AL$21*AL89 -> 2.4693168 | AM23: =SUM(AI23:AL23) -> 67.44051 | AN23: =AG23+AM23 -> 67.44051
A24: 1-10 млн | G24: =G$21*G90 -> 284.56125 | H24: =H$21*H90 -> 171.58887 | I24: =I$21*I90 -> 7.8448274 | J24: =J$21*J90 -> 15.969827 | K24: =SUM(G24:J24) -> 479.96478 | N24: =N$21*N90 -> 417.75509 | O24: =O$21*O90 -> 251.90403 | P24: =P$21*P90 -> 11.516735 | Q24: =Q$21*Q90 -> 23.444782 | R24: =SUM(N24:Q24) -> 704.62064 | T24: =T$21*T90 -> 72.694296 | U24: =U$21*U90 -> 43.834262 | V24: =V$21*V90 -> 2.0040473 | W24: =W$21*W90 -> 4.0796677 | X24: =SUM(T24:W24) -> 122.61227 | AC24: =AC$21*AC90 -> 0 | AD24: =AD$21*AD90 -> 0 | AE24: =AE$21*AE90 -> 0 | AF24: =AF$21*AF90 -> 0 | AG24: =SUM(AC24:AF24) -> 0 | AI24: =AI$21*AI90 -> 417.75509 | AJ24: =AJ$21*AJ90 -> 251.90403 | AK24: =AK$21*AK90 -> 11.516735 | AL24: =AL$21*AL90 -> 23.444782 | AM24: =SUM(AI24:AL24) -> 704.62064 | AN24: =AG24+AM24 -> 704.62064
A25: менее 1 млн | G25: =G$21*G91 -> 2396.964 | H25: =H$21*H91 -> 932.02551 | I25: =I$21*I91 -> 53.528234 | J25: =J$21*J91 -> 108.96819 | K25: =SUM(G25:J25) -> 3491.4859 | N25: =N$21*N91 -> 3518.9046 | O25: =O$21*O91 -> 1368.2762 | P25: =P$21*P91 -> 78.583054 | Q25: =Q$21*Q91 -> 159.97265 | R25: =SUM(N25:Q25) -> 5125.7365 | T25: =T$21*T91 -> 612.33076 | U25: =U$21*U91 -> 238.09615 | V25: =V$21*V91 -> 13.674375 | W25: =W$21*W91 -> 27.837121 | X25: =SUM(T25:W25) -> 891.9384 | AC25: =AC$21*AC91 -> 612.33076 | AD25: =AD$21*AD91 -> 238.09615 | AE25: =AE$21*AE91 -> 13.674375 | AF25: =AF$21*AF91 -> 27.837121 | AG25: =SUM(AC25:AF25) -> 891.9384 | AI25: =AI$21*AI91 -> 0 | AJ25: =AJ$21*AJ91 -> 0 | AK25: =AK$21*AK91 -> 0 | AL25: =AL$21*AL91 -> 0 | AM25: =SUM(AI25:AL25) -> 0 | AN25: =AG25+AM25 -> 891.9384
A26: без оборотов | G26: =G$21*G92 -> 0 | H26: =H$21*H92 -> 0 | I26: =I$21*I92 -> 0 | J26: =J$21*J92 -> 0 | K26: =SUM(G26:J26) -> 0 | N26: =N$21*N92 -> 0 | O26: =O$21*O92 -> 0 | P26: =P$21*P92 -> 0 | Q26: =Q$21*Q92 -> 0 | R26: =SUM(N26:Q26) -> 0 | T26: =T$21*T92 -> 0 | U26: =U$21*U92 -> 0 | V26: =V$21*V92 -> 0 | W26: =W$21*W92 -> 0 | X26: =SUM(T26:W26) -> 0 | AC26: =AC$21*AC92 -> 0 | AD26: =AD$21*AD92 -> 0 | AE26: =AE$21*AE92 -> 0 | AF26: =AF$21*AF92 -> 0 | AG26: =SUM(AC26:AF26) -> 0 | AI26: =AI$21*AI92 -> 0 | AJ26: =AJ$21*AJ92 -> 0 | AK26: =AK$21*AK92 -> 0 | AL26: =AL$21*AL92 -> 0 | AM26: =SUM(AI26:AL26) -> 0 | AN26: =AG26+AM26 -> 0
M27: =M19/F19 -> 1.5
M28: =(M19-F19)/F19 -> 0.5
A29: LTV | G29: =G44/G21 -> 20930.298 | H29: =H44/H21 -> 21327.659 | I29: =I44/I21 -> 21106.467 | J29: =J44/J21 -> 21106.467 | K29: =K44/K21 -> 21050.155 | N29: =N44/N21 -> 23817.576 | O29: =O44/O21 -> 24219.665 | P29: =P44/P21 -> 23995.842 | Q29: =Q44/Q21 -> 23995.842 | R29: =R44/R21 -> 23938.859 | T29: =T44/T21 -> 23817.576 | U29: =U44/U21 -> 24219.665 | V29: =V44/V21 -> 23995.842 | W29: =W44/W21 -> 23995.842 | X29: =X44/X21 -> 23938.859 | AC29: =AC44/AC21 -> 23361.309 | AD29: =AD44/AD21 -> 23361.309 | AE29: =AE44/AE21 -> 23361.309 | AF29: =AF44/AF21 -> 23361.309 | AG29: =AG44/AG21 -> 23361.309 | AI29: =AI44/AI21 -> 27401.866 | AJ29: =AJ44/AJ21 -> 28286.923 | AK29: =AK44/AK21 -> 27889.878 | AL29: =AL44/AL21 -> 27889.878 | AM29: =AM44/AM21 -> 27755.848 | AN29: =AN44/AN21 -> 25405.252
A30: >100 млн | G30: =G45/G22 -> 55362.5 | H30: =H45/H22 -> 55362.5 | I30: =I45/I22 -> 55362.5 | J30: =J45/J22 -> 55362.5 | K30: =K45/K22 -> 55362.5 | N30: =N45/N22 -> 59174.344 | O30: =O45/O22 -> 59174.344 | P30: =P45/P22 -> 59174.344 | Q30: =Q45/Q22 -> 59174.344 | R30: =R45/R22 -> 59174.344 | T30: =T45/T22 -> 59174.344 | U30: =U45/U22 -> 59174.344 | V30: =V45/V22 -> 59174.344 | W30: =W45/W22 -> 59174.344 | X30: =X45/X22 -> 59174.344 | AC30: =AC45/AC22 -> #DIV/0! | AD30: =AD45/AD22 -> #DIV/0! | AE30: =AE45/AE22 -> #DIV/0! | AF30: =AF45/AF22 -> #DIV/0! | AG30: =AG45/AG22 -> #DIV/0! | AI30: =AI45/AI22 -> 59174.344 | AJ30: =AJ45/AJ22 -> 59174.344 | AK30: =AK45/AK22 -> 59174.344 | AL30: =AL45/AL22 -> 59174.344 | AM30: =AM45/AM22 -> 59174.344 | AN30: =AN45/AN22 -> 59174.344
A31: 10-100 млн | G31: =G46/G23 -> 35026.5 | H31: =H46/H23 -> 35026.5 | I31: =I46/I23 -> 35026.5 | J31: =J46/J23 -> 35026.5 | K31: =K46/K23 -> 35026.5 | N31: =N46/N23 -> 38183.395 | O31: =O46/O23 -> 38183.395 | P31: =P46/P23 -> 38183.395 | Q31: =Q46/Q23 -> 38183.395 | R31: =R46/R23 -> 38183.395 | T31: =T46/T23 -> 38183.395 | U31: =U46/U23 -> 38183.395 | V31: =V46/V23 -> 38183.395 | W31: =W46/W23 -> 38183.395 | X31: =X46/X23 -> 38183.395 | AC31: =AC46/AC23 -> #DIV/0! | AD31: =AD46/AD23 -> #DIV/0! | AE31: =AE46/AE23 -> #DIV/0! | AF31: =AF46/AF23 -> #DIV/0! | AG31: =AG46/AG23 -> #DIV/0! | AI31: =AI46/AI23 -> 38183.395 | AJ31: =AJ46/AJ23 -> 38183.395 | AK31: =AK46/AK23 -> 38183.395 | AL31: =AL46/AL23 -> 38183.395 | AM31: =AM46/AM23 -> 38183.395 | AN31: =AN46/AN23 -> 38183.395
A32: 1-10 млн | G32: =G47/G24 -> 23721.5 | H32: =H47/H24 -> 23721.5 | I32: =I47/I24 -> 23721.5 | J32: =J47/J24 -> 23721.5 | K32: =K47/K24 -> 23721.5 | N32: =N47/N24 -> 26600.988 | O32: =O47/O24 -> 26600.988 | P32: =P47/P24 -> 26600.988 | Q32: =Q47/Q24 -> 26600.988 | R32: =R47/R24 -> 26600.988 | T32: =T47/T24 -> 26600.988 | U32: =U47/U24 -> 26600.988 | V32: =V47/V24 -> 26600.988 | W32: =W47/W24 -> 26600.988 | X32: =X47/X24 -> 26600.988 | AC32: =AC47/AC24 -> #DIV/0! | AD32: =AD47/AD24 -> #DIV/0! | AE32: =AE47/AE24 -> #DIV/0! | AF32: =AF47/AF24 -> #DIV/0! | AG32: =AG47/AG24 -> #DIV/0! | AI32: =AI47/AI24 -> 26600.988 | AJ32: =AJ47/AJ24 -> 26600.988 | AK32: =AK47/AK24 -> 26600.988 | AL32: =AL47/AL24 -> 26600.988 | AM32: =AM47/AM24 -> 26600.988 | AN32: =AN47/AN24 -> 26600.988
A33: менее 1 млн | G33: =G48/G25 -> 20475.5 | H33: =H48/H25 -> 20475.5 | I33: =I48/I25 -> 20475.5 | J33: =J48/J25 -> 20475.5 | K33: =K48/K25 -> 20475.5 | N33: =N48/N25 -> 23361.309 | O33: =O48/O25 -> 23361.309 | P33: =P48/P25 -> 23361.309 | Q33: =Q48/Q25 -> 23361.309 | R33: =R48/R25 -> 23361.309 | T33: =T48/T25 -> 23361.309 | U33: =U48/U25 -> 23361.309 | V33: =V48/V25 -> 23361.309 | W33: =W48/W25 -> 23361.309 | X33: =X48/X25 -> 23361.309 | AC33: =AC48/AC25 -> 23361.309 | AD33: =AD48/AD25 -> 23361.309 | AE33: =AE48/AE25 -> 23361.309 | AF33: =AF48/AF25 -> 23361.309 | AG33: =AG48/AG25 -> 23361.309 | AI33: =AI48/AI25 -> #DIV/0! | AJ33: =AJ48/AJ25 -> #DIV/0! | AK33: =AK48/AK25 -> #DIV/0! | AL33: =AL48/AL25 -> #DIV/0! | AM33: =AM48/AM25 -> #DIV/0! | AN33: =AN48/AN25 -> 23361.309
A34: без оборотов
A35: Расходы на 1 платящего клиента | G35: =G36+G40+G41 -> 17257.06 | H35: =H36+H40+H41 -> 17274.489 | I35: =I36+I40+I41 -> 17264.787 | J35: =J36+J40+J41 -> 17264.787 | K35: =K36+K40+K41 -> 17262.317 | N35: =N50/N21 -> 10573.405 | O35: =O50/O21 -> 10590.834 | P35: =P50/P21 -> 10581.132 | Q35: =Q50/Q21 -> 10581.132 | R35: =R50/R21 -> 10578.662 | T35: =T50/T21 -> 5327.4925 | U35: =U50/U21 -> 5344.9216 | V35: =V50/V21 -> 5335.2196 | W35: =W50/W21 -> 5335.2196 | X35: =X50/X21 -> 5332.7497 | AC35: =AC50/AC21 -> 5305.0586 | AD35: =AD50/AD21 -> 5305.0586 | AE35: =AE50/AE21 -> 5305.0586 | AF35: =AF50/AF21 -> 5305.0586 | AG35: =AG50/AG21 -> 5305.0586 | AI35: =AI50/AI21 -> 10658.804 | AJ35: =AJ50/AJ21 -> 10688.887 | AK35: =AK50/AK21 -> 10675.392 | AL35: =AL50/AL21 -> 10675.392 | AM35: =AM50/AM21 -> 10670.836 | AN35: =AN50/AN21 -> 7800.7337
A36: CAC | G36: =SUM(G37:G39) -> 14406.632 | H36: =SUM(H37:H39) -> 14406.632 | I36: =SUM(I37:I39) -> 14406.632 | J36: =SUM(J37:J39) -> 14406.632 | K36: =SUM(K37:K39) -> 14406.632 | N36: =SUM(N37:N39) -> 9619.0183 | O36: =SUM(O37:O39) -> 9619.0183 | P36: =SUM(P37:P39) -> 9619.0183 | Q36: =SUM(Q37:Q39) -> 9619.0183 | R36: =SUM(R37:R39) -> 9619.0183 | T36: =SUM(T37:T39) -> 3940.4519 | U36: =SUM(U37:U39) -> 3940.4519 | V36: =SUM(V37:V39) -> 3940.4519 | W36: =SUM(W37:W39) -> 3940.4519 | X36: =SUM(X37:X39) -> 3940.4519 | AC36: =SUM(AC37:AC39) -> 3940.4519 | AD36: =SUM(AD37:AD39) -> 3940.4519 | AE36: =SUM(AE37:AE39) -> 3940.4519 | AF36: =SUM(AF37:AF39) -> 3940.4519 | AG36: =SUM(AG37:AG39) -> 3940.4519 | AI36: =SUM(AI37:AI39) -> 9619.0183 | AJ36: =SUM(AJ37:AJ39) -> 9619.0183 | AK36: =SUM(AK37:AK39) -> 9619.0183 | AL36: =SUM(AL37:AL39) -> 9619.0183 | AM36: =SUM(AM37:AM39) -> 9619.0183 | AN36: =AN51/AN21 -> 6400.8544
A37: Sales, КЦ | G37: =G52/G19 -> 13400 | H37: =H52/H19 -> 13400 | I37: =I52/I19 -> 13400 | J37: =J52/J19 -> 13400 | K37: =K52/K19 -> 13400 | N37: =N52/N19 -> 8933.3333 | O37: =O52/O19 -> 8933.3333 | P37: =P52/P19 -> 8933.3333 | Q37: =Q52/Q19 -> 8933.3333 | R37: =R52/R19 -> 8933.3333 | T37: =T52/T19 -> 0 | U37: =U52/U19 -> 0 | V37: =V52/V19 -> 0 | W37: =W52/W19 -> 0 | X37: =X52/X19 -> 0 | AC37: =AC52/AC19 -> 0 | AD37: =AD52/AD19 -> 0 | AE37: =AE52/AE19 -> 0 | AF37: =AF52/AF19 -> 0 | AG37: =AG52/AG19 -> 0 | AI37: =AI52/AI19 -> 8933.3333 | AJ37: =AJ52/AJ19 -> 8933.3333 | AK37: =AK52/AK19 -> 8933.3333 | AL37: =AL52/AL19 -> 8933.3333 | AM37: =AM52/AM19 -> 8933.3333
A38: маркетинг Т внешний | G38: =G54/G21 -> 746.30864 | H38: =H54/H21 -> 746.30864 | I38: =I54/I21 -> 746.30864 | J38: =J54/J21 -> 746.30864 | K38: =K54/K21 -> 746.30864 | N38: =N54/N21 -> 508.3613 | O38: =O54/O21 -> 508.3613 | P38: =P54/P21 -> 508.3613 | Q38: =Q54/Q21 -> 508.3613 | R38: =R54/R21 -> 508.3613 | T38: =T54/T21 -> 2921.4193 | U38: =U54/U21 -> 2921.4193 | V38: =V54/V21 -> 2921.4193 | W38: =W54/W21 -> 2921.4193 | X38: =X54/X21 -> 2921.4193 | AC38: =AC54/AC21 -> 2921.4193 | AD38: =AD54/AD21 -> 2921.4193 | AE38: =AE54/AE21 -> 2921.4193 | AF38: =AF54/AF21 -> 2921.4193 | AG38: =AG54/AG21 -> 2921.4193 | AI38: =AI54/AI21 -> 508.3613 | AJ38: =AJ54/AJ21 -> 508.3613 | AK38: =AK54/AK21 -> 508.3613 | AL38: =AL54/AL21 -> 508.3613 | AM38: =AM54/AM21 -> 508.3613
A39: триал | G39: =G53/G21 -> 260.32305 | H39: =H53/H21 -> 260.32305 | I39: =I53/I21 -> 260.32305 | J39: =J53/J21 -> 260.32305 | K39: =K53/K21 -> 260.32305 | N39: =N53/N21 -> 177.32364 | O39: =O53/O21 -> 177.32364 | P39: =P53/P21 -> 177.32364 | Q39: =Q53/Q21 -> 177.32364 | R39: =R53/R21 -> 177.32364 | T39: =T53/T21 -> 1019.0325 | U39: =U53/U21 -> 1019.0325 | V39: =V53/V21 -> 1019.0325 | W39: =W53/W21 -> 1019.0325 | X39: =X53/X21 -> 1019.0325 | AC39: =AC53/AC21 -> 1019.0325 | AD39: =AD53/AD21 -> 1019.0325 | AE39: =AE53/AE21 -> 1019.0325 | AF39: =AF53/AF21 -> 1019.0325 | AG39: =AG53/AG21 -> 1019.0325 | AI39: =AI53/AI21 -> 177.32364 | AJ39: =AJ53/AJ21 -> 177.32364 | AK39: =AK53/AK21 -> 177.32364 | AL39: =AL53/AL21 -> 177.32364 | AM39: =AM53/AM21 -> 177.32364
A40: API | G40: =G55/G21 -> 1250.4282 | H40: =H55/H21 -> 1267.8573 | I40: =I55/I21 -> 1258.1554 | J40: =J55/J21 -> 1258.1554 | K40: =K55/K21 -> 1255.6854 | N40: =N55/N21 -> 1343.0131 | O40: =O55/O21 -> 1360.4421 | P40: =P55/P21 -> 1350.7402 | Q40: =Q55/Q21 -> 1350.7402 | R40: =R55/R21 -> 1348.2703 | T40: =T55/T21 -> 1387.0406 | U40: =U55/U21 -> 1404.4697 | V40: =V55/V21 -> 1394.7678 | W40: =W55/W21 -> 1394.7678 | X40: =X55/X21 -> 1392.2978 | AC40: =AC55/AC21 -> 1364.6068 | AD40: =AD55/AD21 -> 1364.6068 | AE40: =AE55/AE21 -> 1364.6068 | AF40: =AF55/AF21 -> 1364.6068 | AG40: =AG55/AG21 -> 1364.6068 | AI40: =AI55/AI21 -> 1428.4118 | AJ40: =AJ55/AJ21 -> 1458.4952 | AK40: =AK55/AK21 -> 1444.9995 | AL40: =AL55/AL21 -> 1444.9995 | AM40: =AM55/AM21 -> 1440.4438 | AN40: =AN55/AN21 -> 1399.8793
A41: Продление и удержание MPStas | G41: =G71/G21 -> 1600 | H41: =H71/H21 -> 1600 | I41: =I71/I21 -> 1600 | J41: =J71/J21 -> 1600 | K41: =K71/K21 -> 1600 | N41: =N71/N21 -> 0 | O41: =O71/O21 -> 0 | P41: =P71/P21 -> 0 | Q41: =Q71/Q21 -> 0 | R41: =R71/R21 -> 0 | T41: =T71/T21 -> 0 | U41: =U71/U21 -> 0 | V41: =V71/V21 -> 0 | W41: =W71/W21 -> 0 | X41: =X71/X21 -> 0 | AC41: =AC71/AC21 -> 0 | AD41: =AD71/AD21 -> 0 | AE41: =AE71/AE21 -> 0 | AF41: =AF71/AF21 -> 0 | AG41: =AG71/AG21 -> 0 | AI41: =AI71/AI21 -> 0 | AJ41: =AJ71/AJ21 -> 0 | AK41: =AK71/AK21 -> 0 | AL41: =AL71/AL21 -> 0 | AM41: =AM71/AM21 -> 0 | AN41: =AN71/AN21 -> 0
A44: Доходы: Тарифы MPStats | G44: =SUM(G45:G49) -> 56555524 | H44: =SUM(H45:H49) -> 24072968 | I44: =SUM(I45:I49) -> 1313891.4 | J44: =SUM(J45:J49) -> 2674707.5 | K44: =SUM(G44:J44) -> 84617091 | N44: =SUM(N45:N49) -> 94480713 | O44: =SUM(O45:O49) -> 40132904 | P44: =SUM(P45:P49) -> 2192935.6 | Q44: =SUM(Q45:Q49) -> 4464190.4 | R44: =SUM(N44:Q44) -> 1.4127074e+08 | T44: =SUM(T45:T49) -> 16440755 | U44: =SUM(U45:U49) -> 6983597 | V44: =SUM(V45:V49) -> 381596.58 | W44: =SUM(W45:W49) -> 776821.6 | X44: =SUM(T44:W44) -> 24582770 | AC44: =SUM(AC45:AC49) -> 14304848 | AD44: =SUM(AD45:AD49) -> 5562237.6 | AE44: =SUM(AE45:AE49) -> 319451.3 | AF44: =SUM(AF45:AF49) -> 650311.57 | AG44: =SUM(AC44:AF44) -> 20836848 | AI44: =SUM(AI45:AI49) -> 12274496 | AJ44: =SUM(AJ45:AJ49) -> 8168180 | AK44: =SUM(AK45:AK49) -> 357132.65 | AL44: =SUM(AL45:AL49) -> 727020.04 | AM44: =SUM(AI44:AL44) -> 21526829 | AN44: =AM44+AG44 -> 42363677
A45: >100 млн | G45: =G$21*G88*G98 -> 16330.247 | H45: =H$21*H88*H98 -> 107671.8 | I45: =I$21*I88*I98 -> 2842.1423 | J45: =J$21*J88*J98 -> 5785.7896 | K45: =SUM(G45:J45) -> 132629.98 | N45: =N$21*N88*N98 -> 25624.564 | O45: =O$21*O88*O98 -> 168952.92 | P45: =P$21*P88*P98 -> 4459.7402 | Q45: =Q$21*Q88*Q98 -> 9078.7569 | R45: =SUM(N45:Q45) -> 208115.99 | T45: =T$21*T88*T98 -> 4458.9754 | U45: =U$21*U88*U98 -> 29399.795 | V45: =V$21*V88*V98 -> 776.04722 | W45: =W$21*W88*W98 -> 1579.8104 | X45: =SUM(T45:W45) -> 36214.628 | AC45: =AC$21*AC88*AC98 -> 0 | AD45: =AD$21*AD88*AD98 -> 0 | AE45: =AE$21*AE88*AE98 -> 0 | AF45: =AF$21*AF88*AF98 -> 0 | AG45: =SUM(AC45:AF45) -> 0 | AI45: =AI$21*AI88*AI98 -> 25624.564 | AJ45: =AJ$21*AJ88*AJ98 -> 168952.92 | AK45: =AK$21*AK88*AK98 -> 4459.7402 | AL45: =AL$21*AL88*AL98 -> 9078.7569 | AM45: =SUM(AI45:AL45) -> 208115.99 | AN45: =AM45+AG45 -> 208115.99
A46: 10-100 млн | G46: =G$21*G89*G99 -> 709938.67 | H46: =H$21*H89*H99 -> 811262.92 | I46: =I$21*I89*I99 -> 28940.814 | J46: =J$21*J89*J99 -> 58915.228 | K46: =SUM(G46:J46) -> 1609057.6 | N46: =N$21*N89*N99 -> 1136173.4 | O46: =O$21*O89*O99 -> 1298330.9 | P46: =P$21*P89*P99 -> 46316.371 | Q46: =Q$21*Q89*Q99 -> 94286.898 | R46: =SUM(N46:Q46) -> 2575107.6 | T46: =T$21*T89*T99 -> 197707.52 | U46: =U$21*U89*U99 -> 225924.85 | V46: =V$21*V89*V99 -> 8059.593 | W46: =W$21*W89*W99 -> 16407.029 | X46: =SUM(T46:W46) -> 448098.99 | AC46: =AC$21*AC89*AC99 -> 0 | AD46: =AD$21*AD89*AD99 -> 0 | AE46: =AE$21*AE89*AE99 -> 0 | AF46: =AF$21*AF89*AF99 -> 0 | AG46: =SUM(AC46:AF46) -> 0 | AI46: =AI$21*AI89*AI99 -> 1136173.4 | AJ46: =AJ$21*AJ89*AJ99 -> 1298330.9 | AK46: =AK$21*AK89*AK99 -> 46316.371 | AL46: =AL$21*AL89*AL99 -> 94286.898 | AM46: =SUM(AI46:AL46) -> 2575107.6 | AN46: =AM46+AG46 -> 2575107.6
A47: 1-10 млн | G47: =G$21*G90*G100 -> 6750219.7 | H47: =H$21*H90*H100 -> 4070345.5 | I47: =I$21*I90*I100 -> 186091.07 | J47: =J$21*J90*J100 -> 378828.25 | K47: =SUM(G47:J47) -> 11385485 | N47: =N$21*N90*N100 -> 11112698 | O47: =O$21*O90*O100 -> 6700896.2 | P47: =P$21*P90*P100 -> 306356.54 | Q47: =Q$21*Q90*Q100 -> 623654.38 | R47: =SUM(N47:Q47) -> 18743605 | T47: =T$21*T90*T100 -> 1933740.1 | U47: =U$21*U90*U100 -> 1166034.7 | V47: =V$21*V90*V100 -> 53309.639 | W47: =W$21*W90*W100 -> 108523.19 | X47: =SUM(T47:W47) -> 3261607.6 | AC47: =AC$21*AC90*AC100 -> 0 | AD47: =AD$21*AD90*AD100 -> 0 | AE47: =AE$21*AE90*AE100 -> 0 | AF47: =AF$21*AF90*AF100 -> 0 | AG47: =SUM(AC47:AF47) -> 0 | AI47: =AI$21*AI90*AI100 -> 11112698 | AJ47: =AJ$21*AJ90*AJ100 -> 6700896.2 | AK47: =AK$21*AK90*AK100 -> 306356.54 | AL47: =AL$21*AL90*AL100 -> 623654.38 | AM47: =SUM(AI47:AL47) -> 18743605 | AN47: =AM47+AG47 -> 18743605
A48: менее 1 млн | G48: =G$21*G91*G101 -> 49079036 | H48: =H$21*H91*H101 -> 19083688 | I48: =I$21*I91*I101 -> 1096017.4 | J48: =J$21*J91*J101 -> 2231178.2 | K48: =SUM(G48:J48) -> 71489919 | N48: =N$21*N91*N101 -> 82206217 | O48: =O$21*O91*O101 -> 31964724 | P48: =P$21*P91*P101 -> 1835803 | Q48: =Q$21*Q91*Q101 -> 3737170.4 | R48: =SUM(N48:Q48) -> 1.1974391e+08 | T48: =T$21*T91*T101 -> 14304848 | U48: =U$21*U91*U101 -> 5562237.6 | V48: =V$21*V91*V101 -> 319451.3 | W48: =W$21*W91*W101 -> 650311.57 | X48: =SUM(T48:W48) -> 20836848 | AC48: =AC$21*AC91*AC101 -> 14304848 | AD48: =AD$21*AD91*AD101 -> 5562237.6 | AE48: =AE$21*AE91*AE101 -> 319451.3 | AF48: =AF$21*AF91*AF101 -> 650311.57 | AG48: =SUM(AC48:AF48) -> 20836848 | AI48: =AI$21*AI91*AI101 -> 0 | AJ48: =AJ$21*AJ91*AJ101 -> 0 | AK48: =AK$21*AK91*AK101 -> 0 | AL48: =AL$21*AL91*AL101 -> 0 | AM48: =SUM(AI48:AL48) -> 0 | AN48: =AM48+AG48 -> 20836848
A49: без оборотов | G49: =G$21*G92*G102 -> 0 | H49: =H$21*H92*H102 -> 0 | I49: =I$21*I92*I102 -> 0 | J49: =J$21*J92*J102 -> 0 | K49: =SUM(G49:J49) -> 0 | N49: =N$21*N92*N102 -> 0 | O49: =O$21*O92*O102 -> 0 | P49: =P$21*P92*P102 -> 0 | Q49: =Q$21*Q92*Q102 -> 0 | R49: =SUM(N49:Q49) -> 0 | T49: =T$21*T92*T102 -> 0 | U49: =U$21*U92*U102 -> 0 | V49: =V$21*V92*V102 -> 0 | W49: =W$21*W92*W102 -> 0 | X49: =SUM(T49:W49) -> 0 | AC49: =AC$21*AC92*AC102 -> 0 | AD49: =AD$21*AD92*AD102 -> 0 | AE49: =AE$21*AE92*AE102 -> 0 | AF49: =AF$21*AF92*AF102 -> 0 | AG49: =SUM(AC49:AF49) -> 0 | AI49: =AI$21*AI92*AI102 -> 0 | AJ49: =AJ$21*AJ92*AJ102 -> 0 | AK49: =AK$21*AK92*AK102 -> 0 | AL49: =AL$21*AL92*AL102 -> 0 | AM49: =SUM(AI49:AL49) -> 0 | AN49: =AM49+AG49 -> 0
A50: Расходы: Тарифы MPStats | G50: =G51+G55+G71 -> 44317676 | H50: =H51+H55+H71 -> 18532119 | I50: =I51+I55+I71 -> 1021470.5 | J50: =J51+J55+J71 -> 2079422.1 | K50: =SUM(G50:J50) -> 65950688 | N50: =N51+N55+N71 -> 41943095 | O50: =O51+O55+O71 -> 17549414 | P50: =P51+P55+P71 -> 966990.14 | Q50: =Q51+Q55+Q71 -> 1968515.6 | R50: =SUM(N50:Q50) -> 62428015 | T50: =T51+T55+T71 -> 3677452.2 | U50: =U51+U55+U71 -> 1541176.5 | V50: =V51+V55+V71 -> 84843.932 | W50: =W51+W55+W71 -> 172718 | X50: =SUM(T50:W50) -> 5476190.6 | AC50: =AC51+AC55+AC71 -> 3248450.6 | AD50: =AD51+AD55+AD71 -> 1263114 | AE50: =AE51+AE55+AE71 -> 72543.362 | AF50: =AF51+AF55+AF71 -> 147677.56 | AG50: =SUM(AC50:AF50) -> 4731785.5 | AI50: =AI51+AI55+AI71 -> 4774545.3 | AJ50: =AJ51+AJ55+AJ71 -> 3086541.3 | AK50: =AK51+AK55+AK71 -> 136699.44 | AL50: =AL51+AL55+AL71 -> 278281.01 | AM50: =SUM(AI50:AL50) -> 8276067 | AN50: =AM50+AG50 -> 13007853
A51: Привлечение | G51: =G52+G53+G54 -> 36615566 | H51: =H52+H53+H54 -> 15295110 | I51: =I52+I53+I54 -> 843548.48 | J51: =J52+J53+J54 -> 1717223.7 | K51: =SUM(G51:J51) -> 54471448 | N51: =N52+N53+N54 -> 36615566 | O51: =O52+O53+O54 -> 15295110 | P51: =P52+P53+P54 -> 843548.48 | Q51: =Q52+Q53+Q54 -> 1717223.7 | R51: =SUM(N51:Q51) -> 54471448 | T51: =T52+T53+T54 -> 2720008.2 | U51: =U52+U53+U54 -> 1136206 | V51: =V52+V53+V54 -> 62663.48 | W51: =W52+W53+W54 -> 127564.94 | X51: =SUM(T51:W51) -> 4046442.6 | AC51: =AC52+AC53+AC54 -> 2412859.9 | AD51: =AD52+AD53+AD54 -> 938206.41 | AE51: =AE52+AE53+AE54 -> 53883.217 | AF51: =AF52+AF53+AF54 -> 109690.83 | AG51: =SUM(AC51:AF51) -> 3514640.3 | AI51: =AI52+AI53+AI54 -> 4134697 | AJ51: =AJ52+AJ53+AJ54 -> 2665383.7 | AK51: =AK52+AK53+AK54 -> 118196.08 | AL51: =AL52+AL53+AL54 -> 240613.46 | AM51: =SUM(AI51:AL51) -> 7158890.3 | AN51: =AM51+AG51 -> 10673531
A52: Привлечение (sales, КЦ MPStas) | G52: =G19*G149 -> 33895558 | H52: =H19*H149 -> 14158904 | I52: =I19*I149 -> 780885 | J52: =J19*J149 -> 1589658.8 | K52: =SUM(G52:J52) -> 50425005 | N52: =N19*N149 -> 33895558 | O52: =O19*O149 -> 14158904 | P52: =P19*P149 -> 780885 | Q52: =Q19*Q149 -> 1589658.7 | R52: =SUM(N52:Q52) -> 50425005 | T52: =T19*T149 -> 0 | U52: =U19*U149 -> 0 | V52: =V19*V149 -> 0 | W52: =W19*W149 -> 0 | X52: =SUM(T52:W52) -> 0 | AC52: =AC19*AC149 -> 0 | AD52: =AD19*AD149 -> 0 | AE52: =AE19*AE149 -> 0 | AF52: =AF19*AF149 -> 0 | AG52: =SUM(AC52:AF52) -> 0 | AI52: =AI19*AI149 -> 3827548.7 | AJ52: =AJ19*AJ149 -> 2467384.2 | AK52: =AK19*AK149 -> 109415.82 | AL52: =AL19*AL149 -> 222739.35 | AM52: =SUM(AI52:AL52) -> 6627088 | AN52: =AM52+AG52 -> 6627088
A53: Привлечение (триал - 14 дн) | G53: =G7*G160*G152 -> 703416 | H53: =H7*H160*H152 -> 293832 | I53: =I7*I160*I152 -> 16205.28 | J53: =J7*J160*J152 -> 32989.32 | K53: =SUM(G53:J53) -> 1046442.6 | N53: =N7*N160*N152 -> 703416 | O53: =O7*O160*O152 -> 293832 | P53: =P7*P160*P152 -> 16205.28 | Q53: =Q7*Q160*Q152 -> 32989.32 | R53: =SUM(N53:Q53) -> 1046442.6 | T53: =T7*T160*T152 -> 703416 | U53: =U7*U160*U152 -> 293832 | V53: =V7*V160*V152 -> 16205.28 | W53: =W7*W160*W152 -> 32989.32 | X53: =SUM(T53:W53) -> 1046442.6 | AC53: =AC7*AC160*AC152 -> 623984.97 | AD53: =AD7*AD160*AD152 -> 242627.72 | AE53: =AE7*AE160*AE152 -> 13934.633 | AF53: =AF7*AF160*AF152 -> 28366.932 | AG53: =SUM(AC53:AF53) -> 908914.26 | AI53: =AI7*AI160*AI152 -> 79431.028 | AJ53: =AJ7*AJ160*AJ152 -> 51204.276 | AK53: =AK7*AK160*AK152 -> 2270.6468 | AL53: =AL7*AL160*AL152 -> 4622.3881 | AM53: =SUM(AI53:AL53) -> 137528.34 | AN53: =AM53+AG53 -> 1046442.6
A54: Привлечение (маркетинг Т внешний) | G54: =G150*G21 -> 2016592.2 | H54: =H150*H21 -> 842373.96 | I54: =I150*I21 -> 46458.2 | J54: =J150*J21 -> 94575.622 | K54: =SUM(G54:J54) -> 3000000 | N54: =N150*N21 -> 2016592.2 | O54: =O150*O21 -> 842373.96 | P54: =P150*P21 -> 46458.2 | Q54: =Q150*Q21 -> 94575.622 | R54: =SUM(N54:Q54) -> 3000000 | T54: =T150*T21 -> 2016592.2 | U54: =U150*U21 -> 842373.96 | V54: =V150*V21 -> 46458.2 | W54: =W150*W21 -> 94575.622 | X54: =SUM(T54:W54) -> 3000000 | AC54: =AC150*AC21 -> 1788874.9 | AD54: =AD150*AD21 -> 695578.69 | AE54: =AE150*AE21 -> 39948.584 | AF54: =AF150*AF21 -> 81323.902 | AG54: =SUM(AC54:AF54) -> 2605726.1 | AI54: =AI150*AI21 -> 227717.3 | AJ54: =AJ150*AJ21 -> 146795.27 | AK54: =AK150*AK21 -> 6509.6168 | AL54: =AL150*AL21 -> 13251.72 | AM54: =SUM(AI54:AL54) -> 394273.91 | AN54: =AM54+AG54 -> 3000000
A55: API | G55: =G56+G65 -> 3378768 | H55: =H56+H65 -> 1431056.7 | I55: =I56+I65 -> 78320.992 | J55: =J56+J65 -> 159439.16 | K55: =SUM(G55:J55) -> 5047584.8 | N55: =N56+N65 -> 5327529.3 | O55: =O56+O65 -> 2254304.3 | P55: =P56+P65 -> 123441.66 | Q55: =Q56+Q65 -> 251291.94 | R55: =SUM(N55:Q55) -> 7956567.1 | T55: =T56+T65 -> 957443.97 | U55: =U56+U65 -> 404970.52 | V55: =V56+V65 -> 22180.452 | W55: =W56+W65 -> 45153.063 | X55: =SUM(T55:W55) -> 1429748 | AC55: =AC56+AC65 -> 835590.71 | AD55: =AD56+AD65 -> 324907.62 | AE55: =AE56+AE65 -> 18660.145 | AF55: =AF56+AF65 -> 37986.724 | AG55: =SUM(AC55:AF55) -> 1217145.2 | AI55: =AI56+AI65 -> 639848.21 | AJ55: =AJ56+AJ65 -> 421157.56 | AK55: =AK56+AK65 -> 18503.362 | AL55: =AL56+AL65 -> 37667.558 | AM55: =SUM(AI55:AL55) -> 1117176.7 | AN55: =AM55+AG55 -> 2334321.9
A56: Запросы к API МП (бесплатная версия Селлер) | G56: =G64+G63 -> 473030.44 | H56: =H64+H63 -> 197594.99 | I56: =I64+I63 -> 10897.663 | J56: =J64+J63 -> 22184.529 | K56: =SUM(G56:J56) -> 703707.62 | N56: =N64+N63 -> 473030.44 | O56: =O64+O63 -> 197594.99 | P56: =P64+P63 -> 10897.663 | Q56: =Q64+Q63 -> 22184.529 | R56: =SUM(N56:Q56) -> 703707.62 | T56: =T64+T63 -> 112704.11 | U56: =U64+U63 -> 47078.931 | V56: =V64+V63 -> 2596.4744 | W56: =W64+W63 -> 5285.68 | X56: =SUM(T56:W56) -> 167665.19 | AC56: =AC64+AC63 -> 99977.353 | AD56: =AD64+AD63 -> 38874.779 | AE56: =AE64+AE63 -> 2232.6623 | AF56: =AF64+AF63 -> 4545.0626 | AG56: =SUM(AC56:AF56) -> 145629.86 | AI56: =AI64+AI63 -> 12726.755 | AJ56: =AJ64+AJ63 -> 8204.1527 | AK56: =AK64+AK63 -> 363.81205 | AL56: =AL64+AL63 -> 740.61739 | AM56: =SUM(AI56:AL56) -> 22035.337 | AN56: =AM56+AG56 -> 167665.19
A57: Запросы к API МП (бесплатная версия Селлер) - платящие | G57: =SUM(G58:G62) -> 341500.92 | H57: =SUM(H58:H62) -> 144964.33 | I57: =SUM(I58:I62) -> 7924.0222 | J57: =SUM(J58:J62) -> 16131.045 | K57: =SUM(G57:J57) -> 510520.32 | N57: =SUM(N58:N62) -> 570531.85 | O57: =SUM(O58:O62) -> 241717.67 | P57: =SUM(P58:P62) -> 13226.892 | Q57: =SUM(Q58:Q62) -> 26926.173 | R57: =SUM(N57:Q57) -> 852402.58 | T57: =SUM(T58:T62) -> 99279.247 | U57: =SUM(U58:U62) -> 42061.715 | V57: =SUM(V58:V62) -> 2301.6347 | W57: =SUM(W58:W62) -> 4685.4706 | X57: =SUM(T57:W57) -> 148328.07 | AC57: =SUM(AC58:AC62) -> 86454 | AD57: =SUM(AD58:AD62) -> 33616.414 | AE57: =SUM(AE58:AE62) -> 1930.6631 | AF57: =SUM(AF58:AF62) -> 3930.2785 | AG57: =SUM(AC57:AF57) -> 125931.36 | AI57: =SUM(AI58:AI62) -> 73703.337 | AJ57: =SUM(AJ58:AJ62) -> 48532.934 | AK57: =SUM(AK58:AK62) -> 2131.8762 | AL57: =SUM(AL58:AL62) -> 4339.8909 | AM57: =SUM(AI57:AL57) -> 128708.04 | AN57: =AM57+AG57 -> 254639.39
A58: >100 млн | G58: =(G22*G$156*G123) -> 74.718301 | H58: =(H22*H$156*H123) -> 492.64741 | I58: =(I22*I$156*I123) -> 13.004093 | J58: =(J22*J$156*J123) -> 26.472617 | K58: =SUM(G58:J58) -> 606.84242 | N58: =(N22*N$156*N123) -> 117.24403 | O58: =(O22*O$156*O123) -> 773.03642 | P58: =(P22*P$156*P123) -> 20.405338 | Q58: =(Q22*Q$156*Q123) -> 41.539439 | R58: =SUM(N58:Q58) -> 952.22523 | T58: =(T22*T$156*T123) -> 20.401839 | U58: =(U22*U$156*U123) -> 134.51742 | V58: =(V22*V$156*V123) -> 3.5507687 | W58: =(W22*W$156*W123) -> 7.2283506 | X58: =SUM(T58:W58) -> 165.69838 | AC58: =(AC22*AC$156*AC123) -> 0 | AD58: =(AD22*AD$156*AD123) -> 0 | AE58: =(AE22*AE$156*AE123) -> 0 | AF58: =(AF22*AF$156*AF123) -> 0 | AG58: =SUM(AC58:AF58) -> 0 | AI58: =(AI22*AI$156*AI123) -> 117.24403 | AJ58: =(AJ22*AJ$156*AJ123) -> 773.03642 | AK58: =(AK22*AK$156*AK123) -> 20.405338 | AL58: =(AL22*AL$156*AL123) -> 41.539439 | AM58: =SUM(AI58:AL58) -> 952.22523 | AN58: =AM58+AG58 -> 952.22523
A59: 10-100 млн | G59: =(G23*G$156*G124) -> 3922.2033 | H59: =(H23*H$156*H124) -> 4481.9902 | I59: =(I23*I$156*I124) -> 159.88953 | J59: =(J23*J$156*J124) -> 325.48939 | K59: =SUM(G59:J59) -> 8889.5724 | N59: =(N23*N$156*N124) -> 6277.0254 | O59: =(O23*O$156*O124) -> 7172.8984 | P59: =(P23*P$156*P124) -> 255.88439 | Q59: =(Q23*Q$156*Q124) -> 520.90752 | R59: =SUM(N59:Q59) -> 14226.716 | T59: =(T23*T$156*T124) -> 1092.2762 | U59: =(U23*U$156*U124) -> 1248.1686 | V59: =(V23*V$156*V124) -> 44.526892 | W59: =(W23*W$156*W124) -> 90.64403 | X59: =SUM(T59:W59) -> 2475.6158 | AC59: =(AC23*AC$156*AC124) -> 0 | AD59: =(AD23*AD$156*AD124) -> 0 | AE59: =(AE23*AE$156*AE124) -> 0 | AF59: =(AF23*AF$156*AF124) -> 0 | AG59: =SUM(AC59:AF59) -> 0 | AI59: =(AI23*AI$156*AI124) -> 6277.0254 | AJ59: =(AJ23*AJ$156*AJ124) -> 7172.8984 | AK59: =(AK23*AK$156*AK124) -> 255.88439 | AL59: =(AL23*AL$156*AL124) -> 520.90752 | AM59: =SUM(AI59:AL59) -> 14226.716 | AN59: =AM59+AG59 -> 14226.716
A60: 1-10 млн | G60: =(G24*G$156*G125) -> 40885.749 | H60: =(H24*H$156*H125) -> 24653.883 | I60: =(I24*I$156*I125) -> 1127.1445 | J60: =(J24*J$156*J125) -> 2294.5441 | K60: =SUM(G60:J60) -> 68961.32 | N60: =(N24*N$156*N125) -> 67309.068 | O60: =(O24*O$156*O125) -> 40586.999 | P60: =(P24*P$156*P125) -> 1855.5865 | Q60: =(Q24*Q$156*Q125) -> 3777.4439 | R60: =SUM(N60:Q60) -> 113529.1 | T60: =(T24*T$156*T125) -> 11712.569 | U60: =(U24*U$156*U125) -> 7062.6149 | V60: =(V24*V$156*V125) -> 322.89386 | W60: =(W24*W$156*W125) -> 657.31965 | X60: =SUM(T60:W60) -> 19755.397 | AC60: =(AC24*AC$156*AC125) -> 0 | AD60: =(AD24*AD$156*AD125) -> 0 | AE60: =(AE24*AE$156*AE125) -> 0 | AF60: =(AF24*AF$156*AF125) -> 0 | AG60: =SUM(AC60:AF60) -> 0 | AI60: =(AI24*AI$156*AI125) -> 67309.068 | AJ60: =(AJ24*AJ$156*AJ125) -> 40586.999 | AK60: =(AK24*AK$156*AK125) -> 1855.5865 | AL60: =(AL24*AL$156*AL125) -> 3777.4439 | AM60: =SUM(AI60:AL60) -> 113529.1 | AN60: =AM60+AG60 -> 113529.1
A61: менее 1 млн | G61: =(G25*G$156*G126) -> 296618.25 | H61: =(H25*H$156*H126) -> 115335.81 | I61: =(I25*I$156*I126) -> 6623.9841 | J61: =(J25*J$156*J126) -> 13484.539 | K61: =SUM(G61:J61) -> 432062.58 | N61: =(N25*N$156*N126) -> 496828.51 | O61: =(O25*O$156*O126) -> 193184.73 | P61: =(P25*P$156*P126) -> 11095.016 | Q61: =(Q25*Q$156*Q126) -> 22586.282 | R61: =SUM(N61:Q61) -> 723694.54 | T61: =(T25*T$156*T126) -> 86454 | U61: =(U25*U$156*U126) -> 33616.414 | V61: =(V25*V$156*V126) -> 1930.6631 | W61: =(W25*W$156*W126) -> 3930.2785 | X61: =SUM(T61:W61) -> 125931.36 | AC61: =(AC25*AC$156*AC126) -> 86454 | AD61: =(AD25*AD$156*AD126) -> 33616.414 | AE61: =(AE25*AE$156*AE126) -> 1930.6631 | AF61: =(AF25*AF$156*AF126) -> 3930.2785 | AG61: =SUM(AC61:AF61) -> 125931.36 | AI61: =(AI25*AI$156*AI126) -> 0 | AJ61: =(AJ25*AJ$156*AJ126) -> 0 | AK61: =(AK25*AK$156*AK126) -> 0 | AL61: =(AL25*AL$156*AL126) -> 0 | AM61: =SUM(AI61:AL61) -> 0 | AN61: =AM61+AG61 -> 125931.36
A62: без оборотов | G62: =(G26*G$156*G127) -> 0 | H62: =(H26*H$156*H127) -> 0 | I62: =(I26*I$156*I127) -> 0 | J62: =(J26*J$156*J127) -> 0 | K62: =SUM(G62:J62) -> 0 | N62: =(N26*N$156*N127) -> 0 | O62: =(O26*O$156*O127) -> 0 | P62: =(P26*P$156*P127) -> 0 | Q62: =(Q26*Q$156*Q127) -> 0 | R62: =SUM(N62:Q62) -> 0 | T62: =(T26*T$156*T127) -> 0 | U62: =(U26*U$156*U127) -> 0 | V62: =(V26*V$156*V127) -> 0 | W62: =(W26*W$156*W127) -> 0 | X62: =SUM(T62:W62) -> 0 | AC62: =(AC26*AC$156*AC127) -> 0 | AD62: =(AD26*AD$156*AD127) -> 0 | AE62: =(AE26*AE$156*AE127) -> 0 | AF62: =(AF26*AF$156*AF127) -> 0 | AG62: =SUM(AC62:AF62) -> 0 | AI62: =(AI26*AI$156*AI127) -> 0 | AJ62: =(AJ26*AJ$156*AJ127) -> 0 | AK62: =(AK26*AK$156*AK127) -> 0 | AL62: =(AL26*AL$156*AL127) -> 0 | AM62: =SUM(AI62:AL62) -> 0 | AN62: =AM62+AG62 -> 0
A63: Запросы к API МП (бесплатная версия Селлер) - НЕ платящие + платящие МПСтатс (12 мес) | G63: =G167*G161*G157*12 -> 435702.94 | H63: =H167*H161*H157*12 -> 182002.49 | I63: =I167*I161*I157*12 -> 10037.713 | J63: =J167*J161*J157*12 -> 20433.916 | K63: =SUM(G63:J63) -> 648177.06 | N63: =N167*N161*N157*12 -> 435702.94 | O63: =O167*O161*O157*12 -> 182002.49 | P63: =P167*P161*P157*12 -> 10037.713 | Q63: =Q167*Q161*Q157*12 -> 20433.916 | R63: =SUM(N63:Q63) -> 648177.06 | T63: =T167*T161*T157*T165 -> 75376.608 | U63: =U167*U161*U157*U165 -> 31486.431 | V63: =V167*V161*V157*V165 -> 1736.5244 | W63: =W167*W161*W157*W165 -> 3535.0675 | X63: =SUM(T63:W63) -> 112134.63 | AC63: =AC167*AC161*AC157*AC165 -> 66864.943 | AD63: =AD167*AD161*AD157*AD165 -> 25999.487 | AE63: =AE167*AE161*AE157*AE165 -> 1493.2066 | AF63: =AF167*AF161*AF157*AF165 -> 3039.7419 | AG63: =SUM(AC63:AF63) -> 97397.378 | AI63: =AI167*AI161*AI157*AI165 -> 8511.6652 | AJ63: =AJ167*AJ161*AJ157*AJ165 -> 5486.9447 | AK63: =AK167*AK161*AK157*AK165 -> 243.31783 | AL63: =AL167*AL161*AL157*AL165 -> 495.32557 | AM63: =SUM(AI63:AL63) -> 14737.253 | AN63: =AM63+AG63 -> 112134.63
A64: Запросы к API МП (бесплатная версия Селлер) - лиды | G64: =G7*G159*G158 -> 37327.5 | H64: =H7*H159*H158 -> 15592.5 | I64: =I7*I159*I158 -> 859.95 | J64: =J7*J159*J158 -> 1750.6125 | K64: =SUM(G64:J64) -> 55530.562 | N64: =N7*N159*N158 -> 37327.5 | O64: =O7*O159*O158 -> 15592.5 | P64: =P7*P159*P158 -> 859.95 | Q64: =Q7*Q159*Q158 -> 1750.6125 | R64: =SUM(N64:Q64) -> 55530.562 | T64: =T7*T159*T158 -> 37327.5 | U64: =U7*U159*U158 -> 15592.5 | V64: =V7*V159*V158 -> 859.95 | W64: =W7*W159*W158 -> 1750.6125 | X64: =SUM(T64:W64) -> 55530.562 | AC64: =AC7*AC159*AC158 -> 33112.41 | AD64: =AD7*AD159*AD158 -> 12875.292 | AE64: =AE7*AE159*AE158 -> 739.45577 | AF64: =AF7*AF159*AF158 -> 1505.3207 | AG64: =SUM(AC64:AF64) -> 48232.478 | AI64: =AI7*AI159*AI158 -> 4215.0899 | AJ64: =AJ7*AJ159*AJ158 -> 2717.2081 | AK64: =AK7*AK159*AK158 -> 120.49423 | AL64: =AL7*AL159*AL158 -> 245.29182 | AM64: =SUM(AI64:AL64) -> 7298.084 | AN64: =AM64+AG64 -> 55530.563
A65: Запросы к API МП (за MPStats) | G65: =SUM(G66:G70) -> 2905737.6 | H65: =SUM(H66:H70) -> 1233461.7 | I65: =SUM(I66:I70) -> 67423.329 | J65: =SUM(J66:J70) -> 137254.63 | K65: =SUM(G65:J65) -> 4343877.2 | N65: =SUM(N66:N70) -> 4854498.8 | O65: =SUM(O66:O70) -> 2056709.3 | P65: =SUM(P66:P70) -> 112543.99 | Q65: =SUM(Q66:Q70) -> 229107.41 | R65: =SUM(N65:Q65) -> 7252859.5 | T65: =SUM(T66:T70) -> 844739.86 | U65: =SUM(U66:U70) -> 357891.59 | V65: =SUM(V66:V70) -> 19583.977 | W65: =SUM(W66:W70) -> 39867.383 | X65: =SUM(T65:W65) -> 1262082.8 | AC65: =SUM(AC66:AC70) -> 735613.35 | AD65: =SUM(AD66:AD70) -> 286032.84 | AE65: =SUM(AE66:AE70) -> 16427.483 | AF65: =SUM(AF66:AF70) -> 33441.661 | AG65: =SUM(AC65:AF65) -> 1071515.3 | AI65: =SUM(AI66:AI70) -> 627121.46 | AJ65: =SUM(AJ66:AJ70) -> 412953.41 | AK65: =SUM(AK66:AK70) -> 18139.55 | AL65: =SUM(AL66:AL70) -> 36926.94 | AM65: =SUM(AI65:AL65) -> 1095141.4 | AN65: =AM65+AG65 -> 2166656.7
A66: >100 млн | G66: =G22*G123*G$155 -> 635.75751 | H66: =H22*H123*H$155 -> 4191.8016 | I66: =I22*I123*I$155 -> 110.64825 | J66: =J22*J123*J$155 -> 225.24823 | K66: =SUM(G66:J66) -> 5163.4556 | N66: =N22*N123*N$155 -> 997.59725 | O66: =O22*O123*O$155 -> 6577.5547 | P66: =P22*P123*P$155 -> 173.62342 | Q66: =Q22*Q123*Q$155 -> 353.44768 | R66: =SUM(N66:Q66) -> 8102.223 | T66: =T22*T123*T$155 -> 173.59365 | U66: =U22*U123*U$155 -> 1144.5718 | V66: =V22*V123*V$155 -> 30.212516 | W66: =W22*W123*W$155 -> 61.504051 | X66: =SUM(T66:W66) -> 1409.882 | AC66: =AC22*AC123*AC$155 -> 0 | AD66: =AD22*AD123*AD$155 -> 0 | AE66: =AE22*AE123*AE$155 -> 0 | AF66: =AF22*AF123*AF$155 -> 0 | AG66: =SUM(AC66:AF66) -> 0 | AI66: =AI22*AI123*AI$155 -> 997.59725 | AJ66: =AJ22*AJ123*AJ$155 -> 6577.5547 | AK66: =AK22*AK123*AK$155 -> 173.62342 | AL66: =AL22*AL123*AL$155 -> 353.44768 | AM66: =SUM(AI66:AL66) -> 8102.223 | AN66: =AM66+AG66 -> 8102.223
A67: 10-100 млн | G67: =G23*G124*G$155 -> 33372.951 | H67: =H23*H124*H$155 -> 38136.024 | I67: =I23*I124*I$155 -> 1360.4561 | J67: =J23*J124*J$155 -> 2769.4999 | K67: =SUM(G67:J67) -> 75638.931 | N67: =N23*N124*N$155 -> 53409.486 | O67: =O23*O124*O$155 -> 61032.224 | P67: =P23*P124*P$155 -> 2177.2501 | Q67: =Q23*Q124*Q$155 -> 4432.259 | R67: =SUM(N67:Q67) -> 121051.22 | T67: =T23*T124*T$155 -> 9293.8783 | U67: =U23*U124*U$155 -> 10620.324 | V67: =V23*V124*V$155 -> 378.8671 | W67: =W23*W124*W$155 -> 771.26517 | X67: =SUM(T67:W67) -> 21064.335 | AC67: =AC23*AC124*AC$155 -> 0 | AD67: =AD23*AD124*AD$155 -> 0 | AE67: =AE23*AE124*AE$155 -> 0 | AF67: =AF23*AF124*AF$155 -> 0 | AG67: =SUM(AC67:AF67) -> 0 | AI67: =AI23*AI124*AI$155 -> 53409.486 | AJ67: =AJ23*AJ124*AJ$155 -> 61032.224 | AK67: =AK23*AK124*AK$155 -> 2177.2501 | AL67: =AL23*AL124*AL$155 -> 4432.259 | AM67: =SUM(AI67:AL67) -> 121051.22 | AN67: =AM67+AG67 -> 121051.22
A68: 1-10 млн | G68: =G24*G125*G$155 -> 347885.61 | H68: =H24*H125*H$155 -> 209773.12 | I68: =I24*I125*I$155 -> 9590.5629 | J68: =J24*J125*J$155 -> 19523.646 | K68: =SUM(G68:J68) -> 586772.94 | N68: =N24*N125*N$155 -> 572714.38 | O68: =O24*O125*O$155 -> 345343.63 | P68: =P24*P125*P$155 -> 15788.676 | Q68: =Q24*Q125*Q$155 -> 32141.233 | R68: =SUM(N68:Q68) -> 965987.92 | T68: =T24*T125*T$155 -> 99659.033 | U68: =U24*U125*U$155 -> 60093.851 | V68: =V24*V125*V$155 -> 2747.4152 | W68: =W24*W125*W$155 -> 5592.9524 | X68: =SUM(T68:W68) -> 168093.25 | AC68: =AC24*AC125*AC$155 -> 0 | AD68: =AD24*AD125*AD$155 -> 0 | AE68: =AE24*AE125*AE$155 -> 0 | AF68: =AF24*AF125*AF$155 -> 0 | AG68: =SUM(AC68:AF68) -> 0 | AI68: =AI24*AI125*AI$155 -> 572714.38 | AJ68: =AJ24*AJ125*AJ$155 -> 345343.63 | AK68: =AK24*AK125*AK$155 -> 15788.676 | AL68: =AL24*AL125*AL$155 -> 32141.233 | AM68: =SUM(AI68:AL68) -> 965987.92 | AN68: =AM68+AG68 -> 965987.92
A69: менее 1 млн | G69: =G25*G126*G$155 -> 2523843.2 | H69: =H25*H126*H$155 -> 981360.72 | I69: =I25*I126*I$155 -> 56361.662 | J69: =J25*J126*J$155 -> 114736.24 | K69: =SUM(G69:J69) -> 3676301.9 | N69: =N25*N126*N$155 -> 4227377.4 | O69: =O25*O126*O$155 -> 1643755.9 | P69: =P25*P126*P$155 -> 94404.442 | Q69: =Q25*Q126*Q$155 -> 192180.47 | R69: =SUM(N69:Q69) -> 6157718.2 | T69: =T25*T126*T$155 -> 735613.35 | U69: =U25*U126*U$155 -> 286032.84 | V69: =V25*V126*V$155 -> 16427.483 | W69: =W25*W126*W$155 -> 33441.661 | X69: =SUM(T69:W69) -> 1071515.3 | AC69: =AC25*AC126*AC$155 -> 735613.35 | AD69: =AD25*AD126*AD$155 -> 286032.84 | AE69: =AE25*AE126*AE$155 -> 16427.483 | AF69: =AF25*AF126*AF$155 -> 33441.661 | AG69: =SUM(AC69:AF69) -> 1071515.3 | AI69: =AI25*AI126*AI$155 -> 0 | AJ69: =AJ25*AJ126*AJ$155 -> 0 | AK69: =AK25*AK126*AK$155 -> 0 | AL69: =AL25*AL126*AL$155 -> 0 | AM69: =SUM(AI69:AL69) -> 0 | AN69: =AM69+AG69 -> 1071515.3
A70: без оборотов | G70: =G26*G127*G$155 -> 0 | H70: =H26*H127*H$155 -> 0 | I70: =I26*I127*I$155 -> 0 | J70: =J26*J127*J$155 -> 0 | K70: =SUM(G70:J70) -> 0 | N70: =N26*N127*N$155 -> 0 | O70: =O26*O127*O$155 -> 0 | P70: =P26*P127*P$155 -> 0 | Q70: =Q26*Q127*Q$155 -> 0 | R70: =SUM(N70:Q70) -> 0 | T70: =T26*T127*T$155 -> 0 | U70: =U26*U127*U$155 -> 0 | V70: =V26*V127*V$155 -> 0 | W70: =W26*W127*W$155 -> 0 | X70: =SUM(T70:W70) -> 0 | AC70: =AC26*AC127*AC$155 -> 0 | AD70: =AD26*AD127*AD$155 -> 0 | AE70: =AE26*AE127*AE$155 -> 0 | AF70: =AF26*AF127*AF$155 -> 0 | AG70: =SUM(AC70:AF70) -> 0 | AI70: =AI26*AI127*AI$155 -> 0 | AJ70: =AJ26*AJ127*AJ$155 -> 0 | AK70: =AK26*AK127*AK$155 -> 0 | AL70: =AL26*AL127*AL$155 -> 0 | AM70: =SUM(AI70:AL70) -> 0 | AN70: =AM70+AG70 -> 0
A71: Продление и удержание MPStas | G71: =G21*G170 -> 4323342.1 | H71: =H21*H170 -> 1805953 | I71: =I21*I170 -> 99601.045 | J71: =J21*J170 -> 202759.27 | K71: =SUM(G71:J71) -> 6431655.4 | N71: =N21*N170 -> 0 | O71: =O21*O170 -> 0 | P71: =P21*P170 -> 0 | Q71: =Q21*Q170 -> 0 | R71: =SUM(N71:Q71) -> 0 | T71: =T19*T170 -> 0 | U71: =U19*U170 -> 0 | V71: =V19*V170 -> 0 | W71: =W19*W170 -> 0 | X71: =SUM(T71:W71) -> 0 | AC71: =AC19*AC170 -> 0 | AD71: =AD19*AD170 -> 0 | AE71: =AE19*AE170 -> 0 | AF71: =AF19*AF170 -> 0 | AG71: =SUM(AC71:AF71) -> 0 | AI71: =AI21*AI170 -> 0 | AJ71: =AJ21*AJ170 -> 0 | AK71: =AK21*AK170 -> 0 | AL71: =AL21*AL170 -> 0 | AM71: =SUM(AI71:AL71) -> 0 | AN71: =AM71+AG71 -> 0
A75: Потенциальная прибыль: тарифы MPStats Доходы - Расходы на привлечение, API, продление и удержание | G75: =G44-G50 -> 12237848 | H75: =H44-H50 -> 5540849 | I75: =I44-I50 -> 292420.87 | J75: =J44-J50 -> 595285.34 | K75: =SUM(G75:J75) -> 18666403 | N75: =N44-N50 -> 52537618 | O75: =O44-O50 -> 22583490 | P75: =P44-P50 -> 1225945.5 | Q75: =Q44-Q50 -> 2495674.8 | R75: =SUM(N75:Q75) -> 78842728 | T75: =T44-T50 -> 12763302 | U75: =U44-U50 -> 5442420.5 | V75: =V44-V50 -> 296752.64 | W75: =W44-W50 -> 604103.6 | X75: =SUM(T75:W75) -> 19106579 | AC75: =AC44-AC50 -> 11056397 | AD75: =AD44-AD50 -> 4299123.6 | AE75: =AE44-AE50 -> 246907.94 | AF75: =AF44-AF50 -> 502634.01 | AG75: =SUM(AC75:AF75) -> 16105063 | AI75: =AI44-AI50 -> 7499951 | AJ75: =AJ44-AJ50 -> 5081638.8 | AK75: =AK44-AK50 -> 220433.2 | AL75: =AL44-AL50 -> 448739.02 | AM75: =SUM(AI75:AL75) -> 13250762 | AN75: =AM75+AG75 -> 29355825
R76: =R75/K75 -> 4.2237771
A77: Потенциальная прибыль: продукты Т-Банк (влияние MPStats) NVP от всех продуктов Т-Банк | G77: =G19*G142 -> 0 | H77: =H19*H142 -> 0 | I77: =I6*I142 -> 5200000 | J77: =J6*J142 -> 49320000 | K77: =SUM(G77:J77) -> 54520000 | N77: =N21*N143 -> 31734787 | O77: =O21*O143 -> 13256304 | P77: =P6*P142 -> 6240000 | Q77: =Q6*Q142 -> 59184000 | R77: =SUM(N77:Q77) -> 1.1041509e+08 | T77: =T21*T143 -> 5522226 | U77: =U21*U143 -> 2306752.6 | V77: =V6*V142 -> 6240000 | W77: =W6*W142 -> 59184000 | X77: =SUM(T77:W77) -> 73252979 | AC77: =AC21*AC143 -> 4898646.1 | AD77: =AD21*AD143 -> 1904769.2 | AE77: =AE6*AE142 -> 5365665.5 | AF77: =AF6*AF142 -> 50891273 | AG77: =SUM(AC77:AF77) -> 63060354 | AI77: =AI21*AI143 -> 3583550.5 | AJ77: =AJ21*AJ143 -> 2310093.6 | AK77: =AK6*AK142 -> 874334.53 | AL77: =AL6*AL142 -> 8292726.7 | AM77: =SUM(AI77:AL77) -> 15060705 | AN77: =AM77+AG77 -> 78121059
A79: Потенциальная прибыль: всего | G79: =G75+G77 -> 12237848 | H79: =H75+H77 -> 5540849 | I79: =I75+I77 -> 5492420.9 | J79: =J75+J77 -> 49915285 | K79: =SUM(G79:J79) -> 73186403 | N79: =N75+N77 -> 84272405 | O79: =O75+O77 -> 35839793 | P79: =P75+P77 -> 7465945.5 | Q79: =Q75+Q77 -> 61679675 | R79: =SUM(N79:Q79) -> 1.8925782e+08 | T79: =T75+T77 -> 18285528 | U79: =U75+U77 -> 7749173.1 | V79: =V75+V77 -> 6536752.6 | W79: =W75+W77 -> 59788104 | X79: =SUM(T79:W79) -> 92359558 | AC79: =AC75+AC77 -> 15955043 | AD79: =AD75+AD77 -> 6203892.8 | AE79: =AE75+AE77 -> 5612573.4 | AF79: =AF75+AF77 -> 51393907 | AG79: =SUM(AC79:AF79) -> 79165417 | AI79: =AI75+AI77 -> 11083502 | AJ79: =AJ75+AJ77 -> 7391732.4 | AK79: =AK75+AK77 -> 1094767.7 | AL79: =AL75+AL77 -> 8741465.7 | AM79: =SUM(AI79:AL79) -> 28311467 | AN79: =AM79+AG79 -> 1.0747688e+08
R80: =R79/K79 -> 2.5859697
R81: =R79-K79 -> 1.1607142e+08
A82: Данные для расчета:
A84: Данные для расчета
A85: LTV - тарифы MPStats
A86: Распределение селлров as is
A87: Распределение селлеров по сегментам по оборотам в Т-Банке (акт РКО/ не утиль Озони ВБ) | G87: без учета пересечений баз с MPStats (нет данных) | N87: без учета пересечений баз с MPStats (нет данных) | T87: без учета пересечений баз с MPStats (нет данных)
A88: >100 млн | G88: ='База селлеров'!B38 -> 0.0001091635 | H88: ='База селлеров'!C38 -> 0.0017230576 | I88: ='База селлеров'!D38 -> 0.00082468141 | J88: ='База селлеров'!E38 -> 0.00082468141 | N88: =G88 -> 0.0001091635 | O88: =H88 -> 0.0017230576 | P88: =I88 -> 0.00082468141 | Q88: =J88 -> 0.00082468141 | T88: =N88 -> 0.0001091635 | U88: =O88 -> 0.0017230576 | V88: =P88 -> 0.00082468141 | W88: =Q88 -> 0.00082468141 | AC88: 0 | AD88: 0 | AE88: 0 | AF88: 0 | AI88: =T88/(T88+T89+T90) -> 0.0009667173 | AJ88: =U88/(U88+U89+U90) -> 0.0098876404 | AK88: =V88/(V88+V89+V90) -> 0.0058856329 | AL88: =W88/(W88+W89+W90) -> 0.0058856329
A89: 10-100 млн | G89: ='База селлеров'!B39 -> 0.0075010916 | H89: ='База селлеров'!C39 -> 0.02052005 | I89: ='База селлеров'!D39 -> 0.01327303 | J89: =I89 -> 0.01327303 | N89: =G89 -> 0.0075010916 | O89: =H89 -> 0.02052005 | P89: =I89 -> 0.01327303 | Q89: =J89 -> 0.01327303 | T89: =N89 -> 0.0075010916 | U89: =O89 -> 0.02052005 | V89: =P89 -> 0.01327303 | W89: =Q89 -> 0.01327303 | AC89: 0 | AD89: 0 | AE89: 0 | AF89: 0 | AI89: =T89/(T88+T89+T90) -> 0.066427289 | AJ89: =U89/(U88+U89+U90) -> 0.11775281 | AK89: =V89/(V88+V89+V90) -> 0.094727712 | AL89: =W89/(W88+W89+W90) -> 0.094727712
A90: 1-10 млн | G90: ='База селлеров'!B40 -> 0.10531158 | H90: ='База селлеров'!C40 -> 0.15202068 | I90: ='База селлеров'!D40 -> 0.12602 | J90: ='База селлеров'!E40 -> 0.12602 | N90: =G90 -> 0.10531158 | O90: =H90 -> 0.15202068 | P90: =I90 -> 0.12602 | Q90: =J90 -> 0.12602 | T90: =N90 -> 0.10531158 | U90: =O90 -> 0.15202068 | V90: =P90 -> 0.12602 | W90: =Q90 -> 0.12602 | AC90: 0 | AD90: 0 | AE90: 0 | AF90: 0 | AI90: =T90/(T88+T89+T90) -> 0.93260599 | AJ90: =U90/(U88+U89+U90) -> 0.87235955 | AK90: =V90/(V88+V89+V90) -> 0.89938666 | AL90: =W90/(W88+W89+W90) -> 0.89938666
A91: менее 1 млн | G91: ='База селлеров'!B41 -> 0.88707816 | H91: ='База селлеров'!C41 -> 0.82573622 | I91: ='База селлеров'!D41 -> 0.85988229 | J91: ='База селлеров'!E41 -> 0.85988229 | N91: =G91 -> 0.88707816 | O91: =H91 -> 0.82573622 | P91: =I91 -> 0.85988229 | Q91: =J91 -> 0.85988229 | T91: =N91 -> 0.88707816 | U91: =O91 -> 0.82573622 | V91: =P91 -> 0.85988229 | W91: =Q91 -> 0.85988229 | AC91: 1 | AD91: 1 | AE91: 1 | AF91: 1 | AI91: 0 | AJ91: 0 | AK91: 0 | AL91: 0
A92: без оборотов | G92: 0 | H92: 0 | I92: 0 | J92: 0 | N92: =G92 -> 0 | O92: =H92 -> 0 | P92: =I92 -> 0 | Q92: =J92 -> 0 | T92: =N92 -> 0 | U92: =O92 -> 0 | V92: =P92 -> 0 | W92: =Q92 -> 0 | AC92: 0 | AD92: 0 | AE92: 0 | AF92: 0 | AI92: =AC92 -> 0 | AJ92: =AD92 -> 0 | AK92: =AE92 -> 0 | AL92: =AF92 -> 0
A96: LTV гипотеза: тарифы MPStats | G96: скидка 50% от тарифов MPS | M96: LT выше (досписания-люготный период) | N96: гипотеза: +1 мес к LT (за счет досписания с РКО на след мес при недостатке ДС) | T96: гипотеза: +1 мес к LT (за счет досписания с РКО на след мес при недостатке ДС)
A97: Сегмент по обороту
A98: >100 млн | G98: =G107/2 -> 55362.5 | H98: =H107/2 -> 55362.5 | I98: =I107/2 -> 55362.5 | J98: =J107/2 -> 55362.5 | N98: =N115/2*N123 -> 59174.344 | O98: =N98 -> 59174.344 | P98: =O98 -> 59174.344 | Q98: =P98 -> 59174.344 | T98: =N98 -> 59174.344 | U98: =T98 -> 59174.344 | V98: =U98 -> 59174.344 | W98: =V98 -> 59174.344 | AC98: =T98 -> 59174.344 | AD98: =AC98 -> 59174.344 | AE98: =AD98 -> 59174.344 | AF98: =AE98 -> 59174.344 | AI98: =AC98 -> 59174.344 | AJ98: =AI98 -> 59174.344 | AK98: =AJ98 -> 59174.344 | AL98: =AK98 -> 59174.344
A99: 10 + млн | G99: =G108/2 -> 35026.5 | H99: =H108/2 -> 35026.5 | I99: =I108/2 -> 35026.5 | J99: =J108/2 -> 35026.5 | N99: =N116/2*N124 -> 38183.395 | O99: =N99 -> 38183.395 | P99: =O99 -> 38183.395 | Q99: =P99 -> 38183.395 | T99: =N99 -> 38183.395 | U99: =T99 -> 38183.395 | V99: =U99 -> 38183.395 | W99: =V99 -> 38183.395 | AC99: =T99 -> 38183.395 | AD99: =AC99 -> 38183.395 | AE99: =AD99 -> 38183.395 | AF99: =AE99 -> 38183.395 | AI99: =AC99 -> 38183.395 | AJ99: =AI99 -> 38183.395 | AK99: =AJ99 -> 38183.395 | AL99: =AK99 -> 38183.395
A100: 1-10 млн | G100: =G109/2 -> 23721.5 | H100: =H109/2 -> 23721.5 | I100: =I109/2 -> 23721.5 | J100: =J109/2 -> 23721.5 | N100: =N117/2*N125 -> 26600.988 | O100: =N100 -> 26600.988 | P100: =O100 -> 26600.988 | Q100: =P100 -> 26600.988 | T100: =N100 -> 26600.988 | U100: =T100 -> 26600.988 | V100: =U100 -> 26600.988 | W100: =V100 -> 26600.988 | AC100: =T100 -> 26600.988 | AD100: =AC100 -> 26600.988 | AE100: =AD100 -> 26600.988 | AF100: =AE100 -> 26600.988 | AI100: =AC100 -> 26600.988 | AJ100: =AI100 -> 26600.988 | AK100: =AJ100 -> 26600.988 | AL100: =AK100 -> 26600.988
A101: менее 1 млн | G101: =G110/2 -> 20475.5 | H101: =H110/2 -> 20475.5 | I101: =I110/2 -> 20475.5 | J101: =J110/2 -> 20475.5 | N101: =N118/2*N126 -> 23361.309 | O101: =N101 -> 23361.309 | P101: =O101 -> 23361.309 | Q101: =P101 -> 23361.309 | T101: =N101 -> 23361.309 | U101: =T101 -> 23361.309 | V101: =U101 -> 23361.309 | W101: =V101 -> 23361.309 | AC101: =T101 -> 23361.309 | AD101: =AC101 -> 23361.309 | AE101: =AD101 -> 23361.309 | AF101: =AE101 -> 23361.309 | AI101: =AC101 -> 23361.309 | AJ101: =AI101 -> 23361.309 | AK101: =AJ101 -> 23361.309 | AL101: =AK101 -> 23361.309
A102: без оборотов | G102: =G111/2 -> 16914 | H102: =H111/2 -> 16914 | I102: =I111/2 -> 16914 | J102: =J111/2 -> 16914 | N102: =N119/2*N127 -> 19667.442 | O102: =N102 -> 19667.442 | P102: =O102 -> 19667.442 | Q102: =P102 -> 19667.442 | T102: =N102 -> 19667.442 | U102: =T102 -> 19667.442 | V102: =U102 -> 19667.442 | W102: =V102 -> 19667.442 | AC102: =T102 -> 19667.442 | AD102: =AC102 -> 19667.442 | AE102: =AD102 -> 19667.442 | AF102: =AE102 -> 19667.442 | AI102: =AC102 -> 19667.442 | AJ102: =AI102 -> 19667.442 | AK102: =AJ102 -> 19667.442 | AL102: =AK102 -> 19667.442
A103: связь с селлером не найдена | G103: =G112/2 -> 10790.5 | H103: =H112/2 -> 10790.5 | I103: =I112/2 -> 10790.5 | J103: =J112/2 -> 10790.5 | N103: =N120/2*N128 -> 13126.588 | O103: =N103 -> 13126.588 | P103: =O103 -> 13126.588 | Q103: =P103 -> 13126.588 | T103: =N103 -> 13126.588 | U103: =T103 -> 13126.588 | V103: =U103 -> 13126.588 | W103: =V103 -> 13126.588 | AC103: =T103 -> 13126.588 | AD103: =AC103 -> 13126.588 | AE103: =AD103 -> 13126.588 | AF103: =AE103 -> 13126.588 | AI103: =AC103 -> 13126.588 | AJ103: =AI103 -> 13126.588 | AK103: =AJ103 -> 13126.588 | AL103: =AK103 -> 13126.588
A105: LTV as is: MPStats ( май 25-апр 26)
A106: Сегмент по обороту
A107: >100 млн | G107: ='MPS др метрики'!C110 -> 110725 | H107: =G107 -> 110725 | I107: =H107 -> 110725 | J107: =I107 -> 110725 | N107: =G107 -> 110725 | O107: =N107 -> 110725 | P107: =O107 -> 110725 | Q107: =P107 -> 110725 | T107: =N107 -> 110725 | U107: =O107 -> 110725 | V107: =P107 -> 110725 | W107: =Q107 -> 110725 | AC107: =T107 -> 110725 | AD107: =U107 -> 110725 | AE107: =V107 -> 110725 | AF107: =W107 -> 110725 | AI107: =AC107 -> 110725 | AJ107: =AD107 -> 110725 | AK107: =AE107 -> 110725 | AL107: =AF107 -> 110725
A108: 10 + млн | G108: ='MPS др метрики'!C111 -> 70053 | H108: =G108 -> 70053 | I108: =H108 -> 70053 | J108: =I108 -> 70053 | N108: =G108 -> 70053 | O108: =N108 -> 70053 | P108: =O108 -> 70053 | Q108: =P108 -> 70053 | T108: =N108 -> 70053 | U108: =O108 -> 70053 | V108: =P108 -> 70053 | W108: =Q108 -> 70053 | AC108: =T108 -> 70053 | AD108: =U108 -> 70053 | AE108: =V108 -> 70053 | AF108: =W108 -> 70053 | AI108: =AC108 -> 70053 | AJ108: =AD108 -> 70053 | AK108: =AE108 -> 70053 | AL108: =AF108 -> 70053
A109: 1-10 млн | G109: ='MPS др метрики'!C112 -> 47443 | H109: =G109 -> 47443 | I109: =H109 -> 47443 | J109: =I109 -> 47443 | N109: =G109 -> 47443 | O109: =N109 -> 47443 | P109: =O109 -> 47443 | Q109: =P109 -> 47443 | T109: =N109 -> 47443 | U109: =O109 -> 47443 | V109: =P109 -> 47443 | W109: =Q109 -> 47443 | AC109: =T109 -> 47443 | AD109: =U109 -> 47443 | AE109: =V109 -> 47443 | AF109: =W109 -> 47443 | AI109: =AC109 -> 47443 | AJ109: =AD109 -> 47443 | AK109: =AE109 -> 47443 | AL109: =AF109 -> 47443
A110: менее 1 млн | G110: ='MPS др метрики'!C113 -> 40951 | H110: =G110 -> 40951 | I110: =H110 -> 40951 | J110: =I110 -> 40951 | N110: =G110 -> 40951 | O110: =N110 -> 40951 | P110: =O110 -> 40951 | Q110: =P110 -> 40951 | T110: =N110 -> 40951 | U110: =O110 -> 40951 | V110: =P110 -> 40951 | W110: =Q110 -> 40951 | AC110: =T110 -> 40951 | AD110: =U110 -> 40951 | AE110: =V110 -> 40951 | AF110: =W110 -> 40951 | AI110: =AC110 -> 40951 | AJ110: =AD110 -> 40951 | AK110: =AE110 -> 40951 | AL110: =AF110 -> 40951
A111: без оборотов | G111: ='MPS др метрики'!C114 -> 33828 | H111: =G111 -> 33828 | I111: =H111 -> 33828 | J111: =I111 -> 33828 | N111: =G111 -> 33828 | O111: =N111 -> 33828 | P111: =O111 -> 33828 | Q111: =P111 -> 33828 | T111: =N111 -> 33828 | U111: =O111 -> 33828 | V111: =P111 -> 33828 | W111: =Q111 -> 33828 | AC111: =T111 -> 33828 | AD111: =U111 -> 33828 | AE111: =V111 -> 33828 | AF111: =W111 -> 33828 | AI111: =AC111 -> 33828 | AJ111: =AD111 -> 33828 | AK111: =AE111 -> 33828 | AL111: =AF111 -> 33828
...

Sheet Гипотезы_v3
F1: Биллинг MPS | L1: Биллинг Т-Банк | S1: Биллинг Т-Банк | AB1: Биллинг Т-Банк
F2: Гипотеза 1. Sales MPS + Биллинг MPS | M2: Гипотеза 2. Sales MPS + Биллинг Т | S2: Гипотеза 3.Digital + Биллинг Т | AB2: Гипотеза 4. Digital + Sales MPS (> 1млн) + Биллинг Т
AB3: Digital (до 1 млн оборот) | AH3: Sales (>1 млн оборот)
A4: Воронка | B4: Конверсии как дали MPStats | C4: Конверсии как дали MPStats | D4: От какого этапа | E4: От всех лидов | F4: Конверсии | G4: Сегмент 1. Активные клиенты в Т с выплатами от МП. 1 приоритет | H4: Сегмент 2. Активные клиенты в Т., но без выплат от МП на РКО. | I4: Сегмент 3. Спящие клиенты в Т (нет транзакций по РКО). Проснулись | J4: Сегмент 4. Клиенты без РКО в Т - Рынок. Открыли РКО | K4: ALL | L4: От всех лидов | M4: Конверсии | N4: Сегмент 1. Активные селлеры в Т с выплатами от МП. 1 приоритет | O4: Сегмент 2. Активные селлеры в Т., но без выплат от МП | P4: Сегмент 3. Спящие селлеры в Т (нет транзакций по РКО) | Q4: Сегмент 4. Селлеры без РКО в Т - Рынок | R4: ALL | S4: Конверсии | T4: Сегмент 1. Активные селлеры в Т с выплатами от МП. 1 приоритет | U4: Сегмент 2. Активные селлеры в Т., но без выплат от МП | V4: Сегмент 3. Спящие селлеры в Т (нет транзакций по РКО) | W4: Сегмент 4. Селлеры без РКО в Т - Рынок | X4: ALL | Y4: От все Лиды Digital | Z4: От все Лиды Sales | AA4: От все Лиды | AB4: Конверсии | AC4: Сегмент 1. Активные селлеры в Т с выплатами от МП. 1 приоритет | AD4: Сегмент 2. Активные селлеры в Т., но без выплат от МП | AE4: Сегмент 3. Спящие селлеры в Т (нет транзакций по РКО) | AF4: Сегмент 4. Селлеры без РКО в Т - Рынок | AG4: ALL Digital | AH4: Конверсии | AI4: Сегмент 1. Активные селлеры в Т с выплатами от МП. 1 приоритет | AJ4: Сегмент 2. Активные селлеры в Т., но без выплат от МП | AK4: Сегмент 3. Спящие селлеры в Т (нет транзакций по РКО) | AL4: Сегмент 4. Селлеры без РКО в Т - Рынок | AM4: ALL Sales | AN4: ALL
A5: База селлеров | F5: 1 | G5: ='База селлеров'!B63 -> 79000 | H5: ='База селлеров'!C63 -> 33000 | I5: ='База селлеров'!D67 -> 1820 | J5: ='База селлеров'!E67 -> 3705 | K5: =SUM(G5:J5) -> 117525 | M5: =F5 -> 1 | N5: =G5 -> 79000 | O5: =H5 -> 33000 | P5: =I5 -> 1820 | Q5: =J5 -> 3705 | R5: =SUM(N5:Q5) -> 117525 | S5: =M5 -> 1 | T5: =N5 -> 79000 | U5: =O5 -> 33000 | V5: =P5 -> 1820 | W5: =Q5 -> 3705 | X5: =SUM(T5:W5) -> 117525 | AC5: =T5*T88 -> 70079.175 | AD5: =U5*U88 -> 27249.295 | AE5: =V5*V88 -> 1564.9858 | AF5: =W5*W88 -> 3185.8639 | AG5: =SUM(AC5:AF5) -> 102079.32 | AI5: =T5-AC5 -> 8920.8253 | AJ5: =U5-AD5 -> 5750.7049 | AK5: =V5-AE5 -> 255.01424 | AL5: =W5-AF5 -> 519.13612 | AM5: =SUM(AI5:AL5) -> 15445.681 | AN5: =AG5+AM5 -> 117525 | AV5: =T5 -> 79000 | AW5: =U5 -> 33000 | AX5: =V5 -> 1820 | AY5: =W5 -> 3705 | AZ5: =X5 -> 117525
A6: Увеличение базы - влияние MPStast | I6: ='База селлеров'!D69 -> 130 | J6: ='База селлеров'!E69 -> 1233 | P6: =I6 -> 130 | Q6: =J6 -> 1233 | V6: =P6 -> 130 | W6: =Q6 -> 1233 | AE6: =V6*V88 -> 111.7847 | AF6: =W6*W88 -> 1060.2349 | AK6: =V6-AE6 -> 18.215303 | AL6: =W6-AF6 -> 172.76514
A7: Лиды (визиты Селлер) | C7: 1 | D7: от Базы | F7: 0.8 | G7: =G5*$F$7 -> 63200 | H7: =H5*$F$7 -> 26400 | I7: =I5*$F$7 -> 1456 | J7: =J5*$F$7 -> 2964 | K7: =SUM(G7:J7) -> 94020 | M7: =F7 -> 0.8 | N7: =G7 -> 63200 | O7: =H7 -> 26400 | P7: =I7 -> 1456 | Q7: =J7 -> 2964 | R7: =SUM(N7:Q7) -> 94020 | S7: =M7 -> 0.8 | T7: =N7 -> 63200 | U7: =O7 -> 26400 | V7: =P7 -> 1456 | W7: =Q7 -> 2964 | X7: =SUM(T7:W7) -> 94020 | AB7: =S7 -> 0.8 | AC7: =$AB$7*AC5 -> 56063.34 | AD7: =$AB$7*AD5 -> 21799.436 | AE7: =$AB$7*AE5 -> 1251.9886 | AF7: =$AB$7*AF5 -> 2548.6911 | AG7: =SUM(AC7:AF7) -> 81663.456 | AH7: =M7 -> 0.8 | AI7: =$AH$7*AI5 -> 7136.6602 | AJ7: =$AH$7*AJ5 -> 4600.5639 | AK7: =$AH$7*AK5 -> 204.01139 | AL7: =$AH$7*AL5 -> 415.3089 | AM7: =SUM(AI7:AL7) -> 12356.544 | AN7: =AG7+AM7 -> 94020 | AY7: =AY5 -> 3705 | AZ7: =AZ5 -> 117525
A8: Оставление API ключа
A9: Оффер триала
A10: Триала выдан
A11: Активация триала
A12: Активация в Селлере
A13: Квалификацированные лиды ЦА (не дозвон КЦ) | D13: от Лиды | F13: =G13/G7 -> 0.25 | G13: =G7-G14 -> 15800 | H13: =H7-H14 -> 6600 | I13: =I7-I14 -> 364 | J13: =J7-J14 -> 741 | K13: =SUM(G13:J13) -> 23505 | M13: =N13/N7 -> 0.25 | N13: =N7-N14 -> 15800 | O13: =O7-O14 -> 6600 | P13: =P7-P14 -> 364 | Q13: =Q7-Q14 -> 741 | R13: =SUM(N13:Q13) -> 23505 | S13: - | T13: - | U13: - | V13: - | W13: - | X13: - | AH13: =M13 -> 0.25 | AI13: =AI7-AI14 -> 1784.1651 | AJ13: =AJ7-AJ14 -> 1150.141 | AK13: =AK7-AK14 -> 51.002847 | AL13: =AL7-AL14 -> 103.82722 | AM13: =SUM(AI13:AL13) -> 3089.1361 | AN13: =AG13+AM13 -> 3089.1361
A14: Квалификацированные лиды ЦА (дозвоны) | B14: от Лиды | C14: 0.13 | D14: от Лиды | F14: 0.75 | G14: =$G$7*F14 -> 47400 | H14: =$H$7*F14 -> 19800 | I14: =$I$7*F14 -> 1092 | J14: =$J$7*F14 -> 2223 | K14: =SUM(G14:J14) -> 70515 | M14: =F14 -> 0.75 | N14: =$N$7*M14 -> 47400 | O14: =$O$7*M14 -> 19800 | P14: =$P$7*M14 -> 1092 | Q14: =$Q$7*M14 -> 2223 | R14: =SUM(N14:Q14) -> 70515 | S14: - | T14: - | U14: - | V14: - | W14: - | X14: - | AH14: =M14 -> 0.75 | AI14: =$AI$7*AH14 -> 5352.4952 | AJ14: =$AJ$7*AH14 -> 3450.4229 | AK14: =$AK$7*AH14 -> 153.00854 | AL14: =$AL$7*AH14 -> 311.48167 | AM14: =SUM(AI14:AL14) -> 9267.4083 | AN14: =AG14+AM14 -> 9267.4083
A15: /Оффер демо встречи | B15: от Квалиф. Лиды | C15: 1 | D15: от Квал. Лиды | F15: 1 | G15: =$G$14*F15 -> 47400 | H15: =$H$14*F15 -> 19800 | I15: =$I$14*F15 -> 1092 | J15: =$J$14*F15 -> 2223 | K15: =SUM(G15:J15) -> 70515 | M15: =F15 -> 1 | N15: =$N$7*M15 -> 63200 | O15: =$O$7*M15 -> 26400 | P15: =$P$7*M15 -> 1456 | Q15: =$Q$7*M15 -> 2964 | R15: =SUM(N15:Q15) -> 94020 | S15: - | T15: - | U15: - | V15: - | W15: - | X15: - | AH15: =M15 -> 1 | AI15: =$AI$7*AH15 -> 7136.6602 | AJ15: =$AJ$7*AH15 -> 4600.5639 | AK15: =$AK$7*AH15 -> 204.01139 | AL15: =$AL$7*AH15 -> 415.3089 | AM15: =SUM(AI15:AL15) -> 12356.544 | AN15: =AG15+AM15 -> 12356.544
A16: //Согласились на демо встречу | B16: от Квалиф. Лиды | C16: 0.4 | D16: от Квал. Лиды | F16: ='Воронка MPS_обработано'!N10 -> 0.4 | G16: =$G$14*F16 -> 18960 | H16: =$H$14*F16 -> 7920 | I16: =$I$14*F16 -> 436.8 | J16: =$J$14*F16 -> 889.2 | K16: =SUM(G16:J16) -> 28206 | M16: =F16 -> 0.4 | N16: =$N$7*M16 -> 25280 | O16: =$O$7*M16 -> 10560 | P16: =$P$7*M16 -> 582.4 | Q16: =$Q$7*M16 -> 1185.6 | R16: =SUM(N16:Q16) -> 37608 | S16: - | T16: - | U16: - | V16: - | W16: - | X16: - | AH16: =M16 -> 0.4 | AI16: =$AI$7*AH16 -> 2854.6641 | AJ16: =$AJ$7*AH16 -> 1840.2256 | AK16: =$AK$7*AH16 -> 81.604556 | AL16: =$AL$7*AH16 -> 166.12356 | AM16: =SUM(AI16:AL16) -> 4942.6178 | AN16: =AG16+AM16 -> 4942.6178
A17: //Демо встреча состоялась | B17: от Квалиф. Лиды | C17: 0.298 | D17: от Квал. Лиды | F17: ='Воронка MPS_обработано'!N11 -> 0.298 | G17: =$G$14*F17 -> 14125.2 | H17: =$H$14*F17 -> 5900.4 | I17: =$I$14*F17 -> 325.416 | J17: =$J$14*F17 -> 662.454 | K17: =SUM(G17:J17) -> 21013.47 | M17: =F17 -> 0.298 | N17: =$N$7*M17 -> 18833.6 | O17: =$O$7*M17 -> 7867.2 | P17: =$P$7*M17 -> 433.888 | Q17: =$Q$7*M17 -> 883.272 | R17: =SUM(N17:Q17) -> 28017.96 | S17: - | T17: - | U17: - | V17: - | W17: - | X17: - | AH17: =M17 -> 0.298 | AI17: =$AI$7*AH17 -> 2126.7247 | AJ17: =$AJ$7*AH17 -> 1370.968 | AK17: =$AK$7*AH17 -> 60.795394 | AL17: =$AL$7*AH17 -> 123.76205 | AM17: =SUM(AI17:AL17) -> 3682.2502 | AN17: =AG17+AM17 -> 3682.2502
A18: /Дозвон sales (кто не согласился на демо) | B18: от Квалиф. Лиды | C18: 0.455 | D18: от Квал. Лиды | F18: ='Воронка MPS_обработано'!N12 -> 0.455 | G18: =$G$14*F18 -> 21567 | H18: =$H$14*F18 -> 9009 | I18: =$I$14*F18 -> 496.86 | J18: =$J$14*F18 -> 1011.465 | K18: =SUM(G18:J18) -> 32084.325 | M18: =F18 -> 0.455 | N18: =$N$7*M18 -> 28756 | O18: =$O$7*M18 -> 12012 | P18: =$P$7*M18 -> 662.48 | Q18: =$Q$7*M18 -> 1348.62 | R18: =SUM(N18:Q18) -> 42779.1 | S18: - | T18: - | U18: - | V18: - | W18: - | X18: - | AH18: =M18 -> 0.455 | AI18: =$AI$7*AH18 -> 3247.1804 | AJ18: =$AJ$7*AH18 -> 2093.2566 | AK18: =$AK$7*AH18 -> 92.825182 | AL18: =$AL$7*AH18 -> 188.96555 | AM18: =SUM(AI18:AL18) -> 5622.2277 | AN18: =AG18+AM18 -> 5622.2277
A19: Покупка тарифа MPS (основной канал) | B19: от Лиды | C19: 0,7% / 0,41%/ 1,1% всего | D19: от Квал. Лиды | E19: =K19/K7 -> 0.064038462 | F19: ='Воронка MPS_обработано'!N14 -> 0.085384615 | G19: =$G$14*F19 -> 4047.2308 | H19: =$H$14*F19 -> 1690.6154 | I19: =$I$14*F19 -> 93.24 | J19: =$J$14*F19 -> 189.81 | K19: =SUM(G19:J19) -> 6020.8962 | L19: =R19/R7 -> 0.096057692 | M19: =F19*1.5 -> 0.12807692 | N19: =N14*$M$19 -> 6070.8462 | O19: =O14*$M$19 -> 2535.9231 | P19: =P14*$M$19 -> 139.86 | Q19: =Q14*$M$19 -> 284.715 | R19: =SUM(N19:Q19) -> 9031.3442 | S19: ='Воронка Селлер as is'!F12 -> 0.017475399 | T19: =$S$19*T7 -> 1104.4452 | U19: =$S$19*U7 -> 461.35053 | V19: =$S$19*V7 -> 25.444181 | W19: =$S$19*W7 -> 51.797082 | X19: =SUM(T19:W19) -> 1643.037 | Y19: =AG19/$AG$7 -> 0.017475399 | Z19: =AM19/$AM$7 -> 0.096057692 | AA19: =AN19/AN7 -> 0.027803048 | AB19: =S19 -> 0.017475399 | AC19: =$S$19*AC7 -> 979.72922 | AD19: =$S$19*AD7 -> 380.95384 | AE19: =$S$19*AE7 -> 21.879 | AF19: =$S$19*AF7 -> 44.539393 | AG19: =SUM(AC19:AF19) -> 1427.1014 | AH19: =M19 -> 0.12807692 | AI19: =AI14*$AH$19 -> 685.53111 | AJ19: =AJ14*$AH$19 -> 441.91955 | AK19: =AK14*$AH$19 -> 19.596863 | AL19: =AL14*$AH$19 -> 39.893614 | AM19: =SUM(AI19:AL19) -> 1186.9411 | AN19: =AG19+AM19 -> 2614.0426
A20: Покупка тарифа MPS (самоходы) | D20: от Лиды | E20: =K20/K7 -> 0.0043688497 | F20: =S19 -> 0.017475399 | G20: =G13*$F$20 -> 276.1113 | H20: =H13*$F$20 -> 115.33763 | I20: =I13*$F$20 -> 6.3610451 | J20: =J13*$F$20 -> 12.94927 | K20: =SUM(G20:J20) -> 410.75925 | L20: =R20/R7 -> 0.0043688497 | M20: =S19 -> 0.017475399 | N20: =N13*$M$20 -> 276.1113 | O20: =O13*$M$20 -> 115.33763 | P20: =P13*$M$20 -> 6.3610451 | Q20: =Q13*$M$20 -> 12.94927 | R20: =SUM(N20:Q20) -> 410.75925 | Y20: =AG20/$AG$7 -> 0 | Z20: =AM20/$AM$7 -> 0.0043688497 | AA20: =AN20/AN7 -> 0.00057417449 | AH20: =M20 -> 0.017475399 | AI20: =AI13*$AH$20 -> 31.178996 | AJ20: =AJ13*$AH$20 -> 20.099172 | AK20: =AK13*$AH$20 -> 0.89129509 | AL20: =AL13*$AH$20 -> 1.8144222 | AM20: =SUM(AI20:AL20) -> 53.983885 | AN20: =AG20+AM20 -> 53.983885
A21: Покупка тарифа MPS (всего) | E21: =K21/K7 -> 0.068407311 | G21: =SUM(G19:G20) -> 4323.3421 | H21: =SUM(H19:H20) -> 1805.953 | I21: =SUM(I19:I20) -> 99.601045 | J21: =SUM(J19:J20) -> 202.75927 | K21: =SUM(G21:J21) -> 6431.6554 | L21: =R21/R7 -> 0.10042654 | N21: =SUM(N19:N20) -> 6346.9575 | O21: =SUM(O19:O20) -> 2651.2607 | P21: =SUM(P19:P20) -> 146.22105 | Q21: =SUM(Q19:Q20) -> 297.66427 | R21: =SUM(N21:Q21) -> 9442.1035 | T21: =T19 -> 1104.4452 | U21: =U19 -> 461.35053 | V21: =V19 -> 25.444181 | W21: =W19 -> 51.797082 | X21: =SUM(T21:W21) -> 1643.037 | Y21: =AG21/$AG$7 -> 0.017475399 | Z21: =AM21/$AM$7 -> 0.10042654 | AA21: =AN21/AN7 -> 0.028377223 | AC21: =AC19 -> 979.72922 | AD21: =AD19 -> 380.95384 | AE21: =AE19 -> 21.879 | AF21: =AF19 -> 44.539393 | AG21: =SUM(AC21:AF21) -> 1427.1014 | AI21: =SUM(AI19:AI20) -> 716.71011 | AJ21: =SUM(AJ19:AJ20) -> 462.01872 | AK21: =SUM(AK19:AK20) -> 20.488158 | AL21: =SUM(AL19:AL20) -> 41.708037 | AM21: =SUM(AI21:AL21) -> 1240.925 | AN21: =AG21+AM21 -> 2668.0265
A22: >100 млн | G22: =G$21*G85 -> 0.47195113 | H22: =H$21*H85 -> 3.1117611 | I22: =I$21*I85 -> 0.082139131 | J22: =J$21*J85 -> 0.1672118 | K22: =SUM(G22:J22) -> 3.8330632 | N22: =N$21*N85 -> 0.69285606 | O22: =O$21*O85 -> 4.568275 | P22: =P$21*P85 -> 0.12058578 | Q22: =Q$21*Q85 -> 0.24547819 | R22: =SUM(N22:Q22) -> 5.6271951 | T22: =T$21*T85 -> 0.1205651 | U22: =U$21*U85 -> 0.79493355 | V22: =V$21*V85 -> 0.020983343 | W22: =W$21*W85 -> 0.042716091 | X22: =SUM(T22:W22) -> 0.97919808 | AC22: =AC$21*AC85 -> 0 | AD22: =AD$21*AD85 -> 0 | AE22: =AE$21*AE85 -> 0 | AF22: =AF$21*AF85 -> 0 | AG22: =SUM(AC22:AF22) -> 0 | AI22: =AI$21*AI85 -> 0.69285606 | AJ22: =AJ$21*AJ85 -> 4.568275 | AK22: =AK$21*AK85 -> 0.12058578 | AL22: =AL$21*AL85 -> 0.24547819 | AM22: =SUM(AI22:AL22) -> 5.6271951 | AN22: =AG22+AM22 -> 5.6271951
A23: 10-100 млн | G23: =G$21*G86 -> 32.429785 | H23: =H$21*H86 -> 37.058246 | I23: =I$21*I86 -> 1.3220077 | J23: =J$21*J86 -> 2.6912299 | K23: =SUM(G23:J23) -> 73.501269 | N23: =N$21*N86 -> 47.609109 | O23: =O$21*O86 -> 54.404003 | P23: =P$21*P86 -> 1.9407964 | Q23: =Q$21*Q86 -> 3.9509069 | R23: =SUM(N23:Q23) -> 107.90482 | T23: =T$21*T86 -> 8.2845446 | U23: =U$21*U86 -> 9.4669359 | V23: =V$21*V86 -> 0.33772138 | W23: =W$21*W86 -> 0.68750424 | X23: =SUM(T23:W23) -> 18.776706 | AC23: =AC$21*AC86 -> 0 | AD23: =AD$21*AD86 -> 0 | AE23: =AE$21*AE86 -> 0 | AF23: =AF$21*AF86 -> 0 | AG23: =SUM(AC23:AF23) -> 0 | AI23: =AI$21*AI86 -> 47.609109 | AJ23: =AJ$21*AJ86 -> 54.404003 | AK23: =AK$21*AK86 -> 1.9407964 | AL23: =AL$21*AL86 -> 3.9509069 | AM23: =SUM(AI23:AL23) -> 107.90482 | AN23: =AG23+AM23 -> 107.90482
A24: 1-10 млн | G24: =G$21*G87 -> 455.298 | H24: =H$21*H87 -> 274.5422 | I24: =I$21*I87 -> 12.551724 | J24: =J$21*J87 -> 25.551723 | K24: =SUM(G24:J24) -> 767.94365 | N24: =N$21*N87 -> 668.40814 | O24: =O$21*O87 -> 403.04645 | P24: =P$21*P87 -> 18.426776 | Q24: =Q$21*Q87 -> 37.511652 | R24: =SUM(N24:Q24) -> 1127.393 | T24: =T$21*T87 -> 116.31087 | U24: =U$21*U87 -> 70.134819 | V24: =V$21*V87 -> 3.2064756 | W24: =W$21*W87 -> 6.5274683 | X24: =SUM(T24:W24) -> 196.17964 | AC24: =AC$21*AC87 -> 0 | AD24: =AD$21*AD87 -> 0 | AE24: =AE$21*AE87 -> 0 | AF24: =AF$21*AF87 -> 0 | AG24: =SUM(AC24:AF24) -> 0 | AI24: =AI$21*AI87 -> 668.40814 | AJ24: =AJ$21*AJ87 -> 403.04645 | AK24: =AK$21*AK87 -> 18.426776 | AL24: =AL$21*AL87 -> 37.511652 | AM24: =SUM(AI24:AL24) -> 1127.393 | AN24: =AG24+AM24 -> 1127.393
A25: менее 1 млн | G25: =G$21*G88 -> 3835.1423 | H25: =H$21*H88 -> 1491.2408 | I25: =I$21*I88 -> 85.645175 | J25: =J$21*J88 -> 174.34911 | K25: =SUM(G25:J25) -> 5586.3774 | N25: =N$21*N88 -> 5630.2473 | O25: =O$21*O88 -> 2189.242 | P25: =P$21*P88 -> 125.73289 | Q25: =Q$21*Q88 -> 255.95623 | R25: =SUM(N25:Q25) -> 8201.1785 | T25: =T$21*T88 -> 979.72922 | U25: =U$21*U88 -> 380.95384 | V25: =V$21*V88 -> 21.879 | W25: =W$21*W88 -> 44.539393 | X25: =SUM(T25:W25) -> 1427.1014 | AC25: =AC$21*AC88 -> 979.72922 | AD25: =AD$21*AD88 -> 380.95384 | AE25: =AE$21*AE88 -> 21.879 | AF25: =AF$21*AF88 -> 44.539393 | AG25: =SUM(AC25:AF25) -> 1427.1014 | AI25: =AI$21*AI88 -> 0 | AJ25: =AJ$21*AJ88 -> 0 | AK25: =AK$21*AK88 -> 0 | AL25: =AL$21*AL88 -> 0 | AM25: =SUM(AI25:AL25) -> 0 | AN25: =AG25+AM25 -> 1427.1014
A26: без оборотов | G26: =G$21*G89 -> 0 | H26: =H$21*H89 -> 0 | I26: =I$21*I89 -> 0 | J26: =J$21*J89 -> 0 | K26: =SUM(G26:J26) -> 0 | N26: =N$21*N89 -> 0 | O26: =O$21*O89 -> 0 | P26: =P$21*P89 -> 0 | Q26: =Q$21*Q89 -> 0 | R26: =SUM(N26:Q26) -> 0 | T26: =T$21*T89 -> 0 | U26: =U$21*U89 -> 0 | V26: =V$21*V89 -> 0 | W26: =W$21*W89 -> 0 | X26: =SUM(T26:W26) -> 0 | AC26: =AC$21*AC89 -> 0 | AD26: =AD$21*AD89 -> 0 | AE26: =AE$21*AE89 -> 0 | AF26: =AF$21*AF89 -> 0 | AG26: =SUM(AC26:AF26) -> 0 | AI26: =AI$21*AI89 -> 0 | AJ26: =AJ$21*AJ89 -> 0 | AK26: =AK$21*AK89 -> 0 | AL26: =AL$21*AL89 -> 0 | AM26: =SUM(AI26:AL26) -> 0 | AN26: =AG26+AM26 -> 0
M27: =M19/F19 -> 1.5
M28: =(M19-F19)/F19 -> 0.5
A29: LTV | G29: =G44/G21 -> 20930.298 | H29: =H44/H21 -> 21327.659 | I29: =I44/I21 -> 21106.467 | J29: =J44/J21 -> 21106.467 | K29: =K44/K21 -> 21050.155 | N29: =N44/N21 -> 23817.576 | O29: =O44/O21 -> 24219.665 | P29: =P44/P21 -> 23995.842 | Q29: =Q44/Q21 -> 23995.842 | R29: =R44/R21 -> 23938.859 | T29: =T44/T21 -> 23817.576 | U29: =U44/U21 -> 24219.665 | V29: =V44/V21 -> 23995.842 | W29: =W44/W21 -> 23995.842 | X29: =X44/X21 -> 23938.859 | AC29: =AC44/AC21 -> 23361.309 | AD29: =AD44/AD21 -> 23361.309 | AE29: =AE44/AE21 -> 23361.309 | AF29: =AF44/AF21 -> 23361.309 | AG29: =AG44/AG21 -> 23361.309 | AI29: =AI44/AI21 -> 27401.866 | AJ29: =AJ44/AJ21 -> 28286.923 | AK29: =AK44/AK21 -> 27889.878 | AL29: =AL44/AL21 -> 27889.878 | AM29: =AM44/AM21 -> 27755.848 | AN29: =AN44/AN21 -> 25405.252
A30: >100 млн | G30: =G45/G22 -> 55362.5 | H30: =H45/H22 -> 55362.5 | I30: =I45/I22 -> 55362.5 | J30: =J45/J22 -> 55362.5 | K30: =K45/K22 -> 55362.5 | N30: =N45/N22 -> 59174.344 | O30: =O45/O22 -> 59174.344 | P30: =P45/P22 -> 59174.344 | Q30: =Q45/Q22 -> 59174.344 | R30: =R45/R22 -> 59174.344 | T30: =T45/T22 -> 59174.344 | U30: =U45/U22 -> 59174.344 | V30: =V45/V22 -> 59174.344 | W30: =W45/W22 -> 59174.344 | X30: =X45/X22 -> 59174.344 | AC30: =AC45/AC22 -> #DIV/0! | AD30: =AD45/AD22 -> #DIV/0! | AE30: =AE45/AE22 -> #DIV/0! | AF30: =AF45/AF22 -> #DIV/0! | AG30: =AG45/AG22 -> #DIV/0! | AI30: =AI45/AI22 -> 59174.344 | AJ30: =AJ45/AJ22 -> 59174.344 | AK30: =AK45/AK22 -> 59174.344 | AL30: =AL45/AL22 -> 59174.344 | AM30: =AM45/AM22 -> 59174.344 | AN30: =AN45/AN22 -> 59174.344
A31: 10-100 млн | G31: =G46/G23 -> 35026.5 | H31: =H46/H23 -> 35026.5 | I31: =I46/I23 -> 35026.5 | J31: =J46/J23 -> 35026.5 | K31: =K46/K23 -> 35026.5 | N31: =N46/N23 -> 38183.395 | O31: =O46/O23 -> 38183.395 | P31: =P46/P23 -> 38183.395 | Q31: =Q46/Q23 -> 38183.395 | R31: =R46/R23 -> 38183.395 | T31: =T46/T23 -> 38183.395 | U31: =U46/U23 -> 38183.395 | V31: =V46/V23 -> 38183.395 | W31: =W46/W23 -> 38183.395 | X31: =X46/X23 -> 38183.395 | AC31: =AC46/AC23 -> #DIV/0! | AD31: =AD46/AD23 -> #DIV/0! | AE31: =AE46/AE23 -> #DIV/0! | AF31: =AF46/AF23 -> #DIV/0! | AG31: =AG46/AG23 -> #DIV/0! | AI31: =AI46/AI23 -> 38183.395 | AJ31: =AJ46/AJ23 -> 38183.395 | AK31: =AK46/AK23 -> 38183.395 | AL31: =AL46/AL23 -> 38183.395 | AM31: =AM46/AM23 -> 38183.395 | AN31: =AN46/AN23 -> 38183.395
A32: 1-10 млн | G32: =G47/G24 -> 23721.5 | H32: =H47/H24 -> 23721.5 | I32: =I47/I24 -> 23721.5 | J32: =J47/J24 -> 23721.5 | K32: =K47/K24 -> 23721.5 | N32: =N47/N24 -> 26600.988 | O32: =O47/O24 -> 26600.988 | P32: =P47/P24 -> 26600.988 | Q32: =Q47/Q24 -> 26600.988 | R32: =R47/R24 -> 26600.988 | T32: =T47/T24 -> 26600.988 | U32: =U47/U24 -> 26600.988 | V32: =V47/V24 -> 26600.988 | W32: =W47/W24 -> 26600.988 | X32: =X47/X24 -> 26600.988 | AC32: =AC47/AC24 -> #DIV/0! | AD32: =AD47/AD24 -> #DIV/0! | AE32: =AE47/AE24 -> #DIV/0! | AF32: =AF47/AF24 -> #DIV/0! | AG32: =AG47/AG24 -> #DIV/0! | AI32: =AI47/AI24 -> 26600.988 | AJ32: =AJ47/AJ24 -> 26600.988 | AK32: =AK47/AK24 -> 26600.988 | AL32: =AL47/AL24 -> 26600.988 | AM32: =AM47/AM24 -> 26600.988 | AN32: =AN47/AN24 -> 26600.988
A33: менее 1 млн | G33: =G48/G25 -> 20475.5 | H33: =H48/H25 -> 20475.5 | I33: =I48/I25 -> 20475.5 | J33: =J48/J25 -> 20475.5 | K33: =K48/K25 -> 20475.5 | N33: =N48/N25 -> 23361.309 | O33: =O48/O25 -> 23361.309 | P33: =P48/P25 -> 23361.309 | Q33: =Q48/Q25 -> 23361.309 | R33: =R48/R25 -> 23361.309 | T33: =T48/T25 -> 23361.309 | U33: =U48/U25 -> 23361.309 | V33: =V48/V25 -> 23361.309 | W33: =W48/W25 -> 23361.309 | X33: =X48/X25 -> 23361.309 | AC33: =AC48/AC25 -> 23361.309 | AD33: =AD48/AD25 -> 23361.309 | AE33: =AE48/AE25 -> 23361.309 | AF33: =AF48/AF25 -> 23361.309 | AG33: =AG48/AG25 -> 23361.309 | AI33: =AI48/AI25 -> #DIV/0! | AJ33: =AJ48/AJ25 -> #DIV/0! | AK33: =AK48/AK25 -> #DIV/0! | AL33: =AL48/AL25 -> #DIV/0! | AM33: =AM48/AM25 -> #DIV/0! | AN33: =AN48/AN25 -> 23361.309
A34: без оборотов
A35: Расходы на 1 платящего клиента | G35: =G36+G40+G41 -> 16968.269 | H35: =H36+H40+H41 -> 17023.901 | I35: =I36+I40+I41 -> 18076.805 | J35: =J36+J40+J41 -> 17504.01 | K35: =K36+K40+K41 -> 17017.946 | N35: =N50/N21 -> 10434.426 | O35: =O50/O21 -> 10478.531 | P35: =P50/P21 -> 11192.278 | Q35: =Q50/Q21 -> 10802.109 | R35: =R50/R21 -> 10470.138 | T35: =T50/T21 -> 4368.1181 | U35: =U50/U21 -> 4529.1226 | V35: =V50/V21 -> 8682.3067 | W35: =W50/W21 -> 6440.1063 | X35: =X50/X21 -> 4545.4564 | AC35: =AC50/AC21 -> 4340.9299 | AD35: =AD50/AD21 -> 4497.1845 | AE35: =AE50/AE21 -> 8693.1549 | AF35: =AF50/AF21 -> 6428.2867 | AG35: =AG50/AG21 -> 4514.5109 | AI35: =AI50/AI21 -> 10634.266 | AJ35: =AJ50/AJ21 -> 10679.22 | AK35: =AK50/AK21 -> 11351.547 | AL35: =AL50/AL21 -> 10985.584 | AM35: =AM50/AM21 -> 10674.654 | AN35: =AN50/AN21 -> 7379.6532
A36: CAC | G36: =SUM(G37:G39) -> 14126.766 | H36: =SUM(H37:H39) -> 14126.766 | I36: =SUM(I37:I39) -> 14126.766 | J36: =SUM(J37:J39) -> 14126.766 | K36: =SUM(K37:K39) -> 14126.766 | N36: =SUM(N37:N39) -> 9428.3828 | O36: =SUM(O37:O39) -> 9428.3828 | P36: =SUM(P37:P39) -> 9428.3828 | Q36: =SUM(Q37:Q39) -> 9428.3828 | R36: =SUM(R37:R39) -> 9428.3828 | T36: =SUM(T37:T39) -> 2844.9196 | U36: =SUM(U37:U39) -> 2844.9196 | V36: =SUM(V37:V39) -> 2844.9196 | W36: =SUM(W37:W39) -> 2844.9196 | X36: =SUM(X37:X39) -> 2844.9196 | AC36: =SUM(AC37:AC39) -> 2844.9196 | AD36: =SUM(AD37:AD39) -> 2844.9196 | AE36: =SUM(AE37:AE39) -> 2844.9196 | AF36: =SUM(AF37:AF39) -> 2844.9196 | AG36: =SUM(AG37:AG39) -> 2844.9196 | AI36: =SUM(AI37:AI39) -> 9428.3828 | AJ36: =SUM(AJ37:AJ39) -> 9428.3828 | AK36: =SUM(AK37:AK39) -> 9428.3828 | AL36: =SUM(AL37:AL39) -> 9428.3828 | AM36: =SUM(AM37:AM39) -> 9428.3828 | AN36: =AN51/AN21 -> 5726.1984
A37: Sales, КЦ | G37: =G52/G19 -> 13400 | H37: =H52/H19 -> 13400 | I37: =I52/I19 -> 13400 | J37: =J52/J19 -> 13400 | K37: =K52/K19 -> 13400 | N37: =N52/N19 -> 8933.3333 | O37: =O52/O19 -> 8933.3333 | P37: =P52/P19 -> 8933.3333 | Q37: =Q52/Q19 -> 8933.3333 | R37: =R52/R19 -> 8933.3333 | T37: =T52/T19 -> 0 | U37: =U52/U19 -> 0 | V37: =V52/V19 -> 0 | W37: =W52/W19 -> 0 | X37: =X52/X19 -> 0 | AC37: =AC52/AC19 -> 0 | AD37: =AD52/AD19 -> 0 | AE37: =AE52/AE19 -> 0 | AF37: =AF52/AF19 -> 0 | AG37: =AG52/AG19 -> 0 | AI37: =AI52/AI19 -> 8933.3333 | AJ37: =AJ52/AJ19 -> 8933.3333 | AK37: =AK52/AK19 -> 8933.3333 | AL37: =AL52/AL19 -> 8933.3333 | AM37: =AM52/AM19 -> 8933.3333
A38: маркетинг Т внешний | G38: =G54/G21 -> 466.4429 | H38: =H54/H21 -> 466.4429 | I38: =I54/I21 -> 466.4429 | J38: =J54/J21 -> 466.4429 | K38: =K54/K21 -> 466.4429 | N38: =N54/N21 -> 317.72581 | O38: =O54/O21 -> 317.72581 | P38: =P54/P21 -> 317.72581 | Q38: =Q54/Q21 -> 317.72581 | R38: =R54/R21 -> 317.72581 | T38: =T54/T21 -> 1825.8871 | U38: =U54/U21 -> 1825.8871 | V38: =V54/V21 -> 1825.8871 | W38: =W54/W21 -> 1825.8871 | X38: =X54/X21 -> 1825.8871 | AC38: =AC54/AC21 -> 1825.8871 | AD38: =AD54/AD21 -> 1825.8871 | AE38: =AE54/AE21 -> 1825.8871 | AF38: =AF54/AF21 -> 1825.8871 | AG38: =AG54/AG21 -> 1825.8871 | AI38: =AI54/AI21 -> 317.72581 | AJ38: =AJ54/AJ21 -> 317.72581 | AK38: =AK54/AK21 -> 317.72581 | AL38: =AL54/AL21 -> 317.72581 | AM38: =AM54/AM21 -> 317.72581
A39: триал | G39: =G53/G21 -> 260.32305 | H39: =H53/H21 -> 260.32305 | I39: =I53/I21 -> 260.32305 | J39: =J53/J21 -> 260.32305 | K39: =K53/K21 -> 260.32305 | N39: =N53/N21 -> 177.32364 | O39: =O53/O21 -> 177.32364 | P39: =P53/P21 -> 177.32364 | Q39: =Q53/Q21 -> 177.32364 | R39: =R53/R21 -> 177.32364 | T39: =T53/T21 -> 1019.0325 | U39: =U53/U21 -> 1019.0325 | V39: =V53/V21 -> 1019.0325 | W39: =W53/W21 -> 1019.0325 | X39: =X53/X21 -> 1019.0325 | AC39: =AC53/AC21 -> 1019.0325 | AD39: =AD53/AD21 -> 1019.0325 | AE39: =AE53/AE21 -> 1019.0325 | AF39: =AF53/AF21 -> 1019.0325 | AG39: =AG53/AG21 -> 1019.0325 | AI39: =AI53/AI21 -> 177.32364 | AJ39: =AJ53/AJ21 -> 177.32364 | AK39: =AK53/AK21 -> 177.32364 | AL39: =AL53/AL21 -> 177.32364 | AM39: =AM53/AM21 -> 177.32364
A40: API | G40: =G55/G21 -> 1241.5026 | H40: =H55/H21 -> 1297.1346 | I40: =I55/I21 -> 2350.0387 | J40: =J55/J21 -> 1777.244 | K40: =K55/K21 -> 1291.1798 | N40: =N55/N21 -> 1394.6695 | O40: =O55/O21 -> 1438.7743 | P40: =P55/P21 -> 2152.5217 | Q40: =Q55/Q21 -> 1762.3524 | R40: =R55/R21 -> 1430.3811 | T40: =T55/T21 -> 1523.1984 | U40: =U55/U21 -> 1684.2029 | V40: =V55/V21 -> 5837.3871 | W40: =W55/W21 -> 3595.1866 | X40: =X55/X21 -> 1700.5368 | AC40: =AC55/AC21 -> 1496.0103 | AD40: =AD55/AD21 -> 1652.2649 | AE40: =AE55/AE21 -> 5848.2353 | AF40: =AF55/AF21 -> 3583.3671 | AG40: =AG55/AG21 -> 1669.5913 | AI40: =AI55/AI21 -> 1594.5095 | AJ40: =AJ55/AJ21 -> 1639.4637 | AK40: =AK55/AK21 -> 2311.7903 | AL40: =AL55/AL21 -> 1945.8276 | AM40: =AM55/AM21 -> 1634.8973 | AN40: =AN55/AN21 -> 1653.4548
A41: Продление и удержание MPStas | G41: =G71/G21 -> 1600 | H41: =H71/H21 -> 1600 | I41: =I71/I21 -> 1600 | J41: =J71/J21 -> 1600 | K41: =K71/K21 -> 1600 | N41: =N71/N21 -> 0 | O41: =O71/O21 -> 0 | P41: =P71/P21 -> 0 | Q41: =Q71/Q21 -> 0 | R41: =R71/R21 -> 0 | T41: =T71/T21 -> 0 | U41: =U71/U21 -> 0 | V41: =V71/V21 -> 0 | W41: =W71/W21 -> 0 | X41: =X71/X21 -> 0 | AC41: =AC71/AC21 -> 0 | AD41: =AD71/AD21 -> 0 | AE41: =AE71/AE21 -> 0 | AF41: =AF71/AF21 -> 0 | AG41: =AG71/AG21 -> 0 | AI41: =AI71/AI21 -> 0 | AJ41: =AJ71/AJ21 -> 0 | AK41: =AK71/AK21 -> 0 | AL41: =AL71/AL21 -> 0 | AM41: =AM71/AM21 -> 0 | AN41: =AN71/AN21 -> 0
A44: Доходы: Тарифы MPStats | G44: =SUM(G45:G49) -> 90488839 | H44: =SUM(H45:H49) -> 38516750 | I44: =SUM(I45:I49) -> 2102226.2 | J44: =SUM(J45:J49) -> 4279531.9 | K44: =SUM(G44:J44) -> 1.3538735e+08 | N44: =SUM(N45:N49) -> 1.5116914e+08 | O44: =SUM(O45:O49) -> 64212646 | P44: =SUM(P45:P49) -> 3508697 | Q44: =SUM(Q45:Q49) -> 7142704.7 | R44: =SUM(N44:Q44) -> 2.2603319e+08 | T44: =SUM(T45:T49) -> 26305207 | U44: =SUM(U45:U49) -> 11173755 | V44: =SUM(V45:V49) -> 610554.52 | W44: =SUM(W45:W49) -> 1242914.6 | X44: =SUM(T44:W44) -> 39332431 | AC44: =SUM(AC45:AC49) -> 22887757 | AD44: =SUM(AD45:AD49) -> 8899580.2 | AE44: =SUM(AE45:AE49) -> 511122.08 | AF44: =SUM(AF45:AF49) -> 1040498.5 | AG44: =SUM(AC44:AF44) -> 33338957 | AI44: =SUM(AI45:AI49) -> 19639194 | AJ44: =SUM(AJ45:AJ49) -> 13069088 | AK44: =SUM(AK45:AK49) -> 571412.24 | AL44: =SUM(AL45:AL49) -> 1163232.1 | AM44: =SUM(AI44:AL44) -> 34442926 | AN44: =AM44+AG44 -> 67781884
A45: >100 млн | G45: =G$21*G85*G95 -> 26128.395 | H45: =H$21*H85*H95 -> 172274.88 | I45: =I$21*I85*I95 -> 4547.4276 | J45: =J$21*J85*J95 -> 9257.2634 | K45: =SUM(G45:J45) -> 212207.96 | N45: =N$21*N85*N95 -> 40999.303 | O45: =O$21*O85*O95 -> 270324.68 | P45: =P$21*P85*P95 -> 7135.5843 | Q45: =Q$21*Q85*Q95 -> 14526.011 | R45: =SUM(N45:Q45) -> 332985.58 | T45: =T$21*T85*T95 -> 7134.3607 | U45: =U$21*U85*U95 -> 47039.672 | V45: =V$21*V85*V95 -> 1241.6755 | W45: =W$21*W85*W95 -> 2527.6966 | X45: =SUM(T45:W45) -> 57943.404 | AC45: =AC$21*AC85*AC95 -> 0 | AD45: =AD$21*AD85*AD95 -> 0 | AE45: =AE$21*AE85*AE95 -> 0 | AF45: =AF$21*AF85*AF95 -> 0 | AG45: =SUM(AC45:AF45) -> 0 | AI45: =AI$21*AI85*AI95 -> 40999.303 | AJ45: =AJ$21*AJ85*AJ95 -> 270324.68 | AK45: =AK$21*AK85*AK95 -> 7135.5843 | AL45: =AL$21*AL85*AL95 -> 14526.011 | AM45: =SUM(AI45:AL45) -> 332985.58 | AN45: =AM45+AG45 -> 332985.58
A46: 10-100 млн | G46: =G$21*G86*G96 -> 1135901.9 | H46: =H$21*H86*H96 -> 1298020.7 | I46: =I$21*I86*I96 -> 46305.302 | J46: =J$21*J86*J96 -> 94264.366 | K46: =SUM(G46:J46) -> 2574492.2 | N46: =N$21*N86*N96 -> 1817877.4 | O46: =O$21*O86*O96 -> 2077329.5 | P46: =P$21*P86*P96 -> 74106.194 | Q46: =Q$21*Q86*Q96 -> 150859.04 | R46: =SUM(N46:Q46) -> 4120172.2 | T46: =T$21*T86*T96 -> 316332.04 | U46: =U$21*U86*U96 -> 361479.75 | V46: =V$21*V86*V96 -> 12895.349 | W46: =W$21*W86*W96 -> 26251.246 | X46: =SUM(T46:W46) -> 716958.39 | AC46: =AC$21*AC86*AC96 -> 0 | AD46: =AD$21*AD86*AD96 -> 0 | AE46: =AE$21*AE86*AE96 -> 0 | AF46: =AF$21*AF86*AF96 -> 0 | AG46: =SUM(AC46:AF46) -> 0 | AI46: =AI$21*AI86*AI96 -> 1817877.4 | AJ46: =AJ$21*AJ86*AJ96 -> 2077329.5 | AK46: =AK$21*AK86*AK96 -> 74106.194 | AL46: =AL$21*AL86*AL96 -> 150859.04 | AM46: =SUM(AI46:AL46) -> 4120172.2 | AN46: =AM46+AG46 -> 4120172.2
A47: 1-10 млн | G47: =G$21*G87*G97 -> 10800352 | H47: =H$21*H87*H97 -> 6512552.8 | I47: =I$21*I87*I97 -> 297745.72 | J47: =J$21*J87*J97 -> 606125.21 | K47: =SUM(G47:J47) -> 18216775 | N47: =N$21*N87*N97 -> 17780317 | O47: =O$21*O87*O97 -> 10721434 | P47: =P$21*P87*P97 -> 490170.46 | Q47: =Q$21*Q87*Q97 -> 997847.01 | R47: =SUM(N47:Q47) -> 29989769 | T47: =T$21*T87*T97 -> 3093984.2 | U47: =U$21*U87*U97 -> 1865655.5 | V47: =V$21*V87*V97 -> 85295.422 | W47: =W$21*W87*W97 -> 173637.11 | X47: =SUM(T47:W47) -> 5218572.2 | AC47: =AC$21*AC87*AC97 -> 0 | AD47: =AD$21*AD87*AD97 -> 0 | AE47: =AE$21*AE87*AE97 -> 0 | AF47: =AF$21*AF87*AF97 -> 0 | AG47: =SUM(AC47:AF47) -> 0 | AI47: =AI$21*AI87*AI97 -> 17780317 | AJ47: =AJ$21*AJ87*AJ97 -> 10721434 | AK47: =AK$21*AK87*AK97 -> 490170.46 | AL47: =AL$21*AL87*AL97 -> 997847.01 | AM47: =SUM(AI47:AL47) -> 29989769 | AN47: =AM47+AG47 -> 29989769
A48: менее 1 млн | G48: =G$21*G88*G98 -> 78526457 | H48: =H$21*H88*H98 -> 30533901 | I48: =I$21*I88*I98 -> 1753627.8 | J48: =J$21*J88*J98 -> 3569885.1 | K48: =SUM(G48:J48) -> 1.1438387e+08 | N48: =N$21*N88*N98 -> 1.3152995e+08 | O48: =O$21*O88*O98 -> 51143558 | P48: =P$21*P88*P98 -> 2937284.8 | Q48: =Q$21*Q88*Q98 -> 5979472.6 | R48: =SUM(N48:Q48) -> 1.9159026e+08 | T48: =T$21*T88*T98 -> 22887757 | U48: =U$21*U88*U98 -> 8899580.2 | V48: =V$21*V88*V98 -> 511122.08 | W48: =W$21*W88*W98 -> 1040498.5 | X48: =SUM(T48:W48) -> 33338957 | AC48: =AC$21*AC88*AC98 -> 22887757 | AD48: =AD$21*AD88*AD98 -> 8899580.2 | AE48: =AE$21*AE88*AE98 -> 511122.08 | AF48: =AF$21*AF88*AF98 -> 1040498.5 | AG48: =SUM(AC48:AF48) -> 33338957 | AI48: =AI$21*AI88*AI98 -> 0 | AJ48: =AJ$21*AJ88*AJ98 -> 0 | AK48: =AK$21*AK88*AK98 -> 0 | AL48: =AL$21*AL88*AL98 -> 0 | AM48: =SUM(AI48:AL48) -> 0 | AN48: =AM48+AG48 -> 33338957
A49: без оборотов | G49: =G$21*G89*G99 -> 0 | H49: =H$21*H89*H99 -> 0 | I49: =I$21*I89*I99 -> 0 | J49: =J$21*J89*J99 -> 0 | K49: =SUM(G49:J49) -> 0 | N49: =N$21*N89*N99 -> 0 | O49: =O$21*O89*O99 -> 0 | P49: =P$21*P89*P99 -> 0 | Q49: =Q$21*Q89*Q99 -> 0 | R49: =SUM(N49:Q49) -> 0 | T49: =T$21*T89*T99 -> 0 | U49: =U$21*U89*U99 -> 0 | V49: =V$21*V89*V99 -> 0 | W49: =W$21*W89*W99 -> 0 | X49: =SUM(T49:W49) -> 0 | AC49: =AC$21*AC89*AC99 -> 0 | AD49: =AD$21*AD89*AD99 -> 0 | AE49: =AE$21*AE89*AE99 -> 0 | AF49: =AF$21*AF89*AF99 -> 0 | AG49: =SUM(AC49:AF49) -> 0 | AI49: =AI$21*AI89*AI99 -> 0 | AJ49: =AJ$21*AJ89*AJ99 -> 0 | AK49: =AK$21*AK89*AK99 -> 0 | AL49: =AL$21*AL89*AL99 -> 0 | AM49: =SUM(AI49:AL49) -> 0 | AN49: =AM49+AG49 -> 0
A50: Расходы: Тарифы MPStats | G50: =G51+G55+G71 -> 69659738 | H50: =H51+H55+H71 -> 29198840 | I50: =I51+I55+I71 -> 1715230.6 | J50: =J51+J55+J71 -> 3375580.1 | K50: =SUM(G50:J50) -> 1.0394939e+08 | N50: =N51+N55+N71 -> 66226858 | O50: =O51+O55+O71 -> 27781317 | P50: =P51+P55+P71 -> 1636546.6 | Q50: =Q51+Q55+Q71 -> 3215401.9 | R50: =SUM(N50:Q50) -> 98860123 | T50: =T51+T55+T71 -> 4824347 | U50: =U51+U55+U71 -> 2089513.1 | V50: =V51+V55+V71 -> 220914.18 | W50: =W51+W55+W71 -> 333578.71 | X50: =SUM(T50:W50) -> 7468353 | AC50: =AC51+AC55+AC71 -> 4252935.9 | AD50: =AD51+AD55+AD71 -> 1713219.7 | AE50: =AE51+AE55+AE71 -> 190197.54 | AF50: =AF51+AF55+AF71 -> 286311.99 | AG50: =SUM(AC50:AF50) -> 6442665.1 | AI50: =AI51+AI55+AI71 -> 7621685.9 | AJ50: =AJ51+AJ55+AJ71 -> 4933999.7 | AK50: =AK51+AK55+AK71 -> 232572.29 | AL50: =AL51+AL55+AL71 -> 458187.15 | AM50: =SUM(AI50:AL50) -> 13246445 | AN50: =AM50+AG50 -> 19689110
A51: Привлечение | G51: =G52+G53+G54 -> 57374950 | H51: =H52+H53+H54 -> 23966751 | I51: =I52+I53+I54 -> 1321802.6 | J51: =J52+J53+J54 -> 2690812.5 | K51: =SUM(G51:J51) -> 85354317 | N51: =N52+N53+N54 -> 57374950 | O51: =O52+O53+O54 -> 23966751 | P51: =P52+P53+P54 -> 1321802.6 | Q51: =Q52+Q53+Q54 -> 2690812.5 | R51: =SUM(N51:Q51) -> 85354317 | T51: =T52+T53+T54 -> 3142057.8 | U51: =U52+U53+U54 -> 1312505.2 | V51: =V52+V53+V54 -> 72386.648 | W51: =W52+W53+W54 -> 147358.53 | X51: =SUM(T51:W51) -> 4674308.2 | AC51: =AC52+AC53+AC54 -> 2787250.9 | AD51: =AD52+AD53+AD54 -> 1083783 | AE51: =AE52+AE53+AE54 -> 62243.997 | AF51: =AF52+AF53+AF54 -> 126710.99 | AG51: =SUM(AC51:AF51) -> 4059988.9 | AI51: =AI52+AI53+AI54 -> 6478884.9 | AJ51: =AJ52+AJ53+AJ54 -> 4176536.8 | AK51: =AK52+AK53+AK54 -> 185207.96 | AL51: =AL52+AL53+AL54 -> 377030.5 | AM51: =SUM(AI51:AL51) -> 11217660 | AN51: =AM51+AG51 -> 15277649
A52: Привлечение (sales, КЦ MPStas) | G52: =G19*G146 -> 54232892 | H52: =H19*H146 -> 22654246 | I52: =I19*I146 -> 1249416 | J52: =J19*J146 -> 2543454 | K52: =SUM(G52:J52) -> 80680008 | N52: =N19*N146 -> 54232892 | O52: =O19*O146 -> 22654246 | P52: =P19*P146 -> 1249416 | Q52: =Q19*Q146 -> 2543454 | R52: =SUM(N52:Q52) -> 80680008 | T52: =T19*T146 -> 0 | U52: =U19*U146 -> 0 | V52: =V19*V146 -> 0 | W52: =W19*W146 -> 0 | X52: =SUM(T52:W52) -> 0 | AC52: =AC19*AC146 -> 0 | AD52: =AD19*AD146 -> 0 | AE52: =AE19*AE146 -> 0 | AF52: =AF19*AF146 -> 0 | AG52: =SUM(AC52:AF52) -> 0 | AI52: =AI19*AI146 -> 6124077.9 | AJ52: =AJ19*AJ146 -> 3947814.7 | AK52: =AK19*AK146 -> 175065.31 | AL52: =AL19*AL146 -> 356382.96 | AM52: =SUM(AI52:AL52) -> 10603341 | AN52: =AM52+AG52 -> 10603341
A53: Привлечение (триал - 14 дн) | G53: =G7*G157*G149 -> 1125465.6 | H53: =H7*H157*H149 -> 470131.2 | I53: =I7*I157*I149 -> 25928.448 | J53: =J7*J157*J149 -> 52782.912 | K53: =SUM(G53:J53) -> 1674308.2 | N53: =N7*N157*N149 -> 1125465.6 | O53: =O7*O157*O149 -> 470131.2 | P53: =P7*P157*P149 -> 25928.448 | Q53: =Q7*Q157*Q149 -> 52782.912 | R53: =SUM(N53:Q53) -> 1674308.2 | T53: =T7*T157*T149 -> 1125465.6 | U53: =U7*U157*U149 -> 470131.2 | V53: =V7*V157*V149 -> 25928.448 | W53: =W7*W157*W149 -> 52782.912 | X53: =SUM(T53:W53) -> 1674308.2 | AC53: =AC7*AC157*AC149 -> 998375.95 | AD53: =AD7*AD157*AD149 -> 388204.36 | AE53: =AE7*AE157*AE149 -> 22295.413 | AF53: =AF7*AF157*AF149 -> 45387.091 | AG53: =SUM(AC53:AF53) -> 1454262.8 | AI53: =AI7*AI157*AI149 -> 127089.65 | AJ53: =AJ7*AJ157*AJ149 -> 81926.842 | AK53: =AK7*AK157*AK149 -> 3633.0348 | AL53: =AL7*AL157*AL149 -> 7395.8209 | AM53: =SUM(AI53:AL53) -> 220045.34 | AN53: =AM53+AG53 -> 1674308.2
A54: Привлечение (маркетинг Т внешний) | G54: =G147*G21 -> 2016592.2 | H54: =H147*H21 -> 842373.96 | I54: =I147*I21 -> 46458.2 | J54: =J147*J21 -> 94575.622 | K54: =SUM(G54:J54) -> 3000000 | N54: =N147*N21 -> 2016592.2 | O54: =O147*O21 -> 842373.96 | P54: =P147*P21 -> 46458.2 | Q54: =Q147*Q21 -> 94575.622 | R54: =SUM(N54:Q54) -> 3000000 | T54: =T147*T21 -> 2016592.2 | U54: =U147*U21 -> 842373.96 | V54: =V147*V21 -> 46458.2 | W54: =W147*W21 -> 94575.622 | X54: =SUM(T54:W54) -> 3000000 | AC54: =AC147*AC21 -> 1788874.9 | AD54: =AD147*AD21 -> 695578.69 | AE54: =AE147*AE21 -> 39948.584 | AF54: =AF147*AF21 -> 81323.902 | AG54: =SUM(AC54:AF54) -> 2605726.1 | AI54: =AI147*AI21 -> 227717.3 | AJ54: =AJ147*AJ21 -> 146795.27 | AK54: =AK147*AK21 -> 6509.6168 | AL54: =AL147*AL21 -> 13251.72 | AM54: =SUM(AI54:AL54) -> 394273.91 | AN54: =AM54+AG54 -> 3000000
A55: API | G55: =G56+G65 -> 5367440.2 | H55: =H56+H65 -> 2342564.2 | I55: =I56+I65 -> 234066.31 | J55: =J56+J65 -> 360352.7 | K55: =SUM(G55:J55) -> 8304423.5 | N55: =N56+N65 -> 8851907.7 | O55: =O56+O65 -> 3814565.7 | P55: =P56+P65 -> 314743.97 | Q55: =Q56+Q65 -> 524589.35 | R55: =SUM(N55:Q55) -> 13505807 | T55: =T56+T65 -> 1682289.2 | U55: =U56+U65 -> 777007.91 | V55: =V56+V65 -> 148527.53 | W55: =W56+W65 -> 186220.18 | X55: =SUM(T55:W55) -> 2794044.8 | AC55: =AC56+AC65 -> 1465685 | AD55: =AD56+AD65 -> 629436.65 | AE55: =AE56+AE65 -> 127953.54 | AF55: =AF56+AF65 -> 159600.99 | AG55: =SUM(AC55:AF55) -> 2382676.2 | AI55: =AI56+AI65 -> 1142801.1 | AJ55: =AJ56+AJ65 -> 757462.93 | AK55: =AK56+AK65 -> 47364.325 | AL55: =AL56+AL65 -> 81156.65 | AM55: =SUM(AI55:AL55) -> 2028785 | AN55: =AM55+AG55 -> 4411461.2
A56: Запросы к API МП (бесплатная версия Селлер) | G56: =G57+G64+G63 -> 718260.1 | H56: =H57+H64+H63 -> 369025.56 | I56: =I57+I64+I63 -> 126188.99 | J56: =J57+J64+J63 -> 140745.28 | K56: =SUM(G56:J56) -> 1354219.9 | N56: =N57+N64+N63 -> 1084709.6 | O56: =O57+O64+O63 -> 523830.9 | P56: =P57+P64+P63 -> 134673.58 | Q56: =Q57+Q64+Q63 -> 158017.49 | R56: =SUM(N56:Q56) -> 1901231.5 | T56: =T57+T64+T63 -> 330705.43 | U56: =U57+U64+U63 -> 204381.38 | V56: =V57+V64+V63 -> 117193.17 | W56: =W57+W64+W63 -> 122432.36 | X56: =SUM(T56:W56) -> 774712.33 | AC56: =AC57+AC64+AC63 -> 288703.63 | AD56: =AD57+AD64+AD63 -> 171784.11 | AE56: =AE57+AE64+AE63 -> 101669.57 | AF56: =AF57+AF64+AF63 -> 106094.34 | AG56: =SUM(AC56:AF56) -> 668251.65 | AI56: =AI57+AI64+AI63 -> 139406.74 | AJ56: =AJ57+AJ64+AJ63 -> 96737.48 | AK56: =AK57+AK64+AK63 -> 18341.046 | AL56: =AL57+AL64+AL63 -> 22073.546 | AM56: =SUM(AI56:AL56) -> 276558.81 | AN56: =AM56+AG56 -> 944810.46
A57: Запросы к API МП (бесплатная версия Селлер) - платящие | G57: =SUM(G58:G62) -> 546401.47 | H57: =SUM(H58:H62) -> 231942.92 | I57: =SUM(I58:I62) -> 12678.435 | J57: =SUM(J58:J62) -> 25809.672 | K57: =SUM(G57:J57) -> 816832.5 | N57: =SUM(N58:N62) -> 912850.95 | O57: =SUM(O58:O62) -> 386748.27 | P57: =SUM(P58:P62) -> 21163.027 | Q57: =SUM(Q58:Q62) -> 43081.877 | R57: =SUM(N57:Q57) -> 1363844.1 | T57: =SUM(T58:T62) -> 158846.8 | U57: =SUM(U58:U62) -> 67298.744 | V57: =SUM(V58:V62) -> 3682.6155 | W57: =SUM(W58:W62) -> 7496.7529 | X57: =SUM(T57:W57) -> 237324.91 | AC57: =SUM(AC58:AC62) -> 138326.4 | AD57: =SUM(AD58:AD62) -> 53786.263 | AE57: =SUM(AE58:AE62) -> 3089.061 | AF57: =SUM(AF58:AF62) -> 6288.4457 | AG57: =SUM(AC57:AF57) -> 201490.17 | AI57: =SUM(AI58:AI62) -> 117925.34 | AJ57: =SUM(AJ58:AJ62) -> 77652.694 | AK57: =SUM(AK58:AK62) -> 3411.002 | AL57: =SUM(AL58:AL62) -> 6943.8254 | AM57: =SUM(AI57:AL57) -> 205932.86 | AN57: =AM57+AG57 -> 407423.03
A58: >100 млн | G58: =(G22*G$153*G120) -> 119.54928 | H58: =(H22*H$153*H120) -> 788.23586 | I58: =(I22*I$153*I120) -> 20.806548 | J58: =(J22*J$153*J120) -> 42.356187 | K58: =SUM(G58:J58) -> 970.94788 | N58: =(N22*N$153*N120) -> 187.59045 | O58: =(O22*O$153*O120) -> 1236.8583 | P58: =(P22*P$153*P120) -> 32.648542 | Q58: =(Q22*Q$153*Q120) -> 66.463102 | R58: =SUM(N58:Q58) -> 1523.5604 | T58: =(T22*T$153*T120) -> 32.642943 | U58: =(U22*U$153*U120) -> 215.22788 | V58: =(V22*V$153*V120) -> 5.68123 | W58: =(W22*W$153*W120) -> 11.565361 | X58: =SUM(T58:W58) -> 265.11741 | AC58: =(AC22*AC$153*AC120) -> 0 | AD58: =(AD22*AD$153*AD120) -> 0 | AE58: =(AE22*AE$153*AE120) -> 0 | AF58: =(AF22*AF$153*AF120) -> 0 | AG58: =SUM(AC58:AF58) -> 0 | AI58: =(AI22*AI$153*AI120) -> 187.59045 | AJ58: =(AJ22*AJ$153*AJ120) -> 1236.8583 | AK58: =(AK22*AK$153*AK120) -> 32.648542 | AL58: =(AL22*AL$153*AL120) -> 66.463102 | AM58: =SUM(AI58:AL58) -> 1523.5604 | AN58: =AM58+AG58 -> 1523.5604
A59: 10-100 млн | G59: =(G23*G$153*G121) -> 6275.5253 | H59: =(H23*H$153*H121) -> 7171.1843 | I59: =(I23*I$153*I121) -> 255.82324 | J59: =(J23*J$153*J121) -> 520.78303 | K59: =SUM(G59:J59) -> 14223.316 | N59: =(N23*N$153*N121) -> 10043.241 | O59: =(O23*O$153*O121) -> 11476.638 | P59: =(P23*P$153*P121) -> 409.41503 | Q59: =(Q23*Q$153*Q121) -> 833.45203 | R59: =SUM(N59:Q59) -> 22762.745 | T59: =(T23*T$153*T121) -> 1747.6419 | U59: =(U23*U$153*U121) -> 1997.0698 | V59: =(V23*V$153*V121) -> 71.243027 | W59: =(W23*W$153*W121) -> 145.03045 | X59: =SUM(T59:W59) -> 3960.9852 | AC59: =(AC23*AC$153*AC121) -> 0 | AD59: =(AD23*AD$153*AD121) -> 0 | AE59: =(AE23*AE$153*AE121) -> 0 | AF59: =(AF23*AF$153*AF121) -> 0 | AG59: =SUM(AC59:AF59) -> 0 | AI59: =(AI23*AI$153*AI121) -> 10043.241 | AJ59: =(AJ23*AJ$153*AJ121) -> 11476.638 | AK59: =(AK23*AK$153*AK121) -> 409.41503 | AL59: =(AL23*AL$153*AL121) -> 833.45203 | AM59: =SUM(AI59:AL59) -> 22762.745 | AN59: =AM59+AG59 -> 22762.745
A60: 1-10 млн | G60: =(G24*G$153*G122) -> 65417.199 | H60: =(H24*H$153*H122) -> 39446.212 | I60: =(I24*I$153*I122) -> 1803.4312 | J60: =(J24*J$153*J122) -> 3671.2706 | K60: =SUM(G60:J60) -> 110338.11 | N60: =(N24*N$153*N122) -> 107694.51 | O60: =(O24*O$153*O122) -> 64939.198 | P60: =(P24*P$153*P122) -> 2968.9384 | Q60: =(Q24*Q$153*Q122) -> 6043.9103 | R60: =SUM(N60:Q60) -> 181646.55 | T60: =(T24*T$153*T122) -> 18740.11 | U60: =(U24*U$153*U122) -> 11300.184 | V60: =(V24*V$153*V122) -> 516.63018 | W60: =(W24*W$153*W122) -> 1051.7114 | X60: =SUM(T60:W60) -> 31608.636 | AC60: =(AC24*AC$153*AC122) -> 0 | AD60: =(AD24*AD$153*AD122) -> 0 | AE60: =(AE24*AE$153*AE122) -> 0 | AF60: =(AF24*AF$153*AF122) -> 0 | AG60: =SUM(AC60:AF60) -> 0 | AI60: =(AI24*AI$153*AI122) -> 107694.51 | AJ60: =(AJ24*AJ$153*AJ122) -> 64939.198 | AK60: =(AK24*AK$153*AK122) -> 2968.9384 | AL60: =(AL24*AL$153*AL122) -> 6043.9103 | AM60: =SUM(AI60:AL60) -> 181646.55 | AN60: =AM60+AG60 -> 181646.55
A61: менее 1 млн | G61: =(G25*G$153*G123) -> 474589.2 | H61: =(H25*H$153*H123) -> 184537.29 | I61: =(I25*I$153*I123) -> 10598.375 | J61: =(J25*J$153*J123) -> 21575.262 | K61: =SUM(G61:J61) -> 691300.13 | N61: =(N25*N$153*N123) -> 794925.61 | O61: =(O25*O$153*O123) -> 309095.57 | P61: =(P25*P$153*P123) -> 17752.025 | Q61: =(Q25*Q$153*Q123) -> 36138.051 | R61: =SUM(N61:Q61) -> 1157911.3 | T61: =(T25*T$153*T123) -> 138326.4 | U61: =(U25*U$153*U123) -> 53786.263 | V61: =(V25*V$153*V123) -> 3089.061 | W61: =(W25*W$153*W123) -> 6288.4457 | X61: =SUM(T61:W61) -> 201490.17 | AC61: =(AC25*AC$153*AC123) -> 138326.4 | AD61: =(AD25*AD$153*AD123) -> 53786.263 | AE61: =(AE25*AE$153*AE123) -> 3089.061 | AF61: =(AF25*AF$153*AF123) -> 6288.4457 | AG61: =SUM(AC61:AF61) -> 201490.17 | AI61: =(AI25*AI$153*AI123) -> 0 | AJ61: =(AJ25*AJ$153*AJ123) -> 0 | AK61: =(AK25*AK$153*AK123) -> 0 | AL61: =(AL25*AL$153*AL123) -> 0 | AM61: =SUM(AI61:AL61) -> 0 | AN61: =AM61+AG61 -> 201490.17
A62: без оборотов | G62: =(G26*G$153*G124) -> 0 | H62: =(H26*H$153*H124) -> 0 | I62: =(I26*I$153*I124) -> 0 | J62: =(J26*J$153*J124) -> 0 | K62: =SUM(G62:J62) -> 0 | N62: =(N26*N$153*N124) -> 0 | O62: =(O26*O$153*O124) -> 0 | P62: =(P26*P$153*P124) -> 0 | Q62: =(Q26*Q$153*Q124) -> 0 | R62: =SUM(N62:Q62) -> 0 | T62: =(T26*T$153*T124) -> 0 | U62: =(U26*U$153*U124) -> 0 | V62: =(V26*V$153*V124) -> 0 | W62: =(W26*W$153*W124) -> 0 | X62: =SUM(T62:W62) -> 0 | AC62: =(AC26*AC$153*AC124) -> 0 | AD62: =(AD26*AD$153*AD124) -> 0 | AE62: =(AE26*AE$153*AE124) -> 0 | AF62: =(AF26*AF$153*AF124) -> 0 | AG62: =SUM(AC62:AF62) -> 0 | AI62: =(AI26*AI$153*AI124) -> 0 | AJ62: =(AJ26*AJ$153*AJ124) -> 0 | AK62: =(AK26*AK$153*AK124) -> 0 | AL62: =(AL26*AL$153*AL124) -> 0 | AM62: =SUM(AI62:AL62) -> 0 | AN62: =AM62+AG62 -> 0
A63: Запросы к API МП (бесплатная версия Селлер) - НЕ платящие | G63: =G164*G158*G154*G162 -> 112134.63 | H63: =H164*H158*H154*H162 -> 112134.63 | I63: =I164*I158*I154*I162 -> 112134.63 | J63: =J164*J158*J154*J162 -> 112134.63 | K63: =SUM(G63:J63) -> 448538.53 | N63: =N164*N158*N154*N162 -> 112134.63 | O63: =O164*O158*O154*O162 -> 112134.63 | P63: =P164*P158*P154*P162 -> 112134.63 | Q63: =Q164*Q158*Q154*Q162 -> 112134.63 | R63: =SUM(N63:Q63) -> 448538.53 | T63: =T164*T158*T154*T162 -> 112134.63 | U63: =U164*U158*U154*U162 -> 112134.63 | V63: =V164*V158*V154*V162 -> 112134.63 | W63: =W164*W158*W154*W162 -> 112134.63 | X63: =SUM(T63:W63) -> 448538.53 | AC63: =AC164*AC158*AC154*AC162 -> 97397.378 | AD63: =AD164*AD158*AD154*AD162 -> 97397.378 | AE63: =AE164*AE158*AE154*AE162 -> 97397.378 | AF63: =AF164*AF158*AF154*AF162 -> 97397.378 | AG63: =SUM(AC63:AF63) -> 389589.51 | AI63: =AI164*AI158*AI154*AI162 -> 14737.253 | AJ63: =AJ164*AJ158*AJ154*AJ162 -> 14737.253 | AK63: =AK164*AK158*AK154*AK162 -> 14737.253 | AL63: =AL164*AL158*AL154*AL162 -> 14737.253 | AM63: =SUM(AI63:AL63) -> 58949.013 | AN63: =AM63+AG63 -> 448538.53
A64: Запросы к API МП (бесплатная версия Селлер) - лиды | G64: =G7*G156*G155 -> 59724 | H64: =H7*H156*H155 -> 24948 | I64: =I7*I156*I155 -> 1375.92 | J64: =J7*J156*J155 -> 2800.98 | K64: =SUM(G64:J64) -> 88848.9 | N64: =N7*N156*N155 -> 59724 | O64: =O7*O156*O155 -> 24948 | P64: =P7*P156*P155 -> 1375.92 | Q64: =Q7*Q156*Q155 -> 2800.98 | R64: =SUM(N64:Q64) -> 88848.9 | T64: =T7*T156*T155 -> 59724 | U64: =U7*U156*U155 -> 24948 | V64: =V7*V156*V155 -> 1375.92 | W64: =W7*W156*W155 -> 2800.98 | X64: =SUM(T64:W64) -> 88848.9 | AC64: =AC7*AC156*AC155 -> 52979.856 | AD64: =AD7*AD156*AD155 -> 20600.467 | AE64: =AE7*AE156*AE155 -> 1183.1292 | AF64: =AF7*AF156*AF155 -> 2408.5131 | AG64: =SUM(AC64:AF64) -> 77171.966 | AI64: =AI7*AI156*AI155 -> 6744.1439 | AJ64: =AJ7*AJ156*AJ155 -> 4347.5329 | AK64: =AK7*AK156*AK155 -> 192.79076 | AL64: =AL7*AL156*AL155 -> 392.46691 | AM64: =SUM(AI64:AL64) -> 11676.934 | AN64: =AM64+AG64 -> 88848.9
A65: Запросы к API МП (за MPStats) | G65: =SUM(G66:G70) -> 4649180.1 | H65: =SUM(H66:H70) -> 1973538.7 | I65: =SUM(I66:I70) -> 107877.33 | J65: =SUM(J66:J70) -> 219607.42 | K65: =SUM(G65:J65) -> 6950203.5 | N65: =SUM(N66:N70) -> 7767198.1 | O65: =SUM(O66:O70) -> 3290734.8 | P65: =SUM(P66:P70) -> 180070.39 | Q65: =SUM(Q66:Q70) -> 366571.86 | R65: =SUM(N65:Q65) -> 11604575 | T65: =SUM(T66:T70) -> 1351583.8 | U65: =SUM(U66:U70) -> 572626.54 | V65: =SUM(V66:V70) -> 31334.364 | W65: =SUM(W66:W70) -> 63787.812 | X65: =SUM(T65:W65) -> 2019332.5 | AC65: =SUM(AC66:AC70) -> 1176981.4 | AD65: =SUM(AD66:AD70) -> 457652.54 | AE65: =SUM(AE66:AE70) -> 26283.972 | AF65: =SUM(AF66:AF70) -> 53506.658 | AG65: =SUM(AC65:AF65) -> 1714424.5 | AI65: =SUM(AI66:AI70) -> 1003394.3 | AJ65: =SUM(AJ66:AJ70) -> 660725.45 | AK65: =SUM(AK66:AK70) -> 29023.279 | AL65: =SUM(AL66:AL70) -> 59083.104 | AM65: =SUM(AI65:AL65) -> 1752226.2 | AN65: =AM65+AG65 -> 3466650.7
A66: >100 млн | G66: =G22*G120*G$152 -> 1017.212 | H66: =H22*H120*H$152 -> 6706.8825 | I66: =I22*I120*I$152 -> 177.03721 | J66: =J22*J120*J$152 -> 360.39717 | K66: =SUM(G66:J66) -> 8261.5289 | N66: =N22*N120*N$152 -> 1596.1556 | O66: =O22*O120*O$152 -> 10524.087 | P66: =P22*P120*P$152 -> 277.79748 | Q66: =Q22*Q120*Q$152 -> 565.51629 | R66: =SUM(N66:Q66) -> 12963.557 | T66: =T22*T120*T$152 -> 277.74984 | U66: =U22*U120*U$152 -> 1831.3149 | V66: =V22*V120*V$152 -> 48.340026 | W66: =W22*W120*W$152 -> 98.406482 | X66: =SUM(T66:W66) -> 2255.8113 | AC66: =AC22*AC120*AC$152 -> 0 | AD66: =AD22*AD120*AD$152 -> 0 | AE66: =AE22*AE120*AE$152 -> 0 | AF66: =AF22*AF120*AF$152 -> 0 | AG66: =SUM(AC66:AF66) -> 0 | AI66: =AI22*AI120*AI$152 -> 1596.1556 | AJ66: =AJ22*AJ120*AJ$152 -> 10524.087 | AK66: =AK22*AK120*AK$152 -> 277.79748 | AL66: =AL22*AL120*AL$152 -> 565.51629 | AM66: =SUM(AI66:AL66) -> 12963.557 | AN66: =AM66+AG66 -> 12963.557
A67: 10-100 млн | G67: =G23*G121*G$152 -> 53396.722 | H67: =H23*H121*H$152 -> 61017.638 | I67: =I23*I121*I$152 -> 2176.7297 | J67: =J23*J121*J$152 -> 4431.1998 | K67: =SUM(G67:J67) -> 121022.29 | N67: =N23*N121*N$152 -> 85455.178 | O67: =O23*O121*O$152 -> 97651.558 | P67: =P23*P121*P$152 -> 3483.6001 | Q67: =Q23*Q121*Q$152 -> 7091.6145 | R67: =SUM(N67:Q67) -> 193681.95 | T67: =T23*T121*T$152 -> 14870.205 | U67: =U23*U121*U$152 -> 16992.519 | V67: =V23*V121*V$152 -> 606.18736 | W67: =W23*W121*W$152 -> 1234.0243 | X67: =SUM(T67:W67) -> 33702.936 | AC67: =AC23*AC121*AC$152 -> 0 | AD67: =AD23*AD121*AD$152 -> 0 | AE67: =AE23*AE121*AE$152 -> 0 | AF67: =AF23*AF121*AF$152 -> 0 | AG67: =SUM(AC67:AF67) -> 0 | AI67: =AI23*AI121*AI$152 -> 85455.178 | AJ67: =AJ23*AJ121*AJ$152 -> 97651.558 | AK67: =AK23*AK121*AK$152 -> 3483.6001 | AL67: =AL23*AL121*AL$152 -> 7091.6145 | AM67: =SUM(AI67:AL67) -> 193681.95 | AN67: =AM67+AG67 -> 193681.95
A68: 1-10 млн | G68: =G24*G122*G$152 -> 556616.98 | H68: =H24*H122*H$152 -> 335636.99 | I68: =I24*I122*I$152 -> 15344.901 | J68: =J24*J122*J$152 -> 31237.834 | K68: =SUM(G68:J68) -> 938836.71 | N68: =N24*N122*N$152 -> 916343 | O68: =O24*O122*O$152 -> 552549.81 | P68: =P24*P122*P$152 -> 25261.882 | Q68: =Q24*Q122*Q$152 -> 51425.974 | R68: =SUM(N68:Q68) -> 1545580.7 | T68: =T24*T122*T$152 -> 159454.45 | U68: =U24*U122*U$152 -> 96150.161 | V68: =V24*V122*V$152 -> 4395.8643 | W68: =W24*W122*W$152 -> 8948.7238 | X68: =SUM(T68:W68) -> 268949.2 | AC68: =AC24*AC122*AC$152 -> 0 | AD68: =AD24*AD122*AD$152 -> 0 | AE68: =AE24*AE122*AE$152 -> 0 | AF68: =AF24*AF122*AF$152 -> 0 | AG68: =SUM(AC68:AF68) -> 0 | AI68: =AI24*AI122*AI$152 -> 916343 | AJ68: =AJ24*AJ122*AJ$152 -> 552549.81 | AK68: =AK24*AK122*AK$152 -> 25261.882 | AL68: =AL24*AL122*AL$152 -> 51425.974 | AM68: =SUM(AI68:AL68) -> 1545580.7 | AN68: =AM68+AG68 -> 1545580.7
A69: менее 1 млн | G69: =G25*G123*G$152 -> 4038149.2 | H69: =H25*H123*H$152 -> 1570177.2 | I69: =I25*I123*I$152 -> 90178.659 | J69: =J25*J123*J$152 -> 183577.98 | K69: =SUM(G69:J69) -> 5882083 | N69: =N25*N123*N$152 -> 6763803.8 | O69: =O25*O123*O$152 -> 2630009.4 | P69: =P25*P123*P$152 -> 151047.11 | Q69: =Q25*Q123*Q$152 -> 307488.76 | R69: =SUM(N69:Q69) -> 9852349 | T69: =T25*T123*T$152 -> 1176981.4 | U69: =U25*U123*U$152 -> 457652.54 | V69: =V25*V123*V$152 -> 26283.972 | W69: =W25*W123*W$152 -> 53506.658 | X69: =SUM(T69:W69) -> 1714424.5 | AC69: =AC25*AC123*AC$152 -> 1176981.4 | AD69: =AD25*AD123*AD$152 -> 457652.54 | AE69: =AE25*AE123*AE$152 -> 26283.972 | AF69: =AF25*AF123*AF$152 -> 53506.658 | AG69: =SUM(AC69:AF69) -> 1714424.5 | AI69: =AI25*AI123*AI$152 -> 0 | AJ69: =AJ25*AJ123*AJ$152 -> 0 | AK69: =AK25*AK123*AK$152 -> 0 | AL69: =AL25*AL123*AL$152 -> 0 | AM69: =SUM(AI69:AL69) -> 0 | AN69: =AM69+AG69 -> 1714424.5
A70: без оборотов | G70: =G26*G124*G$152 -> 0 | H70: =H26*H124*H$152 -> 0 | I70: =I26*I124*I$152 -> 0 | J70: =J26*J124*J$152 -> 0 | K70: =SUM(G70:J70) -> 0 | N70: =N26*N124*N$152 -> 0 | O70: =O26*O124*O$152 -> 0 | P70: =P26*P124*P$152 -> 0 | Q70: =Q26*Q124*Q$152 -> 0 | R70: =SUM(N70:Q70) -> 0 | T70: =T26*T124*T$152 -> 0 | U70: =U26*U124*U$152 -> 0 | V70: =V26*V124*V$152 -> 0 | W70: =W26*W124*W$152 -> 0 | X70: =SUM(T70:W70) -> 0 | AC70: =AC26*AC124*AC$152 -> 0 | AD70: =AD26*AD124*AD$152 -> 0 | AE70: =AE26*AE124*AE$152 -> 0 | AF70: =AF26*AF124*AF$152 -> 0 | AG70: =SUM(AC70:AF70) -> 0 | AI70: =AI26*AI124*AI$152 -> 0 | AJ70: =AJ26*AJ124*AJ$152 -> 0 | AK70: =AK26*AK124*AK$152 -> 0 | AL70: =AL26*AL124*AL$152 -> 0 | AM70: =SUM(AI70:AL70) -> 0 | AN70: =AM70+AG70 -> 0
A71: Продление и удержание MPStas | G71: =G21*G167 -> 6917347.3 | H71: =H21*H167 -> 2889524.8 | I71: =I21*I167 -> 159361.67 | J71: =J21*J167 -> 324414.83 | K71: =SUM(G71:J71) -> 10290649 | N71: =N21*N167 -> 0 | O71: =O21*O167 -> 0 | P71: =P21*P167 -> 0 | Q71: =Q21*Q167 -> 0 | R71: =SUM(N71:Q71) -> 0 | T71: =T19*T167 -> 0 | U71: =U19*U167 -> 0 | V71: =V19*V167 -> 0 | W71: =W19*W167 -> 0 | X71: =SUM(T71:W71) -> 0 | AC71: =AC19*AC167 -> 0 | AD71: =AD19*AD167 -> 0 | AE71: =AE19*AE167 -> 0 | AF71: =AF19*AF167 -> 0 | AG71: =SUM(AC71:AF71) -> 0 | AI71: =AI21*AI167 -> 0 | AJ71: =AJ21*AJ167 -> 0 | AK71: =AK21*AK167 -> 0 | AL71: =AL21*AL167 -> 0 | AM71: =SUM(AI71:AL71) -> 0 | AN71: =AM71+AG71 -> 0
A74: Потенциальная прибыль: тарифы MPStats Доходы - Расходы на привлечение, API, продление и удержание | G74: =G44-G50 -> 20829101 | H74: =H44-H50 -> 9317909.2 | I74: =I44-I50 -> 386995.58 | J74: =J44-J50 -> 903951.88 | K74: =SUM(G74:J74) -> 31437958 | N74: =N44-N50 -> 84942283 | O74: =O44-O50 -> 36431329 | P74: =P44-P50 -> 1872150.4 | Q74: =Q44-Q50 -> 3927302.8 | R74: =SUM(N74:Q74) -> 1.2717306e+08 | T74: =T44-T50 -> 21480860 | U74: =U44-U50 -> 9084242.1 | V74: =V44-V50 -> 389640.34 | W74: =W44-W50 -> 909335.85 | X74: =SUM(T74:W74) -> 31864079 | AC74: =AC44-AC50 -> 18634821 | AD74: =AD44-AD50 -> 7186360.5 | AE74: =AE44-AE50 -> 320924.54 | AF74: =AF44-AF50 -> 754186.53 | AG74: =SUM(AC74:AF74) -> 26896292 | AI74: =AI44-AI50 -> 12017508 | AJ74: =AJ44-AJ50 -> 8135088.3 | AK74: =AK44-AK50 -> 338839.95 | AL74: =AL44-AL50 -> 705044.91 | AM74: =SUM(AI74:AL74) -> 21196481 | AN74: =AM74+AG74 -> 48092774
R75: =R74/K74 -> 4.0452076
A76: Потенциальная прибыль: продукты Т-Банк (влияние MPStats) NVP от всех продуктов Т-Банк | G76: =G19*G139 -> 0 | H76: =H19*H139 -> 0 | I76: =I6*I139 -> 5200000 | J76: =J6*J139 -> 49320000 | K76: =SUM(G76:J76) -> 54520000 | N76: =N21*N140 -> 50775660 | O76: =O21*O140 -> 21210086 | P76: =P6*P139 -> 6240000 | Q76: =Q6*Q139 -> 59184000 | R76: =SUM(N76:Q76) -> 1.3740975e+08 | T76: =T21*T140 -> 8835561.6 | U76: =U21*U140 -> 3690804.2 | V76: =V6*V139 -> 6240000 | W76: =W6*W139 -> 59184000 | X76: =SUM(T76:W76) -> 77950366 | AC76: =AC21*AC140 -> 7837833.7 | AD76: =AD21*AD140 -> 3047630.7 | AE76: =AE6*AE139 -> 5365665.5 | AF76: =AF6*AF139 -> 50891273 | AG76: =SUM(AC76:AF76) -> 67142403 | AI76: =AI21*AI140 -> 5733680.9 | AJ76: =AJ21*AJ140 -> 3696149.8 | AK76: =AK6*AK139 -> 874334.53 | AL76: =AL6*AL139 -> 8292726.7 | AM76: =SUM(AI76:AL76) -> 18596892 | AN76: =AM76+AG76 -> 85739295
A78: Потенциальная прибыль: всего | G78: =G74+G76 -> 20829101 | H78: =H74+H76 -> 9317909.2 | I78: =I74+I76 -> 5586995.6 | J78: =J74+J76 -> 50223952 | K78: =SUM(G78:J78) -> 85957958 | N78: =N74+N76 -> 1.3571794e+08 | O78: =O74+O76 -> 57641415 | P78: =P74+P76 -> 8112150.4 | Q78: =Q74+Q76 -> 63111303 | R78: =SUM(N78:Q78) -> 2.6458281e+08 | T78: =T74+T76 -> 30316422 | U78: =U74+U76 -> 12775046 | V78: =V74+V76 -> 6629640.3 | W78: =W74+W76 -> 60093336 | X78: =SUM(T78:W78) -> 1.0981444e+08 | AC78: =AC74+AC76 -> 26472655 | AD78: =AD74+AD76 -> 10233991 | AE78: =AE74+AE76 -> 5686590 | AF78: =AF74+AF76 -> 51645460 | AG78: =SUM(AC78:AF78) -> 94038696 | AI78: =AI74+AI76 -> 17751189 | AJ78: =AJ74+AJ76 -> 11831238 | AK78: =AK74+AK76 -> 1213174.5 | AL78: =AL74+AL76 -> 8997771.6 | AM78: =SUM(AI78:AL78) -> 39793373 | AN78: =AM78+AG78 -> 1.3383207e+08
R79: =R78/K78 -> 3.0780491
R80: =(R78-K78)/K78 -> 2.0780491
A81: Данные для расчета
A82: LTV - тарифы MPStats
A83: Распределение селлров as is
A84: Распределение селлеров по сегментам по оборотам в Т-Банке (акт РКО/ не утиль Озони ВБ) | G84: без учета пересечений баз с MPStats (нет данных) | N84: без учета пересечений баз с MPStats (нет данных) | T84: без учета пересечений баз с MPStats (нет данных)
A85: >100 млн | G85: ='База селлеров'!B38 -> 0.0001091635 | H85: ='База селлеров'!C38 -> 0.0017230576 | I85: ='База селлеров'!D38 -> 0.00082468141 | J85: ='База селлеров'!E38 -> 0.00082468141 | N85: =G85 -> 0.0001091635 | O85: =H85 -> 0.0017230576 | P85: =I85 -> 0.00082468141 | Q85: =J85 -> 0.00082468141 | T85: =N85 -> 0.0001091635 | U85: =O85 -> 0.0017230576 | V85: =P85 -> 0.00082468141 | W85: =Q85 -> 0.00082468141 | AC85: 0 | AD85: 0 | AE85: 0 | AF85: 0 | AI85: =T85/(T85+T86+T87) -> 0.0009667173 | AJ85: =U85/(U85+U86+U87) -> 0.0098876404 | AK85: =V85/(V85+V86+V87) -> 0.0058856329 | AL85: =W85/(W85+W86+W87) -> 0.0058856329
A86: 10-100 млн | G86: ='База селлеров'!B39 -> 0.0075010916 | H86: ='База селлеров'!C39 -> 0.02052005 | I86: ='База селлеров'!D39 -> 0.01327303 | J86: =I86 -> 0.01327303 | N86: =G86 -> 0.0075010916 | O86: =H86 -> 0.02052005 | P86: =I86 -> 0.01327303 | Q86: =J86 -> 0.01327303 | T86: =N86 -> 0.0075010916 | U86: =O86 -> 0.02052005 | V86: =P86 -> 0.01327303 | W86: =Q86 -> 0.01327303 | AC86: 0 | AD86: 0 | AE86: 0 | AF86: 0 | AI86: =T86/(T85+T86+T87) -> 0.066427289 | AJ86: =U86/(U85+U86+U87) -> 0.11775281 | AK86: =V86/(V85+V86+V87) -> 0.094727712 | AL86: =W86/(W85+W86+W87) -> 0.094727712
A87: 1-10 млн | G87: ='База селлеров'!B40 -> 0.10531158 | H87: ='База селлеров'!C40 -> 0.15202068 | I87: ='База селлеров'!D40 -> 0.12602 | J87: ='База селлеров'!E40 -> 0.12602 | N87: =G87 -> 0.10531158 | O87: =H87 -> 0.15202068 | P87: =I87 -> 0.12602 | Q87: =J87 -> 0.12602 | T87: =N87 -> 0.10531158 | U87: =O87 -> 0.15202068 | V87: =P87 -> 0.12602 | W87: =Q87 -> 0.12602 | AC87: 0 | AD87: 0 | AE87: 0 | AF87: 0 | AI87: =T87/(T85+T86+T87) -> 0.93260599 | AJ87: =U87/(U85+U86+U87) -> 0.87235955 | AK87: =V87/(V85+V86+V87) -> 0.89938666 | AL87: =W87/(W85+W86+W87) -> 0.89938666
A88: менее 1 млн | G88: ='База селлеров'!B41 -> 0.88707816 | H88: ='База селлеров'!C41 -> 0.82573622 | I88: ='База селлеров'!D41 -> 0.85988229 | J88: ='База селлеров'!E41 -> 0.85988229 | N88: =G88 -> 0.88707816 | O88: =H88 -> 0.82573622 | P88: =I88 -> 0.85988229 | Q88: =J88 -> 0.85988229 | T88: =N88 -> 0.88707816 | U88: =O88 -> 0.82573622 | V88: =P88 -> 0.85988229 | W88: =Q88 -> 0.85988229 | AC88: 1 | AD88: 1 | AE88: 1 | AF88: 1 | AI88: 0 | AJ88: 0 | AK88: 0 | AL88: 0
A89: без оборотов | G89: 0 | H89: 0 | I89: 0 | J89: 0 | N89: =G89 -> 0 | O89: =H89 -> 0 | P89: =I89 -> 0 | Q89: =J89 -> 0 | T89: =N89 -> 0 | U89: =O89 -> 0 | V89: =P89 -> 0 | W89: =Q89 -> 0 | AC89: 0 | AD89: 0 | AE89: 0 | AF89: 0 | AI89: =AC89 -> 0 | AJ89: =AD89 -> 0 | AK89: =AE89 -> 0 | AL89: =AF89 -> 0
A93: LTV гипотеза: тарифы MPStats | G93: скидка 50% от тарифов MPS | M93: LT выше (досписания-люготный период) | N93: гипотеза: +1 мес к LT (за счет досписания с РКО на след мес при недостатке ДС) | T93: гипотеза: +1 мес к LT (за счет досписания с РКО на след мес при недостатке ДС)
A94: Сегмент по обороту
A95: >100 млн | G95: =G104/2 -> 55362.5 | H95: =H104/2 -> 55362.5 | I95: =I104/2 -> 55362.5 | J95: =J104/2 -> 55362.5 | N95: =N112/2*N120 -> 59174.344 | O95: =N95 -> 59174.344 | P95: =O95 -> 59174.344 | Q95: =P95 -> 59174.344 | T95: =N95 -> 59174.344 | U95: =T95 -> 59174.344 | V95: =U95 -> 59174.344 | W95: =V95 -> 59174.344 | AC95: =T95 -> 59174.344 | AD95: =AC95 -> 59174.344 | AE95: =AD95 -> 59174.344 | AF95: =AE95 -> 59174.344 | AI95: =AC95 -> 59174.344 | AJ95: =AI95 -> 59174.344 | AK95: =AJ95 -> 59174.344 | AL95: =AK95 -> 59174.344
A96: 10 + млн | G96: =G105/2 -> 35026.5 | H96: =H105/2 -> 35026.5 | I96: =I105/2 -> 35026.5 | J96: =J105/2 -> 35026.5 | N96: =N113/2*N121 -> 38183.395 | O96: =N96 -> 38183.395 | P96: =O96 -> 38183.395 | Q96: =P96 -> 38183.395 | T96: =N96 -> 38183.395 | U96: =T96 -> 38183.395 | V96: =U96 -> 38183.395 | W96: =V96 -> 38183.395 | AC96: =T96 -> 38183.395 | AD96: =AC96 -> 38183.395 | AE96: =AD96 -> 38183.395 | AF96: =AE96 -> 38183.395 | AI96: =AC96 -> 38183.395 | AJ96: =AI96 -> 38183.395 | AK96: =AJ96 -> 38183.395 | AL96: =AK96 -> 38183.395
A97: 1-10 млн | G97: =G106/2 -> 23721.5 | H97: =H106/2 -> 23721.5 | I97: =I106/2 -> 23721.5 | J97: =J106/2 -> 23721.5 | N97: =N114/2*N122 -> 26600.988 | O97: =N97 -> 26600.988 | P97: =O97 -> 26600.988 | Q97: =P97 -> 26600.988 | T97: =N97 -> 26600.988 | U97: =T97 -> 26600.988 | V97: =U97 -> 26600.988 | W97: =V97 -> 26600.988 | AC97: =T97 -> 26600.988 | AD97: =AC97 -> 26600.988 | AE97: =AD97 -> 26600.988 | AF97: =AE97 -> 26600.988 | AI97: =AC97 -> 26600.988 | AJ97: =AI97 -> 26600.988 | AK97: =AJ97 -> 26600.988 | AL97: =AK97 -> 26600.988
A98: менее 1 млн | G98: =G107/2 -> 20475.5 | H98: =H107/2 -> 20475.5 | I98: =I107/2 -> 20475.5 | J98: =J107/2 -> 20475.5 | N98: =N115/2*N123 -> 23361.309 | O98: =N98 -> 23361.309 | P98: =O98 -> 23361.309 | Q98: =P98 -> 23361.309 | T98: =N98 -> 23361.309 | U98: =T98 -> 23361.309 | V98: =U98 -> 23361.309 | W98: =V98 -> 23361.309 | AC98: =T98 -> 23361.309 | AD98: =AC98 -> 23361.309 | AE98: =AD98 -> 23361.309 | AF98: =AE98 -> 23361.309 | AI98: =AC98 -> 23361.309 | AJ98: =AI98 -> 23361.309 | AK98: =AJ98 -> 23361.309 | AL98: =AK98 -> 23361.309
A99: без оборотов | G99: =G108/2 -> 16914 | H99: =H108/2 -> 16914 | I99: =I108/2 -> 16914 | J99: =J108/2 -> 16914 | N99: =N116/2*N124 -> 19667.442 | O99: =N99 -> 19667.442 | P99: =O99 -> 19667.442 | Q99: =P99 -> 19667.442 | T99: =N99 -> 19667.442 | U99: =T99 -> 19667.442 | V99: =U99 -> 19667.442 | W99: =V99 -> 19667.442 | AC99: =T99 -> 19667.442 | AD99: =AC99 -> 19667.442 | AE99: =AD99 -> 19667.442 | AF99: =AE99 -> 19667.442 | AI99: =AC99 -> 19667.442 | AJ99: =AI99 -> 19667.442 | AK99: =AJ99 -> 19667.442 | AL99: =AK99 -> 19667.442
A100: связь с селлером не найдена | G100: =G109/2 -> 10790.5 | H100: =H109/2 -> 10790.5 | I100: =I109/2 -> 10790.5 | J100: =J109/2 -> 10790.5 | N100: =N117/2*N125 -> 13126.588 | O100: =N100 -> 13126.588 | P100: =O100 -> 13126.588 | Q100: =P100 -> 13126.588 | T100: =N100 -> 13126.588 | U100: =T100 -> 13126.588 | V100: =U100 -> 13126.588 | W100: =V100 -> 13126.588 | AC100: =T100 -> 13126.588 | AD100: =AC100 -> 13126.588 | AE100: =AD100 -> 13126.588 | AF100: =AE100 -> 13126.588 | AI100: =AC100 -> 13126.588 | AJ100: =AI100 -> 13126.588 | AK100: =AJ100 -> 13126.588 | AL100: =AK100 -> 13126.588
A102: LTV as is: MPStats ( май 25-апр 26)
A103: Сегмент по обороту
A104: >100 млн | G104: ='MPS др метрики'!C110 -> 110725 | H104: =G104 -> 110725 | I104: =H104 -> 110725 | J104: =I104 -> 110725 | N104: =G104 -> 110725 | O104: =N104 -> 110725 | P104: =O104 -> 110725 | Q104: =P104 -> 110725 | T104: =N104 -> 110725 | U104: =O104 -> 110725 | V104: =P104 -> 110725 | W104: =Q104 -> 110725 | AC104: =T104 -> 110725 | AD104: =U104 -> 110725 | AE104: =V104 -> 110725 | AF104: =W104 -> 110725 | AI104: =AC104 -> 110725 | AJ104: =AD104 -> 110725 | AK104: =AE104 -> 110725 | AL104: =AF104 -> 110725
A105: 10 + млн | G105: ='MPS др метрики'!C111 -> 70053 | H105: =G105 -> 70053 | I105: =H105 -> 70053 | J105: =I105 -> 70053 | N105: =G105 -> 70053 | O105: =N105 -> 70053 | P105: =O105 -> 70053 | Q105: =P105 -> 70053 | T105: =N105 -> 70053 | U105: =O105 -> 70053 | V105: =P105 -> 70053 | W105: =Q105 -> 70053 | AC105: =T105 -> 70053 | AD105: =U105 -> 70053 | AE105: =V105 -> 70053 | AF105: =W105 -> 70053 | AI105: =AC105 -> 70053 | AJ105: =AD105 -> 70053 | AK105: =AE105 -> 70053 | AL105: =AF105 -> 70053
A106: 1-10 млн | G106: ='MPS др метрики'!C112 -> 47443 | H106: =G106 -> 47443 | I106: =H106 -> 47443 | J106: =I106 -> 47443 | N106: =G106 -> 47443 | O106: =N106 -> 47443 | P106: =O106 -> 47443 | Q106: =P106 -> 47443 | T106: =N106 -> 47443 | U106: =O106 -> 47443 | V106: =P106 -> 47443 | W106: =Q106 -> 47443 | AC106: =T106 -> 47443 | AD106: =U106 -> 47443 | AE106: =V106 -> 47443 | AF106: =W106 -> 47443 | AI106: =AC106 -> 47443 | AJ106: =AD106 -> 47443 | AK106: =AE106 -> 47443 | AL106: =AF106 -> 47443
A107: менее 1 млн | G107: ='MPS др метрики'!C113 -> 40951 | H107: =G107 -> 40951 | I107: =H107 -> 40951 | J107: =I107 -> 40951 | N107: =G107 -> 40951 | O107: =N107 -> 40951 | P107: =O107 -> 40951 | Q107: =P107 -> 40951 | T107: =N107 -> 40951 | U107: =O107 -> 40951 | V107: =P107 -> 40951 | W107: =Q107 -> 40951 | AC107: =T107 -> 40951 | AD107: =U107 -> 40951 | AE107: =V107 -> 40951 | AF107: =W107 -> 40951 | AI107: =AC107 -> 40951 | AJ107: =AD107 -> 40951 | AK107: =AE107 -> 40951 | AL107: =AF107 -> 40951
A108: без оборотов | G108: ='MPS др метрики'!C114 -> 33828 | H108: =G108 -> 33828 | I108: =H108 -> 33828 | J108: =I108 -> 33828 | N108: =G108 -> 33828 | O108: =N108 -> 33828 | P108: =O108 -> 33828 | Q108: =P108 -> 33828 | T108: =N108 -> 33828 | U108: =O108 -> 33828 | V108: =P108 -> 33828 | W108: =Q108 -> 33828 | AC108: =T108 -> 33828 | AD108: =U108 -> 33828 | AE108: =V108 -> 33828 | AF108: =W108 -> 33828 | AI108: =AC108 -> 33828 | AJ108: =AD108 -> 33828 | AK108: =AE108 -> 33828 | AL108: =AF108 -> 33828
A109: связь с селлером не найдена | G109: ='MPS др метрики'!C115 -> 21581 | H109: =G109 -> 21581 | I109: =H109 -> 21581 | J109: =I109 -> 21581 | N109: =G109 -> 21581 | O109: =N109 -> 21581 | P109: =O109 -> 21581 | Q109: =P109 -> 21581 | T109: =N109 -> 21581 | U109: =O109 -> 21581 | V109: =P109 -> 21581 | W109: =Q109 -> 21581 | AC109: =T109 -> 21581 | AD109: =U109 -> 21581 | AE109: =V109 -> 21581 | AF109: =W109 -> 21581 | AI109: =AC109 -> 21581 | AJ109: =AD109 -> 21581 | AK109: =AE109 -> 21581 | AL109: =AF109 -> 21581
...

Sheet Саммари_воронка
A1: Гипотеза акт
B2: 1. Sales MPS – Биллинг MPS | C2: 2. Sales MPS – Биллинг Т | D2: 3.Digital – Биллинг Т | E2: 4. Digital + Sales MPS (>1 млн) – Биллинг Т | G2: Тесты Sales (< 1млн) - проверка доходности
A3: Воронка
A4: Лиды | B4: =Воронка!K7 -> 58762.5 | C4: =B4 -> 58762.5 | D4: =C4 -> 58762.5 | E4: =D4 -> 58762.5
A5: Оплаты тарифов | B5: =Воронка!K21 -> 4019.7846 | C5: =Воронка!R21 -> 5901.3147 | D5: =Воронка!X21 -> 1026.8981 | E5: =Воронка!AN21 -> 1667.5165
A6: CR в оплату (от всех лидов) | B6: =Воронка!E21 -> 0.068407311 | C6: =Воронка!L21 -> 0.10042654 | D6: =Воронка!S19 -> 0.017475399 | E6: =Воронка!AA21 -> 0.028377223 | I6: CR в оплату (от всех лидов) – основной канал + самходы digital
A7: CR - точка безубыточности | B7: 0.0122 | C7: 0.0097 | D7: 0.0025 | E7: 0,26% / 0,57% | H7: =C6/B6 -> 1.4680674 | I7: CR в покупку с билингом Т (#1 vs #2) вышевыше в 1,5 раза за счет рекурентных платежей
A8: Доходы и расходы на 1 платящего клиента
A9: LTV | B9: =Воронка!K29 -> 21050.155 | C9: =Воронка!R29 -> 23938.859 | D9: =Воронка!X29 -> 23938.859 | E9: =Воронка!AN29 -> 25405.252 | G9: 23361.309
A10: Расходы | B10: =Воронка!K35 -> 17262.317 | C10: =Воронка!R35 -> 10578.662 | D10: =Воронка!X35 -> 5332.7497 | E10: =Воронка!AN35 -> 7800.7337 | G10: 12200.561
A11: CAC (sales, внешн. маркетинг Т, триал) | B11: =Воронка!K36 -> 14406.632 | C11: =Воронка!R36 -> 9619.0183 | D11: =Воронка!X36 -> 3940.4519 | E11: =Воронка!AN36 -> 6400.8544 | G11: 11189.751 | I11: Внешний маркетинг 3 млн на страте (опсевый, каналы). Триал 14 дней
A12: API маркетплейсов | B12: =Воронка!K40 -> 1255.6854 | C12: =Воронка!R40 -> 1348.2703 | D12: =Воронка!X40 -> 1392.2978 | E12: =Воронка!AN40 -> 1399.8793 | G12: 1399.4357 | I12: API маркетплейсов – бесплатный и платный Селлер (для бесплатных и платных пользователей), платный МПС
A13: Продление и удержание | B13: =Воронка!K41 -> 1600 | C13: =Воронка!R41 -> 0 | D13: =Воронка!X41 -> 0 | E13: =Воронка!AN41 -> 0 | I13: Гипотеза 2 - API - 1430 (больше чем в гипотезе 1), тк LT больше
A14: Доходы и расходы: Тарифы MPStats
A15: Доходы | B15: =Воронка!K44 -> 84617091 | C15: =Воронка!R44 -> 1.4127074e+08 | D15: =Воронка!X44 -> 24582770 | E15: =Воронка!AN44 -> 42363677
A16: Расходы | B16: =Воронка!K50 -> 65950688 | C16: =Воронка!R50 -> 62428015 | D16: =Воронка!X50 -> 5476190.6 | E16: =Воронка!AN50 -> 13007853
A17: Потенциальная прибыль
A18: Тарифы MPStats Доходы - Расходы (привлечение, API, продление и удержание) | B18: =Воронка!K75 -> 18666403 | C18: =Воронка!R75 -> 78842728 | D18: =Воронка!X75 -> 19106579 | E18: =Воронка!AN75 -> 29355825 | I18: Каналы #2 Sales MPS (биллинг MPS) и #3 Digital (биллинг Т) – соизмеримы
A19: Продукты Т-Банк (влияние MPStats) NVP от всех продуктов Т-Банк | B19: =Воронка!K77 -> 54520000 | C19: =Воронка!R77 -> 1.1041509e+08 | D19: =Воронка!X77 -> 73252979 | E19: =Воронка!AN77 -> 78121059 | I19: Канал Digital + Sales MPS – потенциально выгодный, нужно добавлять сегменты <1 млн и тестировать
A20: Всего | B20: =Воронка!K79 -> 73186403 | C20: =Воронка!R79 -> 1.8925782e+08 | D20: =Воронка!X79 -> 92359558 | E20: =Воронка!AN79 -> 1.0747688e+08 | H20: =(C20-B20)/B20 -> 1.5859697 | I20: Совокупный доход с билингом Т (#1 vs #2) выше в 2 раза за счет: рекурентых платежей - CR в покупку выше x1,5, досписания (грейс период) + 0.7 мес к LT, а также потенциал ковенант
I21: Каналы Sales MPS (биллинг Т) – наиболее выгодный
A49: Гипотеза v3 _ CR лиды upd - 50% + API скоррект
B50: 1. Sales MPS – Биллинг MPS | C50: 2. Sales MPS – Биллинг Т | D50: 3.Digital – Биллинг Т | E50: 4. Digital + Sales MPS (>1 млн) – Биллинг Т
A51: Воронка
A52: Лиды | B52: 58762.5 | C52: 58762.5 | D52: 58762.5 | E52: 58762.5
A53: Оплаты тарифов | B53: 4019.7846 | C53: 5901.3147 | D53: 1026.8981 | E53: 1667.5165
A54: CR в оплату (от всех лидов) | B54: 0.068407311 | C54: 0.10042654 | D54: 0.017475399 | E54: 0.028377223
A55: CR - точка безубыточности | B55: 0.0122 | C55: 0.0097 | D55: 0.0025 | E55: 0,26% / 0,57%
A56: Доходы и расходы на 1 платящего клиента
A57: LTV | B57: 21050.155 | C57: 23938.859 | D57: 23938.859 | E57: 25405.252
A58: Расходы | B58: 17335.232 | C58: 10487.828 | D58: 5332.7497 | E58: 7800.7337
A59: CAC (sales, внешн. маркетинг Т, триал) | B59: 14406.632 | C59: 9619.0183 | D59: 3940.4519 | E59: 6400.8544
A60: API маркетплейсов | B60: 1328.5998 | C60: 1257.4359 | D60: 1392.2978 | E60: 1399.8793
A61: Продление и удержание | B61: 1600 | C61: 0 | D61: 0 | E61: 0
A62: Доходы и расходы: Тарифы MPStats
A63: Доходы | B63: 84617091 | C63: 1.4127074e+08 | D63: 24582770 | E63: 42363677
A64: Расходы | B64: 66243788 | C64: 61891973 | D64: 5476190.6 | E64: 13007853
A65: Потенциальная прибыль
A66: Тарифы MPStats Доходы - Расходы (привлечение, API, продление и удержание) | B66: 18373303 | C66: 79378770 | D66: 19106579 | E66: 29355825
A67: Продукты Т-Банк (влияние MPStats) NVP от всех продуктов Т-Банк | B67: 54520000 | C67: 1.1041509e+08 | D67: 73252979 | E67: 78121059
A68: Всего | B68: 72893303 | C68: 1.8979386e+08 | D68: 92359558 | E68: 1.0747688e+08
C69: =(C66-B66)/B66 -> 3.320332 | E69: =(E66-D66)/D66 -> 0.53642495 | G69: =C67/B67 -> 2.0252218
A70: РАЗНИЦА с исх | C70: =(C68-B68)/B68 -> 1.6037215 | E70: =(E68-D68)/D68 -> 0.16367907 | G70: =C68/B68 -> 2.6037215
A71: Доходы и расходы: Тарифы MPStats
A72: Доходы | B72: =B63-B147 -> -50770255 | C72: =C63-C147 -> -84762446 | D72: =D63-D147 -> -14749662 | E72: =E63-E147 -> -25418206
A73: Расходы | B73: =B64-B148 -> -37705600 | C73: =C64-C148 -> -36968151 | D73: =D64-D148 -> -1992162.4 | E73: =E64-E148 -> -6681257.7
A74: Потенциальная прибыль | B74: =B65-B149 -> 0 | C74: =C65-C149 -> 0 | D74: =D65-D149 -> 0 | E74: =E65-E149 -> 0
A75: Тарифы MPStats Доходы - Расходы (привлечение, API, продление и удержание) | B75: =B66-B150 -> -13064655 | C75: =C66-C150 -> -47794295 | D75: =D66-D150 -> -12757499 | E75: =E66-E150 -> -18736949
A76: Продукты Т-Банк (влияние MPStats) NVP от всех продуктов Т-Банк | B76: =B67-B151 -> 0 | C76: =C67-C151 -> -26994654 | D76: =D67-D151 -> -4697387.2 | E76: =E67-E151 -> -7618235.7
A77: Всего | B77: =B68-B152 -> -13064655 | C77: =C68-C152 -> -74788949 | D77: =D68-D152 -> -17454887 | E77: =E68-E152 -> -26355184
A79: Доходы и расходы: Тарифы MPStats | B79: =B72/B147 -> -0.375 | C79: =C72/C147 -> -0.375 | D79: =D72/D147 -> -0.375 | E79: =E72/E147 -> -0.375
A80: Доходы | B80: =B73/B148 -> -0.36273037 | C80: =C73/C148 -> -0.37394401 | D80: =D73/D148 -> -0.26674722 | E80: =E73/E148 -> -0.33933772
A81: Расходы | B81: =B74/B149 -> #DIV/0! | C81: =C74/C149 -> #DIV/0! | D81: =D74/D149 -> #DIV/0! | E81: =E74/E149 -> #DIV/0!
A82: Потенциальная прибыль | B82: =B75/B150 -> -0.41556944 | C82: =C75/C150 -> -0.37582089 | D82: =D75/D150 -> -0.40037246 | E82: =E75/E150 -> -0.38960009
A83: Тарифы MPStats Доходы - Расходы (привлечение, API, продление и удержание) | B83: =B76/B151 -> 0 | C83: =C76/C151 -> -0.19645371 | D83: =D76/D151 -> -0.060261259 | E83: =E76/E151 -> -0.088853491
A84: Продукты Т-Банк (влияние MPStats) NVP от всех продуктов Т-Банк | B84: =B77/B152 -> -0.15198889 | C84: =C77/C152 -> -0.28266745 | D84: =D77/D152 -> -0.15894891 | E84: =E77/E152 -> -0.19692727
A85: Всего | B85: =B78/B153 -> #DIV/0! | C85: =C78/C153 -> 0 | D85: =D78/D153 -> #DIV/0! | E85: =E78/E153 -> 0
A89: Гипотеза v3 _ CR лиды upd - 50%
B90: 1. Sales MPS – Биллинг MPS | C90: 2. Sales MPS – Биллинг Т | D90: 3.Digital – Биллинг Т | E90: 4. Digital + Sales MPS (>1 млн) – Биллинг Т
A91: Воронка
A92: Лиды | B92: 58762.5 | C92: 58762.5 | D92: 58762.5 | E92: 58762.5
A93: Оплаты тарифов | B93: 4019.7846 | C93: 5901.3147 | D93: 1026.8981 | E93: 1667.5165
A94: CR в оплату (от всех лидов) | B94: 0.068407311 | C94: 0.10042654 | D94: 0.017475399 | E94: 0.028377223
A95: CR - точка безубыточности | B95: 0.0122 | C95: 0.0097 | D95: 0.0025 | E95: 0,26% / 0,57%
A96: Доходы и расходы на 1 платящего клиента
A97: LTV | B97: 21050.155 | C97: 23938.859 | D97: 23938.859 | E97: 25405.252
A98: Расходы | B98: 17339.655 | C98: 10689.276 | D98: 5804.7848 | E98: 8155.1789
A99: CAC (sales, внешн. маркетинг Т, триал) | B99: 14406.632 | C99: 9619.0183 | D99: 3940.4519 | E99: 6400.8544
A100: API маркетплейсов | B100: 1333.0233 | C100: 1458.8836 | D100: 1864.3329 | E100: 1754.3245
A101: Продление и удержание | B101: 1600 | C101: 0 | D101: 0 | E101: 0
A102: Доходы и расходы: Тарифы MPStats
A103: Доходы | B103: 84617091 | C103: 1.4127074e+08 | D103: 24582770 | E103: 42363677
A104: Расходы | B104: 66261570 | C104: 63080779 | D104: 5960922.6 | E104: 13598896
A105: Потенциальная прибыль
A106: Тарифы MPStats Доходы - Расходы (привлечение, API, продление и удержание) | B106: 18355522 | C106: 78189963 | D106: 18621847 | E106: 28764782
A107: Продукты Т-Банк (влияние MPStats) NVP от всех продуктов Т-Банк | B107: 54520000 | C107: 1.1041509e+08 | D107: 73252979 | E107: 78121059
A108: Всего | B108: 72875522 | C108: 1.8860505e+08 | D108: 91874826 | E108: 1.0688584e+08
A110: РАЗНИЦА с нов версией CR лиды upd - 50% + API скоррект
A111: Доходы и расходы: Тарифы MPStats
A112: Доходы | B112: =B103-B63 -> 0 | C112: =C103-C63 -> 0 | D112: =D103-D63 -> 0 | E112: =E103-E63 -> 0
A113: Расходы | B113: =B104-B64 -> 17781.519 | C113: =C104-C64 -> 1188806.5 | D113: =D104-D64 -> 484731.96 | E113: =E104-E64 -> 591043.29
A114: Потенциальная прибыль | B114: =B105-B65 -> 0 | C114: =C105-C65 -> 0 | D114: =D105-D65 -> 0 | E114: =E105-E65 -> 0
A115: Тарифы MPStats Доходы - Расходы (привлечение, API, продление и удержание) | B115: =B106-B66 -> -17781.519 | C115: =C106-C66 -> -1188806.5 | D115: =D106-D66 -> -484731.96 | E115: =E106-E66 -> -591043.29
A116: Продукты Т-Банк (влияние MPStats) NVP от всех продуктов Т-Банк | B116: =B107-B67 -> 0 | C116: =C107-C67 -> 0 | D116: =D107-D67 -> 0 | E116: =E107-E67 -> 0
A117: Всего | B117: =B108-B68 -> -17781.519 | C117: =C108-C68 -> -1188806.5 | D117: =D108-D68 -> -484731.96 | E117: =E108-E68 -> -591043.29
A120: Доходы и расходы: Тарифы MPStats
A121: Доходы | B121: =B112/B103 -> 0 | C121: =C112/C103 -> 0 | D121: =D112/D103 -> 0 | E121: =E112/E103 -> 0
A122: Расходы | B122: =B113/B104 -> 0.00026835342 | C122: =C113/C104 -> 0.01884578 | D122: =D113/D104 -> 0.081318279 | E122: =E113/E104 -> 0.043462594
A123: Потенциальная прибыль | B123: =B114/B105 -> #DIV/0! | C123: =C114/C105 -> #DIV/0! | D123: =D114/D105 -> #DIV/0! | E123: =E114/E105 -> #DIV/0!
A124: Тарифы MPStats Доходы - Расходы (привлечение, API, продление и удержание) | B124: =B115/B106 -> -0.00096872861 | C124: =C115/C106 -> -0.01520408 | D124: =D115/D106 -> -0.026030284 | E124: =E115/E106 -> -0.020547463
A125: Продукты Т-Банк (влияние MPStats) NVP от всех продуктов Т-Банк | B125: =B116/B107 -> 0 | C125: =C116/C107 -> 0 | D125: =D116/D107 -> 0 | E125: =E116/E107 -> 0
A126: Всего | B126: =B117/B108 -> -0.00024399851 | C126: =C117/C108 -> -0.0063031528 | D126: =D117/D108 -> -0.0052760041 | E126: =E117/E108 -> -0.0055296687
A132: Гипотеза v3 03.07.2026
B134: 1. Sales MPS – Биллинг MPS | C134: 2. Sales MPS – Биллинг Т | D134: 3.Digital – Биллинг Т | E134: 4. Digital + Sales MPS (>1 млн) – Биллинг Т
A135: Воронка
A136: Лиды | B136: 94020 | C136: 94020 | D136: 94020 | E136: 94020
A137: Оплаты тарифов | B137: 6431.6554 | C137: 9442.1035 | D137: 1643.037 | E137: 2668.0265
A138: CR в оплату (от всех лидов) | B138: 0.068407311 | C138: 0.10042654 | D138: 0.017475399 | E138: 0.028377223
A139: CR - точка безубыточности | B139: 0.0122 | C139: 0.0097 | D139: 0.0025 | E139: 0,26% / 0,57%
A140: Доходы и расходы на 1 платящего клиента
...

Sheet расходы для PnL
A1: Расход | B1: Биллинг Т + Sales Mpstast | C1: Биллинг MPS (если рекуррекнты и ковенанты будут доработаны) + Sales Mpstast | D1: Учтено в PnL | E1: Учтено в воронке +PnL (не все расходы)
A2: 1. Расходы на привлечение Т-Банк | B2: =SUM(B3:B5) -> 7046442.6 | C2: =SUM(C3:C5) -> 7046442.6
A3: Расходы на внутренний маркетинг (запуск 6 кампаний) | B3: 4500000 | C3: 4500000 | D3: да | E3: нет
A4: Расходы на внешний маркетинг (медиа, тг) | B4: 1500000 | C4: 1500000 | D4: да | E4: да
A5: Расходы на API запросы к маркетплейсам на время триал (бесплатная версия полного продуката MPStats на 14 дней) | B5: =Воронка!R53 -> 1046442.6 | C5: =B5 -> 1046442.6 | D5: да | E5: да
A6: 2. Расходы на биллинг Т-Банк | B6: =SUM(B7:B9) -> 3072857.1 | C6: =SUM(C7:C9) -> 500000
A7: Разработка Биллинга от Т-Банк | B7: 1800000 | C7: 500000 | D7: да | E7: нет
A8: Бухгалтерское сопровождение биллинга | D8: нет | E8: нет
A9: Техподдержка биллинг | B9: 1272857.1 | C9: 0 | D9: да | E9: нет
A10: 3. Техподдержка Т-банк интеграции | B10: 1272857.1 | C10: 1272857.1 | D10: да | E10: нет
A11: 4. Расходы на запросы к API Т-Банк | B11: =Воронка!R55 -> 7956567.1 | C11: =B11 -> 7956567.1 | D11: да | E11: да
A13: Расходы MPStats
A14: Sales команда МПСтатс | B14: =Воронка!R52 -> 50425005 | C14: =B14 -> 50425005
A15: Техподдержка интеграции МПСтатс | B15: 360000 | C15: 360000
A16: Техподдержка пользователей МПСтатс | B16: 8352000 | C16: 4176000

Sheet период вознаграждения
A1: Сегмент | B1: Кол-во платящих клиентов | C1: Доходы: Тарифы MPStats (за все время - условно 1 год) | D1: Доля сегмента в доходе | E1: LT в мес | F1: Доход в мес as is (все время ~12 мес) | G1: Доходы: Тарифы MPStats - за ограниченное кол-во мес | H1: кол-во мес | I1: Доходы: Тарифы MPStats - за ограниченное кол-во мес | J1: кол-во мес | K1: Доходы: Тарифы MPStats - за ограниченное кол-во мес | L1: кол-во мес | M1: Доходы: Тарифы MPStats - за ограниченное кол-во мес | N1: кол-во мес | O1: v1 Доходы: Тарифы MPStats - за ограниченное кол-во мес | P1: кол-во мес в первой оплате | Q1: Доходы: Тарифы MPStats - Бизнес | R1: Доходы: Тарифы MPStats - за ограниченное кол-во мес - Ср чек | S1: Доходы: Тарифы MPStats - за ограниченное кол-во мес - медианный чек | T1: v2 Доходы: Тарифы MPStats - за ограниченное кол-во мес - Ср чек /2 (скидка 50%)
A2: >100 млн | B2: 3.5169969 | C2: 208115.99 | D2: 0.0014731712 | E2: 10.866667 | F2: =C2/B2/E2 -> 5445.4918 | G2: =F2*B2*H2 -> 114910.67 | H2: 6 | I2: =B2*J2*F2 -> 19151.778 | J2: 1 | K2: =B2*F2*L2 -> 38303.556 | L2: 2 | M2: =B2*F2*N2 -> 57455.334 | N2: 3 | O2: =B2*F2*P2 -> 85924.193 | P2: =W39 -> 4.4864865 | Q2: =B2*P2*X39 -> 198550.35 | R2: =B2*W15 -> 192440.09 | S2: =B2*X15 -> 105474.74 | T2: =R2/2 -> 96220.045
A3: 10-100 млн | B3: 67.44051 | C3: 2575107.6 | D3: 0.018228174 | E3: 8.4666667 | F3: =C3/B3/E3 -> 4509.8498 | G3: =F3*B3*H3 -> 1824879.4 | H3: 6 | I3: =B3*J3*F3 -> 304146.57 | J3: 1 | K3: =B3*F3*L3 -> 608293.14 | L3: 2 | M3: =B3*F3*N3 -> 912439.7 | N3: 3 | O3: =B3*F3*P3 -> 1364549.5 | P3: =W40 -> 4.4864865 | Q3: =B3*P3*X40 -> 3807321.2 | R3: =B3*W16 -> 3690153.3 | S3: =B3*X16 -> 2022540.9 | T3: =R3/2 -> 1845076.6
A4: 1-10 млн | B4: 704.62064 | C4: 18743605 | D4: 0.13267861 | E4: 6.4666667 | F4: =C4/B4/E4 -> 4113.5549 | G4: =F4*B4*H4 -> 17390974 | H4: 6 | I4: =B4*J4*F4 -> 2898495.7 | J4: 1 | K4: =B4*F4*L4 -> 5796991.4 | L4: 2 | M4: =B4*F4*N4 -> 8695487 | N4: 3 | O4: =B4*F4*P4 -> 10627817 | P4: =W41 -> 3.6666667 | Q4: =B4*P4*X41 -> 33684044 | R4: =B4*W17 -> 23437679 | S4: =B4*X17 -> 10562968 | T4: =R4/2 -> 11718839
A5: менее 1 млн | B5: 5125.7365 | C5: 1.1974391e+08 | D5: 0.84762005 | E5: 5.6666667 | F5: =C5/B5/E5 -> 4122.5839 | G5: =F5*B5*H5 -> 1.1974391e+08 | H5: =E5 -> 5.6666667 | I5: =B5*J5*F5 -> 21131279 | J5: 1 | K5: =B5*F5*L5 -> 42262558 | L5: 2 | M5: =B5*F5*N5 -> 63393837 | N5: 3 | O5: =B5*F5*P5 -> 66543841 | P5: =W42 -> 3.1490683 | Q5: =B5*P5*X42 -> 2.0973508e+08 | R5: =B5*W18 -> 1.4254011e+08 | S5: =B5*X18 -> 66583318 | T5: =R5/2 -> 71270055
A6: клиентский доход | B6: 5901.3147 | C6: 1.4127074e+08 | G6: =SUM(G2:G5) -> 1.3907468e+08 | I6: =SUM(I2:I5) -> 24353073 | K6: =SUM(K2:K5) -> 48706146 | M6: =SUM(M2:M5) -> 73059219 | O6: =SUM(O2:O5) -> 78622132 | Q6: =SUM(Q2:Q5) -> 2.47425e+08 | R6: =SUM(R2:R5) -> 1.6986038e+08 | S6: =SUM(S2:S5) -> 79274301 | T6: =SUM(T2:T5) -> 84930192
G7: =G6-C6 -> -2196064.8 | I7: =I6-C6 -> -1.1691767e+08 | K7: =K6-C6 -> -92564597 | M7: =M6-C6 -> -68211524 | O7: =O6-C6 -> -62648610 | R7: =R6/2 -> 84930192 | T7: =T6-C6 -> -56340551
G8: =G6/C6 -> 0.98445492 | I8: =I6/C6 -> 0.17238582 | K8: =K6/C6 -> 0.34477164 | M8: =M6/C6 -> 0.51715746 | O8: =O6/C6 -> 0.55653514 | T8: =T7/C6 -> -0.39881259
T11: Средняя сумма первой оплаты по сегментам оборота
T12: Данные реальные (pricefinal), без оценки через тарифы. Среднее чувствительно к выбросам — смотрите и медиану: это «типичный» чек, устойчивый к крупным разовым платежам.
T14: Сегмент | U14: Кол-во клиентов | V14: Сумма оплат, ₽ | W14: Средний чек, ₽ | X14: Медианный чек, ₽ | Y14: Мин, ₽ | Z14: Макс, ₽ | AA14: Доля клиентов
T15: >100 млн | U15: 37 | V15: 2024535 | W15: 54717.162 | X15: 29990 | Y15: 6492 | Z15: 152952 | AA15: 0.075356415
T16: 10-100 млн | U16: 37 | V16: 2024535 | W16: 54717.162 | X16: 29990 | Y16: 6492 | Z16: 152952 | AA16: 0.075356415
T17: 3_1-10 млн | U17: 102 | V17: 3392809 | W17: 33262.833 | X17: 14991 | Y17: 1000 | Z17: 143946 | AA17: 0.20773931
T18: 2_<1 млн | U18: 161 | V18: 4477202 | W18: 27808.708 | X18: 12990 | Y18: 6492 | Z18: 268732 | AA18: 0.32790224
T19: 1_неизвестно | U19: 191 | V19: 3752242 | W19: 19645.246 | X19: 12990 | Y19: 1 | Z19: 152952 | AA19: 0.38900204
T20: ИТОГО / в среднем | U20: 491 | V20: 13646788 | W20: 27793.866 | X20: 12990 | Y20: 1 | Z20: 268732 | AA20: 1
T22: Примечание: медианный чек и медианный срок — формулы массива (в старых версиях Excel вводятся через Ctrl+Shift+Enter). Значения уже посчитаны.
T26: LTV as is: MPStats ( май 25-апр 26)
T27: Сегмент по обороту | U27: LTV | W27: За 1 мес LT | Y27: LT гипотеза: тарифы MPStats | Z27: гипотеза: +1 мес к LT (за счет досписания с РКО на след мес при недостатке ДС)
T28: >100 млн | U28: 110725 | V28: =W15/U28 -> 0.49417171 | W28: >100 млн | X28: 10890.984 | Y28: >100 млн | Z28: 10.866667
T29: 10 + млн | U29: 70053 | V29: =W16/U29 -> 0.78108235 | W29: 10 + млн | X29: 9019.6996 | Y29: 10 + млн | Z29: 8.4666667
T30: 1-10 млн | U30: 47443 | V30: =W17/U30 -> 0.70111151 | W30: 1-10 млн | X30: 8227.1098 | Y30: 1-10 млн | Z30: 6.4666667
T31: менее 1 млн | U31: 40951 | V31: =W18/U31 -> 0.67907275 | W31: менее 1 млн | X31: 8245.1678 | Y31: менее 1 млн | Z31: 5.6666667
T32: без оборотов | U32: 33828 | V32: =W19/U32 -> 0.58073921 | W32: без оборотов | X32: 7866.9767 | Y32: без оборотов | Z32: 5
T33: связь с селлером не найдена | U33: 21581 | V33: =W20/U33 -> 1.2878859 | W33: связь с селлером не найдена | X33: 6674.5361 | Y33: связь с селлером не найдена | Z33: 3.9333333
Z34: 7.0333333
T37: Первые оплаты МПСтатс после обновления тарифов (в налаче июня)
T38: Категория доходов | U38: Кол-во пользователей | V38: Вклад | W38: Средний срок (мес.) | X38: Сумма за 1 мес (если тариф Бизнес)
T39: >100 млн | W39: =W40 -> 4.4864865 | X39: =X40 -> 12583.235
T40: 10-100 млн | U40: 37 | V40: 166 | W40: 4.4864865 | X40: 12583.235
T41: 1-10 млн | U41: 102 | V41: 374 | W41: 3.6666667 | X41: 13037.594
T42: менее 1 млн | U42: 161 | V42: 507 | W42: 3.1490683 | X42: 12993.696
T43: неизвестно | U43: 191 | V43: 408 | W43: 2.1361257 | X43: 13539.237

Sheet доп расходы_свод
A1: Что удалось собрать из того что обсуждали
A2: 1. Расходы на внутренний маркетинг 4,5 в год/всего
A3: 2. Расходы на внешний маркетинг 1,5-3 млн в год/всего
A5: 3. Тех поддержка интеграции в целом от Т-Банка:
A6: если биллинг Т - 750 k в мес, 9 млн в год
A7: если биллинг МСП - 376 k в мес, 4,5 млн в год
A9: 4. Разработка Биллинга от Т-Банк (разовый расход)
A10: если биллинг Т - 1,8 млн
A11: если биллинг Т, тарифы интерфейсно в МПС - 1,3 млн
A12: если биллинг МПС - 500k
A14: жду от МПСтатст сегодня
A15: 5. ожидаемое вознаграждение за лицензию на ПО - минимально возможное для налогов
A16: 6. ожидаемое вознаграждение за тех поддержку интеграции от МПС - жду от МПСтатст сегодня | C16: тех поддержка | D16: поддержка пользовтаелей
A17: если биллинг Т - 726k ежемесячно, 8 712 000 в год | B17: =726000*12 -> 8712000 | C17: =30000*12 -> 360000 | D17: =B17-C17 -> 8352000
A18: если биллинг МПС - 378k ежемесячно, 4 536 000 в год | B18: =378000*12 -> 4536000 | C18: =30000*12 -> 360000 | D18: =B18-C18 -> 4176000
A20: жду от Карины завтра утром
A21: расходы на бухгалтерскую поддержку (если биллинг Т)
A22: если не будет инфо - значит без этих расходов
A25: МПСтатс планируют реккуренты
A26: рекурренты с карт (ФЛ/ЮЛ) - август
A27: рекурренты с счета ЮЛ) - сентябрь
A28: грейс период 3 попыткив теч 3 дней - сентябрь
A30: ковенанты под вопросом
A34: Лицензия
A35: В расчет стоимости лицензии входят:
A36: - Балансовая стоимость всех версии Актива МПСТАТС ( за минусом амортизации) = 231 963 170 млн руб;
A37: - Доля выручки продуктов, которые окажутся в Виджете Т селлера ( Внешняя аналитика Озон \ Внешняя аналитика ВБ \ Кабинет ВБ \ Кабинет Озон) = 16%;
... A45: если хотим оставить ту же стоимость - то на клиента должно быть:
A46: =379.281362007168 -> 379.28136
A48: с учетом того что в Селлере будет доступно не все - предлагаю изменить долю выручки продуктов виджет ан а
A51: =231963170 -> 231963170
A52: 0.03
A54: =A51*A52 -> 6958895.1
A55: 9800
A56: =A54/A55 -> 710.09134
A57: 558 | B57: число платных Т
A58: =A56*A57 -> 396230.97 | B58: пердложение

Sheet ИТОГ_new v4
G1: Комментарии | H1: Что сделать
B2: Период расчета в модели: год | C2: Вариант 1 | E2: Вариант 2.1
C3: Биллинг Т | E3: Биллинг МПС (с рекуррентами и ковенантами)
A4: Доходы: Тарифы MPStats оплачены клиентами | B4: Клиентский доход (тарифы МПСтатс) - от всей базы селлеров (~12 мес) | C4: =Воронка!#REF! -> #REF! | E4: =Воронка!#REF! -> #REF!
B5: Клиентский доход (тарифы МПСтатс) - 6 мес | C5: ='период вознаграждения'!G6 -> 1.3907468e+08 | E5: =C5 -> 1.3907468e+08
B6: Клиентский доход (тарифы МПСтатс) - 3 мес | C6: ='период вознаграждения'!M6 -> 73059219 | E6: =C6 -> 73059219
B7: Клиентский доход (тарифы МПСтатс) - 1 мес | C7: ='период вознаграждения'!I6 -> 24353073 | E7: =C7 -> 24353073
B9: Расходы Т-Банк
B10: Договор 1 (лицензия + техподдержка ПО МПСтатс)
B11: услуги по договору | C11: лицензия + техподдержка | E11: лицензия + техподдержка
A12: Договор 1 (лицензия и тех поддержка со стороны МПСтатс) | B12: Лицензия на ПО MPStats (единоразово) | C12: 378000 | E12: =C12 -> 378000 | G12: Стоимость от МПСтатс - 378 000 руб. (скорее всего оценивали объем используемого функционала). Провалидировать с налогами.
A13: Лицензия на ПО MPStats -- какая минимально возможная? (единоразово бессрочно) | B13: Тех. поддержка ПО MPStats (в год) | C13: ='доп расходы_свод'!C17 -> 360000 | E13: =C13 -> 360000 | G13: по расчету МПС
A14: Тех. поддержка интеграции в целом от MPStats (в год) | B14: ИТОГО по Договору 1 | C14: =C12+C13 -> 738000 | E14: =E12+E13 -> 738000 | G14: Доход для МПС, расход для Т
B15: доля от клиентского дохода MPStats | C15: =C14/C$4 -> #REF! | E15: =E14/E$4 -> #REF!
B16: Договор 2 (биллинг + лидген)
B17: услуги по договору | C17: биллинг + техподдержка + лидогенерация Т | E17: лидогенерация + техподдержка Т
A18: Расходы на привлечение Т-Банк | B18: 1. Расходы на привлечение Т-Банк | C18: =SUM(C19:C21) -> #REF! | E18: =SUM(E19:E21) -> #REF!
A19: Расходы на внутренний маркетинг (запуск 6 кампаний) | B19: Расходы на внутренний маркетинг | C19: =Воронка!#REF! -> #REF! | E19: =Воронка!#REF! -> #REF! | G19: запуск 6 кампаний
A20: Расходы на внешний маркетинг (медиа, тг) | B20: Расходы на внешний маркетинг | C20: =Воронка!#REF! -> #REF! | E20: =Воронка!#REF! -> #REF! | G20: медиа, ТГ
A21: Расходы на API запросы к маркетплейсам на время триал (бесплатная версия полного продуката MPStats на 14 дней) | B21: Расходы на API запросы к маркетплейсам на время триал | C21: =Воронка!#REF! -> #REF! | E21: =Воронка!#REF! -> #REF! | G21: Т несет расходы в период пользования клиентами продуката MPStats - триал на 14 дней
A22: Расходы на биллинг Т-Банк | B22: 2. Расходы на биллинг Т-Банк | C22: =SUM(C23:C25) -> #REF! | E22: =SUM(E23:E25) -> #REF!
A23: Разработка Биллинга от Т-Банк | B23: Разработка Биллинга от Т-Банк | C23: =Воронка!#REF! -> #REF! | E23: =Воронка!#REF! -> #REF!
A24: Бухгалтерское сопровождение биллинга | B24: Бухгалтерское сопровождение биллинга | C24: =Воронка!#REF! -> #REF! | E24: =Воронка!#REF! -> #REF! | G24: нет данных для расчета
B25: Техподдержка биллинг | C25: =расходы_разработка!D50-расходы_разработка!E50 -> 1272857.1
A26: Тех. поддержка интеграции в целом от Т-Банк | B26: 3. Техподдержка Т-банк интеграции | C26: =расходы_разработка!D50-расходы_разработка!E50 -> 1272857.1 | E26: =расходы_разработка!E50 -> 1272857.1
A27: Расходы на запросы к API Т-Банк (необходимо для базовой работы сервиса) | B27: 4. Расходы на запросы к API Т-Банк | C27: =Воронка!#REF! -> #REF! | E27: =Воронка!#REF! -> #REF! | G27: необходимо для базовой работы сервиса
B28: ИТОГО расходы Т | C28: =SUM(C18,C22,C26,C27) -> #REF! | E28: =SUM(E18,E22,E26,E27) -> #REF!
B29: маржа поверх расходов | C29: 0.13 | E29: 0.13 | G29: 10% - мин.требование налогов Т для рыночности сделки
B31: Стоимость для договора 2 (калькуляция от затрат + маржа)
B32: Биллинг | C32: =C22*(1+C$29) -> #REF! | E32: 0 | G32: разработка+интеграция +маржа Т
B33: доля от клиентского дохода MPStats (бессрочно) | C33: =C32/C$4 -> #REF! | E33: =E32/E$4 -> #REF!
B34: Лидогенерация Т (вкл расходы техподдержка Т + API) | C34: =(C18+C26+C27)*(1+C$29) -> #REF! | E34: =(E18+E26+E27+E22)*(1+E$29) -> #REF! | G34: внешний/внутренний маркетинг Т + расходы на API/техподдержку +маржа 10%
B35: % от клиентского дохода (12 мес) | C35: =C$34/C4 -> #REF! | E35: =E$34/E4 -> #REF!
B36: % от клиентского дохода (6 мес) | C36: =C$34/C5 -> #REF! | E36: =E$34/E5 -> #REF!
B37: % от клиентского дохода (3 мес) | C37: =C$34/C6 -> #REF! | E37: =E$34/E6 -> #REF!
B38: % от клиентского дохода (1 мес) | C38: =C$34/C7 -> #REF! | E38: =E$34/E7 -> #REF!
B39: ИТОГО по Договору 2 (расчет 1: расходы Т+ маржа) | C39: =C32+C34 -> #REF! | E39: =E32+E34 -> #REF! | G39: Доход для Т, расход для МПС
B40: % от клиентского дохода (12 мес) | C40: =C39/C4 -> #REF! | E40: =E39/E4 -> #REF!
B42: Стоимость для договора 2 (калькуляция от клиентских доходов)
B43: Биллинг Т | C43: =C$4*C47 -> #REF! | E43: =E$4*E47 -> #REF!
B44: Лидогенерация Т | C44: =C$4*C48 -> #REF! | E44: =E$4*E48 -> #REF!
B45: ИТОГО по Договору 2 (расчет 2: флэт % от клиентского дохода) | C45: =C43+C44 -> #REF! | E45: =E43+E44 -> #REF! | G45: Доход для Т, расход для МПС
B46: Расчет от доли клиентского дохода MPStats | C46: =C45/C4 -> #REF! | E46: =E47+E48 -> #REF!
B47: % биллинг | C47: =C33 -> #REF! | E47: =E33 -> #REF!
B48: % лидген (вкл расходы: привлечение, техподдержка, запросы API) | C48: =C35 -> #REF! | E48: =E35 -> #REF!
G49: похожий договор Мпстаст - Партнер (получает 15-30%) - нужен актуальный договор!!
B50: P&L для сторон | C50: Биллинг Т | E50: Биллинг МПС (с рекуррентами и ковенантами) | H50: Выбор варианта расчета по Договору 2 | K50: 2 | L50: 1 - от расходов Т + маржа; 2 - от требуемой доходности Т
B51: МПСтатс
B52: Доходы | C52: =SUM(C53:C54) -> #REF! | E52: =SUM(E53:E54) -> #REF!
B53: Доход с клиентов (тарифы МПСтатс) | C53: =C4 -> #REF! | E53: =E4 -> #REF! | G53: без НДС (льгота для ИТ компаний)
B54: Договор 1 (лицензия + тех поддержка МПСтатс) | C54: =C14 -> 738000 | E54: =E14 -> 738000 | G54: лицензция – без НДС (льгота для ИТ компаний); тех поддержка – с НДС.
B56: Расходы | C56: =SUM(C57:C61) -> #REF! | E56: =SUM(E57:E61) -> #REF!
B57: Sales команда МПСтатс | C57: =Воронка!R52 -> 50425005 | E57: =Воронка!R52 -> 50425005
B58: Договор 2 (биллинг Т) | C58: =CHOOSE($K$50,C32,C43) -> #REF! | E58: =CHOOSE($K$50,E32,E43) -> #REF! | G58: НДС 22% к стоимости услуг по Дог.2. Т-Банк начисляет НДС, уплачивает его в бюджет. МПСтатс оплачивают счет от нас с учетом НДС и принимают к себе в зачет эту сумму
B59: Договор 2 (лидген Т) | C59: =CHOOSE($K$50,C34,C44) -> #REF! | E59: =CHOOSE($K$50,E34,E44) -> #REF!
B60: Техподдержка интеграции МПСтатс | C60: =C13 -> 360000 | E60: =E13 -> 360000
B61: Техподдержка пользователей МПСтатс | C61: ='доп расходы_свод'!D17 -> 8352000 | E61: ='доп расходы_свод'!D18 -> 4176000
B63: Прибыль МПС от МПСтатс (за вычетом всех расходов) | C63: =C52-C56 -> #REF! | E63: =E52-E56 -> #REF!
B64: маржинальность по проекту для МПС (прибыль/доходы) | C64: =C63/C52 -> #REF! | E64: =E63/E52 -> #REF!
B65: Прибыль МПС от клиентского дохода МПСтатс (за вычетом лидгена Т) | C65: =C53-C59 -> #REF! | E65: =E53-E59 -> #REF!
B66: доля от клиентского дохода MPStats | C66: =C65/C4 -> #REF! | E66: =E65/E4 -> #REF! | G66: Вознаграждение МПСтатс за вычетом комиссии Т-Банк за лидген+ биллинг/ только лидген. | H66: Открытый вопрос - получение вознаграждения за все время пока платит клиент или ограниченное время? У Точки (пример договора) - комиссия партнера за все время оплаты клиентом (без ограничений). В Т обычно 3-6 мес - за лидген. Иначе если без ограничений - нужно согласовывать налоговые риски - если услуга за все время оплаты. Если билиинг на стороне Т - то нужно получать оплату постоянно (можо выделить услугу биллинга - фикс или %)
B68: Справочно: налоги МПС
B69: НДС 22% – тех поддержка по Договору 1 | C69: =C13*22% -> 79200 | E69: =E13*22% -> 79200 | G69: валидация от МПС | H69: нужно валидировать с налоговиками?
B70: Налог на прибыль 5% (льгота для ИТ компаний) | C70: =C63*5% -> #REF! | E70: =E63*5% -> #REF! | G70: валидация от МПС
B71: Разница налог на прибыль | C71: =C70-E70 -> #REF!
B73: Т-Банк
B74: Доходы | C74: =SUM(C75:C77) -> #REF! | E74: =SUM(E75:E77) -> #REF!
B75: Доход с клиентов (тарифы МПСтатс)
B76: Договор 2 (биллинг Т) | C76: =C58 -> #REF! | E76: =E58 -> #REF! | G76: НДС 22% к стоимости услуг по Дог.2. Т-Банк начисляет НДС, уплачивает его в бюджет. МПСтатс оплачивают счет от нас с учетом НДС и принимают к себе в зачет эту сумму
B77: Договор 2 (лидген Т) | C77: =C59 -> #REF! | E77: =E59 -> #REF!
B79: Расходы | C79: =SUM(C80:C82) -> #REF! | E79: =SUM(E80:E82) -> #REF!
B80: Договор 1 (лицензия + тех поддержка МПСтатс) | C80: =C54 -> 738000 | E80: =E54 -> 738000
B81: Договор 2 (биллинг Т) | C81: =C22 -> #REF! | E81: 0
B82: Договор 2 (лидген Т + тех поддержка + API) | C82: =C18+C26+C27 -> #REF! | E82: =E18+E26+E27+E22 -> #REF!
B84: Прибыль Т от МПСтатс | C84: =C74-C79 -> #REF! | E84: =E74-E79 -> #REF!
B85: маржинальность по проекту для Т (прибыль/доходы) | C85: =C84/C74 -> #REF! | E85: =E84/E74 -> #REF!
B86: доля от клиентского дохода MPStats | C86: =C84/C$4 -> #REF! | E86: =E84/E$4 -> #REF!
B87: маржинальность как доля прибыли Т к расходам (от налоговиков) | C87: =C84/C79 -> #REF! | E87: =E84/E79 -> #REF! | G87: 10% - мин.требование налогов Т для рыночности сделки
B89: Потенциальная прибыль Т по другим продуктам | C89: =Воронка!#REF! -> #REF! | E89: =Воронка!#REF! -> #REF!
B90: Общая прибыль Т (MPStats + экосистемный эффект) | C90: =C84+C89 -> #REF! | E90: =E84+E89 -> #REF!
B92: Справочно: налоги Т-Банк | G92: получить подтвержение от налогов Т что рассчитано верно | H92: нужно валидировать с налоговиками?
B93: НДС 22% (в доходах по Договору 2) | C93: =(C76+C77)*22% -> #REF! | E93: =(E76+E77)*22% -> #REF! | G93: НДС 22% к стоимости услуг по Дог.2. Т-Банк начисляет НДС, уплачивает его в бюджет. МПСтатс оплачивают счет от нас с учетом НДС и НЕ принимают к себе в зачет эту сумму (инфо от МПС что не смогут в зачет). ?? Уточнить с налогами последствия по НДС для МПС (большую часть выручки не облагают НДС => не смогут принять к вычету НДС по договору с Т?)
B94: Налог на прибыль 25% | C94: =C84*25% -> #REF! | E94: =E84*25% -> #REF!
B95: Разница налог на прибыль | C95: =C94-E94 -> #REF!
B97: P&L Total | C97: Биллинг Т | E97: Биллинг МПС (с рекуррентами и ковенантами)
B98: ИТОГО: МПС + Т-Банк
B99: Доходы | C99: =C100+C103 -> #REF! | E99: =E100+E103 -> #REF!
B100: МПС | C100: =SUM(C101:C102) -> #REF! | E100: =SUM(E101:E102) -> #REF!
B101: Доход с клиентов (тарифы МПСтатс) | C101: =C53 -> #REF! | E101: =E53 -> #REF! | G101: доход МПС
B102: Договор 1 (лицензия + тех поддержка МПСтатс) | C102: =C54 -> 738000 | E102: =E54 -> 738000 | G102: доход МПС, расход Т. 1) Стоимость лиценции уточняется.
B103: Т-Банк | C103: =C104+C105 -> #REF! | E103: =E104+E105 -> #REF!
B104: Договор 2 (биллинг Т) | C104: =C58 -> #REF! | E104: =E58 -> #REF! | G104: доход Т-Банк, расход МПС
B105: Договор 2 (лидген Т) | C105: =C59 -> #REF! | E105: =E59 -> #REF!
B107: Расходы | C107: =C108+C114 -> #REF! | E107: =E108+E114 -> #REF!
B108: МПС | C108: =SUM(C109:C113) -> #REF! | E108: =SUM(E109:E113) -> #REF!
B109: =B57 -> Sales команда МПСтатс | C109: =C57 -> 50425005 | E109: =E57 -> 50425005
B110: Договор 2 (биллинг Т) | C110: =C58 -> #REF! | E110: =E58 -> #REF! | G110: оплата Т за биллинг
B111: Договор 2 (лидген Т) | C111: =C59 -> #REF! | E111: =E59 -> #REF! | G111: оплата Т за лидген
B112: Техподдержка интеграции МПСтатс | C112: =C60 -> 360000 | E112: =E60 -> 360000
B113: Техподдержка пользователей МПСтатс | C113: =C61 -> 8352000 | E113: =E61 -> 4176000
...

Sheet ИТОГ_new v2_в презе
H1: Комментарии | I1: Что сделать
B2: Использовано в презентации | C2: Вариант 1 | E2: Вариант 2.1 | G2: Вариант 2.2
C3: Биллинг Т | E3: Биллинг МПС (с рекуррентами и ковенантами) | G3: Биллинг МПС (без рекуррентов и ковенантов)
A4: Доходы: Тарифы MPStats оплачены клиентами | B4: Клиентский доход (тарифы МПСтатс) | C4: =[1]Гипотезы_акт!T103 -> 1.4127074e+08 | E4: =[1]Гипотезы_акт!F103 -> 1.4127074e+08 | G4: =[1]Гипотезы_акт!M103 -> 84617091
B6: Расходы Т-Банк
B7: Договор 1 (лицензия + техподдержка ПО МПСтатс)
B8: услуги по договору | C8: лицензия + техподдержка | E8: лицензия + техподдержка | G8: лицензия + техподдержка
A9: Договор 1 (лицензия и тех поддержка со стороны МПСтатс) | B9: Лицензия на ПО MPStats (единоразово) | C9: 100000 | E9: =C9 -> 100000 | G9: =[1]Гипотезы_акт!M87 -> 100000 | H9: Заложили минимально 100 000 р, можем увеличить - провалидировать (налоги). Необходимо обоснование.
A10: Лицензия на ПО MPStats -- какая минимально возможная? (единоразово бессрочно) | B10: Тех. поддержка ПО MPStats (в год) | C10: ='[1]доп расходы_свод'!C17 -> 360000 | E10: =C10 -> 360000 | G10: =E10 -> 360000 | H10: по расчету МПС
A11: Тех. поддержка интеграции в целом от MPStats (в год) | B11: ИТОГО по Договору 1 | C11: =C9+C10 -> 460000 | E11: =E9+E10 -> 460000 | G11: =G9+G10 -> 460000 | H11: Доход для МПС, расход для Т
B12: доля от клиентского дохода MPStats | C12: =C11/C$4 -> 0.003256159 | E12: =E11/E$4 -> 0.003256159 | G12: =G11/G$4 -> 0.005436254
B13: Договор 2 (биллинг + лидген)
B14: услуги по договору | C14: биллинг + техподдержка + лидогенерация Т | E14: лидогенерация + техподдержка Т | G14: лидогенерация + техподдержка Т
A15: Расходы на привлечение Т-Банк | B15: 1. Расходы на привлечение Т-Банк | C15: =SUM(C16:C18) -> 7046442.6 | E15: =SUM(E16:E18) -> 7046442.6 | G15: =SUM(G16:G18) -> 7046442.6
A16: Расходы на внутренний маркетинг (запуск 6 кампаний) | B16: Расходы на внутренний маркетинг | C16: =[1]Гипотезы_акт!T92 -> 4500000 | E16: =[1]Гипотезы_акт!F92 -> 4500000 | G16: =[1]Гипотезы_акт!M92 -> 4500000 | H16: запуск 6 кампаний
A17: Расходы на внешний маркетинг (медиа, тг) | B17: Расходы на внешний маркетинг | C17: =[1]Гипотезы_акт!T93 -> 1500000 | E17: =[1]Гипотезы_акт!F93 -> 1500000 | G17: =[1]Гипотезы_акт!M93 -> 1500000 | H17: медиа, ТГ
A18: Расходы на API запросы к маркетплейсам на время триал (бесплатная версия полного продуката MPStats на 14 дней) | B18: Расходы на API запросы к маркетплейсам на время триал | C18: =[1]Гипотезы_акт!T94 -> 1046442.6 | E18: =[1]Гипотезы_акт!F94 -> 1046442.6 | G18: =[1]Гипотезы_акт!M94 -> 1046442.6 | H18: Т несет расходы в период пользования клиентами продуката MPStats - триал на 14 дней
A19: Расходы на биллинг Т-Банк | B19: 2. Расходы на биллинг Т-Банк | C19: =SUM(C20:C22) -> 3072857.1 | E19: =SUM(E20:E22) -> 500000 | G19: =SUM(G20:G22) -> 500000
A20: Разработка Биллинга от Т-Банк | B20: Разработка Биллинга от Т-Банк | C20: =[1]Гипотезы_акт!T96 -> 1800000 | E20: =[1]Гипотезы_акт!F96 -> 500000 | G20: =[1]Гипотезы_акт!M96 -> 500000
A21: Бухгалтерское сопровождение биллинга | B21: Бухгалтерское сопровождение биллинга | C21: =[1]Гипотезы_акт!T97 -> 0 | E21: =[1]Гипотезы_акт!F97 -> 0 | G21: =[1]Гипотезы_акт!M97 -> 0 | H21: нет данных для расчета
B22: Техподдержка биллинг | C22: =[1]расходы_разработка!D50-[1]расходы_разработка!E50 -> 1272857.1
A23: Тех. поддержка интеграции в целом от Т-Банк | B23: 3. Техподдержка Т-банк интеграции | C23: =[1]расходы_разработка!D50-[1]расходы_разработка!E50 -> 1272857.1 | E23: =[1]расходы_разработка!E50 -> 1272857.1 | G23: =[1]Гипотезы_акт!M98 -> 4512000
A24: Расходы на запросы к API Т-Банк (необходимо для базовой работы сервиса) | B24: 4. Расходы на запросы к API Т-Банк | C24: =[1]Гипотезы_акт!T99 -> 7956567.1 | E24: =[1]Гипотезы_акт!F99 -> 7956567.1 | G24: =[1]Гипотезы_акт!M99 -> 5047584.8 | H24: необходимо для базовой работы сервиса
B25: ИТОГО расходы Т | C25: =SUM(C15,C19,C23,C24) -> 19348724 | E25: =SUM(E15,E19,E23,E24) -> 16775867 | G25: =SUM(G15,G19,G23,G24) -> 17106027
B26: маржа поверх расходов | C26: 0.1 | E26: =C26 -> 0.1 | G26: =C26 -> 0.1 | H26: 10% слишком мало для покрытия всех расходов по проекту
B28: ИТОГО по Договору 2 (расчет 1: расходы Т+ маржа) | C28: =C25*(1+C26) -> 21283596 | E28: =E25*(1+E26) -> 18453454 | G28: =G25*(1+G26) -> 18816630 | H28: Доход для Т, расход для МПС
B29: доля от клиентского дохода MPStats (если маржа 10%) | C29: =C28/C$4 -> 0.1506582 | E29: =E28/E$4 -> 0.13062474 | G29: =G28/G$4 -> 0.22237387
B31: ИТОГО по Договору 2 (расчет 2: флэт % от клиентского дохода) | C31: =C4*C32 -> 35317686 | E31: =E4*E32 -> 28254149 | G31: =G4*G32 -> 16923418 | H31: Доход для Т, расход для МПС
B32: альтернатива для договора - доля от клиентского дохода MPStats | C32: 0.25 | E32: 0.2 | G32: 0.2 | H32: провалидировать (налоги) - ОК
H33: похожий договор Мпстаст - Партнер (получает 15-30%)
B34: P&L для сторон | C34: =C3 -> Биллинг Т | E34: =E3 -> Биллинг МПС (с рекуррентами и ковенантами) | G34: =G3 -> Биллинг МПС (без рекуррентов и ковенантов) | I34: Выбор варианта расчета по Договору 2 | L34: 2 | M34: 1 - от расходов Т + маржа; 2 - от требуемой доходности Т
B35: МПСтатс
B36: Доходы | C36: =SUM(C37:C38) -> 1.4173074e+08 | E36: =SUM(E37:E38) -> 1.4173074e+08 | G36: =SUM(G37:G38) -> 85077091
B37: Доход с клиентов (тарифы МПСтатс) | C37: =C4 -> 1.4127074e+08 | E37: =E4 -> 1.4127074e+08 | G37: =G4 -> 84617091 | H37: без НДС (льгота для ИТ компаний)
B38: Договор 1 (лицензия + тех поддержка МПСтатс) | C38: =C11 -> 460000 | E38: =E11 -> 460000 | G38: =G11 -> 460000 | H38: лицензция – без НДС (льгота для ИТ компаний); тех поддержка – с НДС.
B40: Расходы | C40: =SUM(C41:C44) -> 94454691 | E40: =SUM(E41:E44) -> 83215154 | G40: =SUM(G41:G44) -> 71884424
B41: Sales команда МПСтатс | C41: =[1]Гипотезы_акт!T52 -> 50425005 | E41: =[1]Гипотезы_акт!T52 -> 50425005 | G41: =[1]Гипотезы_акт!M52 -> 50425005
B42: Договор 2 (биллинг + лидген Т) | C42: =CHOOSE($L$34,C28,C31) -> 35317686 | E42: =CHOOSE($L$34,E28,E31) -> 28254149 | G42: =CHOOSE($L$34,G28,G31) -> 16923418 | H42: НДС 22% к стоимости услуг по Дог.2. Т-Банк начисляет НДС, уплачивает его в бюджет. МПСтатс оплачивают счет от нас с учетом НДС и принимают к себе в зачет эту сумму
B43: Техподдержка интеграции МПСтатс | C43: =C10 -> 360000 | E43: =E10 -> 360000 | G43: =E43 -> 360000 | H43: уточнить МПС
B44: Техподдержка пользователей МПСтатс | C44: ='[1]доп расходы_свод'!D17 -> 8352000 | E44: ='[1]доп расходы_свод'!D18 -> 4176000 | G44: =E44 -> 4176000
B46: Прибыль МПС от МПСтатс (за вычетом всех расходов) | C46: =C36-C40 -> 47276052 | E46: =E36-E40 -> 58515589 | G46: =G36-G40 -> 13192668
B47: маржинальность по проекту для МПС (прибыль/доходы) | C47: =C46/C36 -> 0.33356244 | E47: =E46/E36 -> 0.41286448 | G47: =G46/G$4 -> 0.1559102
B48: Прибыль МПС от клиентского дохода МПСтатс (за вычетом лидгена Т) | C48: =C37-C42 -> 1.0595306e+08 | E48: =E37-E42 -> 1.1301659e+08 | G48: =G37-G42 -> 67693673
B49: доля от клиентского дохода MPStats | C49: =C48/C4 -> 0.75 | E49: =E48/E4 -> 0.8 | G49: =G48/G4 -> 0.8 | H49: Комиссия Т-Банк за лидген+ биллинг/ только лидген. | I49: Открытый вопрос - получение вознаграждения за все время пока платит клиент или ограниченное время? У Точки (пример договора) - комиссия партнера за все время оплаты клиентом (без ограничений). В Т обычно 3-6 мес - за лидген. Иначе если без ограничений - нужно согласовывать налоговые риски - если услуга за все время оплаты. Если билиинг на стороне Т - то нужно получать оплату постоянно (можо выделить услугу биллинга - фикс или %)
B51: Справочно: налоги МПС
B52: НДС 22% – тех поддержка по Договору 1 | C52: =C10*22% -> 79200 | E52: =E10*22% -> 79200 | G52: =G10*22% -> 79200 | H52: валидация от МПС | I52: нужно валидировать с налоговиками?
B53: Налог на прибыль 5% (льгота для ИТ компаний) | C53: =C46*5% -> 2363802.6 | E53: =E46*5% -> 2925779.4 | G53: =G46*5% -> 659633.39 | H53: валидация от МПС
B54: Разница | C54: =C53-E53 -> -561976.86
B56: Т-Банк
B57: Доходы | C57: =SUM(C58:C59) -> 35317686 | E57: =SUM(E58:E59) -> 28254149 | G57: =SUM(G58:G59) -> 16923418
B58: Доход с клиентов (тарифы МПСтатс)
B59: Договор 2 (биллинг + лидген Т) | C59: =C42 -> 35317686 | E59: =E42 -> 28254149 | G59: =G42 -> 16923418 | H59: НДС 22% к стоимости услуг по Дог.2. Т-Банк начисляет НДС, уплачивает его в бюджет. МПСтатс оплачивают счет от нас с учетом НДС и принимают к себе в зачет эту сумму
B61: Расходы | C61: =SUM(C62:C63) -> 19808724 | E61: =SUM(E62:E63) -> 17235867 | G61: =SUM(G62:G63) -> 17566027
B62: Договор 1 (лицензия + тех поддержка МПСтатс) | C62: =C38 -> 460000 | E62: =E38 -> 460000 | G62: =G38 -> 460000
B63: Договор 2 (биллинг + лидген Т) | C63: =C25 -> 19348724 | E63: =E25 -> 16775867 | G63: =G25 -> 17106027
B65: Прибыль Т от МПСтатс | C65: =C57-C61 -> 15508962 | E65: =E57-E61 -> 11018282 | G65: =G57-G61 -> -642609.14
B66: маржинальность по проекту для Т (прибыль/доходы) | C66: =C65/C57 -> 0.43912735 | E66: =E65/E57 -> 0.3899704
B67: доля от клиентского дохода MPStats | C67: =C65/C$4 -> 0.10978184 | E67: =E65/E$4 -> 0.07799408 | G67: =G65/G$4 -> -0.0075943185
B68: доля прибыли Т к расходам | C68: =C65/C61 -> 0.78293592 | E68: =E65/E61 -> 0.63926472 | G68: =G65/G61 -> -0.036582497 | H68: мин маржинальность - 10% (требование налоговиков)
B70: Потенциальная прибыль Т по другим продуктам | C70: =[1]Гипотезы_акт!T118 -> 1.1041509e+08 | E70: =[1]Гипотезы_акт!F118 -> 1.1041509e+08 | G70: =[1]Гипотезы_акт!M118 -> 54520000
B71: Общая прибыль Т (MPStats + экосистемный эффект) | C71: =C65+C70 -> 1.2592405e+08 | E71: =E65+E70 -> 1.2143337e+08 | G71: =G65+G70 -> 53877391
B73: Справочно: налоги Т-Банк | G73: =G74+G75 -> 3562499.7 | H73: получить подтвержение от налогов Т что рассчитано верно | I73: нужно валидировать с налоговиками?
B74: НДС 22% (в доходах по Договору 2) | C74: =C59*22% -> 7769890.8 | E74: =E59*22% -> 6215912.7 | G74: =G59*22% -> 3723152 | H74: НДС 22% к стоимости услуг по Дог.2. Т-Банк начисляет НДС, уплачивает его в бюджет. МПСтатс оплачивают счет от нас с учетом НДС и принимают к себе в зачет эту сумму
B75: Налог на прибыль 25% | C75: =C65*25% -> 3877240.4 | E75: =E65*25% -> 2754570.4 | G75: =G65*25% -> -160652.29
B76: Разница | C76: =C75-E75 -> 1122670
B78: P&L Total | C78: =C3 -> Биллинг Т | E78: =E3 -> Биллинг МПС (с рекуррентами и ковенантами) | G78: =G3 -> Биллинг МПС (без рекуррентов и ковенантов)
B79: ИТОГО: МПС + Т-Банк
B80: Доходы | C80: =C81+C84 -> 1.7704843e+08 | E80: =E81+E84 -> 1.6998489e+08 | G80: =G81+G84 -> 1.0200051e+08
B81: МПС | C81: =SUM(C82:C83) -> 1.4173074e+08 | E81: =SUM(E82:E83) -> 1.4173074e+08 | G81: =SUM(G82:G83) -> 85077091
B82: Доход с клиентов (тарифы МПСтатс) | C82: =C37 -> 1.4127074e+08 | E82: =E37 -> 1.4127074e+08 | G82: =G37 -> 84617091 | H82: доход МПС
B83: Договор 1 (лицензия + тех поддержка МПСтатс) | C83: =C38 -> 460000 | E83: =E38 -> 460000 | G83: =G38 -> 460000 | H83: доход МПС, расход Т. 1) Стоимость лиценции уточняется.
B84: Т-Банк | C84: =C85 -> 35317686 | E84: =E85 -> 28254149 | G84: =G85 -> 16923418
B85: Договор 2 (биллинг + лидген Т) | C85: =C59 -> 35317686 | E85: =E59 -> 28254149 | G85: =G59 -> 16923418 | H85: доход Т-Банк, расход МПС
B87: Расходы | C87: =C88+C93 -> 1.1426341e+08 | E87: =E88+E93 -> 1.0045102e+08 | G87: =G88+G93 -> 85274451
B88: МПС | C88: =SUM(C89:C92) -> 94454691 | E88: =SUM(E89:E92) -> 83215154 | G88: =SUM(G89:G91) -> 67708424
B89: =B41 -> Sales команда МПСтатс | C89: =C41 -> 50425005 | E89: =E41 -> 50425005 | G89: =G41 -> 50425005
B90: Договор 2 (биллинг + лидген Т) | C90: =C42 -> 35317686 | E90: =E42 -> 28254149 | G90: =G42 -> 16923418 | H90: оплата Т за услуги биллинга, лидгена
B91: Техподдержка интеграции МПСтатс | C91: =C43 -> 360000 | E91: =E43 -> 360000 | G91: =G43 -> 360000
B92: Техподдержка пользователей МПСтатс | C92: =C44 -> 8352000 | E92: =E44 -> 4176000
B93: Т-Банк | C93: =SUM(C94:C95) -> 19808724 | E93: =SUM(E94:E95) -> 17235867 | G93: =SUM(G94:G95) -> 17566027
B94: Договор 1 (лицензия + тех поддержка МПСтатс) | C94: =C62 -> 460000 | E94: =E62 -> 460000 | G94: =G62 -> 460000 | H94: оплата МПС лицензии за ПО MPStats, техподдержку
B95: Договор 2 (биллинг + лидген Т) | C95: =C63 -> 19348724 | E95: =E63 -> 16775867 | G95: =G63 -> 17106027 | H95: расходы на маркетинг, разработку
B97: Прибыль общая по проекту MPStats | C97: =C80-C87 -> 62785013 | E97: =E80-E87 -> 69533870 | G97: =G80-G87 -> 16726059
B98: маржинальность по проекту (прибыль/доходы) | C98: =C97/C80 -> 0.35462056 | E98: =E97/E80 -> 0.40905912
B99: прибыль MPStats | C99: =C81-C88 -> 47276052 | E99: =E81-E88 -> 58515589
B100: прибыль Т-Банк от проекта MPStats | C100: =C84-C93 -> 15508962 | E100: =E84-E93 -> 11018282
B101: потенциальная прибыль Т-Банк от других продуктов | C101: =C70 -> 1.1041509e+08 | E101: =E70 -> 1.1041509e+08 | H101: экосистемный эффект
B102: общая прибыль + экосистемный эффект Т | C102: =SUM(C99:C101) -> 1.732001e+08 | E102: =SUM(E99:E101) -> 1.7994896e+08
B103: Разница по проекту MPStats | C103: =(C102-E102)/E102 -> -0.037504285
C105: =C78 -> Биллинг Т | E105: =E78 -> Биллинг МПС (с рекуррентами и ковенантами)
B106: Распределение клиентского дохода MPStats | C106: =C82 -> 1.4127074e+08 | E106: =E82 -> 1.4127074e+08 | F106: =F82 -> 0 | G106: =G82 -> 84617091 | H106: фиксируется в Договоре 2
B107: МПС доход по тарифам MPStats | C107: =C106-C109 -> 1.0595306e+08 | E107: =E106-E109 -> 1.1301659e+08
B108: доля МПС | C108: =C107/C$106 -> 0.75 | E108: =E107/E$106 -> 0.8
B109: Т-Банк (Договор 2: биллинг + лидген) | C109: =C85 -> 35317686 | E109: =E85 -> 28254149
B110: доля Т-Банк | C110: =C109/C$106 -> 0.25 | E110: =E109/E$106 -> 0.2
B112: Справочно: налоги Т-Банк + МПС
B113: НДС в доходах (22%) | H113: подлежит вычету в расходах у другой стороны
B114: Договор 1 (техподдержка) - МПС | C114: =C52 -> 79200 | E114: =E52 -> 79200 | H114: услуги техподдержки облагаются НДС, лицензия нет
B115: Договор 2 (биллинг + лидген) - Т-Банк | C115: =C74 -> 7769890.8 | E115: =E74 -> 6215912.7
B116: Налог на прибыль | C116: =SUM(C117:C118) -> 6241043 | E116: =SUM(E117:E118) -> 5680349.8 | G116: =G73+G51 -> 3562499.7
...

Sheet Юля_ИТОГ_new v3
H1: Комментарии | I1: Что сделать
C2: Вариант 1 | E2: Вариант 2.1 | G2: Вариант 2.2
C3: Биллинг Т | E3: Биллинг МПС (с рекуррентами и ковенантами) | G3: Биллинг МПС (без рекуррентов и ковенантов)
A4: Доходы: Тарифы MPStats оплачены клиентами | B4: Клиентский доход (тарифы МПСтатс) | C4: =Воронка!#REF! -> #REF! | E4: =Воронка!#REF! -> #REF! | G4: =Воронка!#REF! -> #REF!
B6: Расходы Т-Банк
B7: Договор 1 (лицензия + техподдержка ПО МПСтатс)
B8: услуги по договору | C8: лицензия + техподдержка | E8: лицензия + техподдержка | G8: лицензия + техподдержка
A9: Договор 1 (лицензия и тех поддержка со стороны МПСтатс) | B9: Лицензия на ПО MPStats (единоразово) | C9: 100000 | E9: =C9 -> 100000 | G9: =Воронка!#REF! -> #REF! | H9: Заложили минимально 100 000 р, можем увеличить - провалидировать (налоги). Необходимо обоснование.
A10: Лицензия на ПО MPStats -- какая минимально возможная? (единоразово бессрочно) | B10: Тех. поддержка ПО MPStats (в год) | C10: ='доп расходы_свод'!C17 -> 360000 | E10: =C10 -> 360000 | G10: =E10 -> 360000 | H10: по расчету МПС
A11: Тех. поддержка интеграции в целом от MPStats (в год) | B11: ИТОГО по Договору 1 | C11: =C9+C10 -> 460000 | E11: =E9+E10 -> 460000 | G11: =G9+G10 -> #REF! | H11: Доход для МПС, расход для Т
B12: доля от клиентского дохода MPStats | C12: =C11/C$4 -> #REF! | E12: =E11/E$4 -> #REF! | G12: =G11/G$4 -> #REF!
B13: Договор 2 (биллинг + лидген)
B14: услуги по договору | C14: биллинг + техподдержка + лидогенерация Т | E14: лидогенерация + техподдержка Т | G14: лидогенерация + техподдержка Т
